package e.d.c.x.h;

import e.d.b.o;
import e.d.c.x.i.l;

public class m extends i<m.a> {
  public m(o paramo, a parama) {
    super(paramo, parama);
  }
  
  a a(o paramo) {
    return new a(this, paramo);
  }
  
  public void a(l paraml) {
    // Byte code:
    //   0: aload_0
    //   1: getfield d : Ljava/util/ArrayList;
    //   4: astore #5
    //   6: iconst_0
    //   7: istore #4
    //   9: aload #5
    //   11: iconst_0
    //   12: invokevirtual get : (I)Ljava/lang/Object;
    //   15: checkcast e/d/c/x/h/m$a
    //   18: astore #6
    //   20: aload #6
    //   22: getfield b : I
    //   25: iconst_2
    //   26: iand
    //   27: iconst_2
    //   28: if_icmpne -> 36
    //   31: iconst_1
    //   32: istore_3
    //   33: goto -> 38
    //   36: iconst_0
    //   37: istore_3
    //   38: aload_1
    //   39: iconst_1
    //   40: iload_3
    //   41: invokevirtual a : (IZ)V
    //   44: aload #6
    //   46: getfield b : I
    //   49: bipush #8
    //   51: iand
    //   52: bipush #8
    //   54: if_icmpne -> 62
    //   57: iconst_1
    //   58: istore_3
    //   59: goto -> 64
    //   62: iconst_0
    //   63: istore_3
    //   64: aload_1
    //   65: iconst_2
    //   66: iload_3
    //   67: invokevirtual a : (IZ)V
    //   70: aload #6
    //   72: getfield b : I
    //   75: bipush #32
    //   77: iand
    //   78: bipush #32
    //   80: if_icmpne -> 88
    //   83: iconst_1
    //   84: istore_3
    //   85: goto -> 90
    //   88: iconst_0
    //   89: istore_3
    //   90: aload_1
    //   91: iconst_3
    //   92: iload_3
    //   93: invokevirtual a : (IZ)V
    //   96: aload #6
    //   98: getfield b : I
    //   101: bipush #64
    //   103: iand
    //   104: bipush #64
    //   106: if_icmpne -> 114
    //   109: iconst_1
    //   110: istore_3
    //   111: goto -> 116
    //   114: iconst_0
    //   115: istore_3
    //   116: aload_1
    //   117: iconst_4
    //   118: iload_3
    //   119: invokevirtual a : (IZ)V
    //   122: aload #6
    //   124: getfield b : I
    //   127: sipush #128
    //   130: iand
    //   131: sipush #128
    //   134: if_icmpne -> 144
    //   137: ldc 'Horizontal'
    //   139: astore #5
    //   141: goto -> 148
    //   144: ldc 'Vertical'
    //   146: astore #5
    //   148: aload_1
    //   149: iconst_5
    //   150: aload #5
    //   152: invokevirtual a : (ILjava/lang/String;)V
    //   155: aload #6
    //   157: getfield b : I
    //   160: sipush #256
    //   163: iand
    //   164: sipush #256
    //   167: if_icmpne -> 177
    //   170: ldc 'Reverse'
    //   172: astore #5
    //   174: goto -> 181
    //   177: ldc 'Normal'
    //   179: astore #5
    //   181: aload_1
    //   182: bipush #6
    //   184: aload #5
    //   186: invokevirtual a : (ILjava/lang/String;)V
    //   189: aload #6
    //   191: getfield b : I
    //   194: sipush #512
    //   197: iand
    //   198: sipush #512
    //   201: if_icmpne -> 209
    //   204: iconst_1
    //   205: istore_3
    //   206: goto -> 211
    //   209: iconst_0
    //   210: istore_3
    //   211: aload_1
    //   212: bipush #7
    //   214: iload_3
    //   215: invokevirtual a : (IZ)V
    //   218: aload #6
    //   220: getfield b : I
    //   223: sipush #4096
    //   226: iand
    //   227: sipush #4096
    //   230: if_icmpne -> 238
    //   233: iconst_1
    //   234: istore_3
    //   235: goto -> 240
    //   238: iconst_0
    //   239: istore_3
    //   240: aload_1
    //   241: bipush #8
    //   243: iload_3
    //   244: invokevirtual a : (IZ)V
    //   247: aload #6
    //   249: getfield b : I
    //   252: sipush #8192
    //   255: iand
    //   256: sipush #8192
    //   259: if_icmpne -> 267
    //   262: iconst_1
    //   263: istore_3
    //   264: goto -> 269
    //   267: iconst_0
    //   268: istore_3
    //   269: aload_1
    //   270: bipush #9
    //   272: iload_3
    //   273: invokevirtual a : (IZ)V
    //   276: iload #4
    //   278: istore_3
    //   279: aload #6
    //   281: getfield b : I
    //   284: sipush #16384
    //   287: iand
    //   288: sipush #16384
    //   291: if_icmpne -> 296
    //   294: iconst_1
    //   295: istore_3
    //   296: aload_1
    //   297: bipush #10
    //   299: iload_3
    //   300: invokevirtual a : (IZ)V
    //   303: aload #6
    //   305: getfield c : I
    //   308: istore_2
    //   309: iload_2
    //   310: iconst_m1
    //   311: if_icmpeq -> 340
    //   314: iload_2
    //   315: ifeq -> 333
    //   318: iload_2
    //   319: iconst_1
    //   320: if_icmpeq -> 326
    //   323: goto -> 352
    //   326: ldc 'Center'
    //   328: astore #5
    //   330: goto -> 344
    //   333: ldc 'Left'
    //   335: astore #5
    //   337: goto -> 344
    //   340: ldc 'Right'
    //   342: astore #5
    //   344: aload_1
    //   345: bipush #11
    //   347: aload #5
    //   349: invokevirtual a : (ILjava/lang/String;)V
    //   352: aload_1
    //   353: bipush #12
    //   355: aload #6
    //   357: getfield d : [I
    //   360: invokevirtual a : (I[I)V
    //   363: aload_1
    //   364: bipush #13
    //   366: aload #6
    //   368: getfield e : J
    //   371: invokevirtual a : (IJ)V
    //   374: aload_1
    //   375: bipush #14
    //   377: aload #6
    //   379: getfield f : I
    //   382: invokevirtual a : (II)V
    //   385: aload #6
    //   387: getfield g : I
    //   390: istore_2
    //   391: iload_2
    //   392: iconst_1
    //   393: if_icmpeq -> 475
    //   396: iload_2
    //   397: iconst_2
    //   398: if_icmpeq -> 468
    //   401: iload_2
    //   402: iconst_4
    //   403: if_icmpeq -> 461
    //   406: iload_2
    //   407: bipush #8
    //   409: if_icmpeq -> 454
    //   412: iload_2
    //   413: bipush #16
    //   415: if_icmpeq -> 447
    //   418: iload_2
    //   419: bipush #32
    //   421: if_icmpeq -> 440
    //   424: iload_2
    //   425: bipush #64
    //   427: if_icmpeq -> 433
    //   430: goto -> 487
    //   433: ldc 'Extend'
    //   435: astore #5
    //   437: goto -> 479
    //   440: ldc 'Condense'
    //   442: astore #5
    //   444: goto -> 479
    //   447: ldc 'Shadow'
    //   449: astore #5
    //   451: goto -> 479
    //   454: ldc 'Outline'
    //   456: astore #5
    //   458: goto -> 479
    //   461: ldc 'Underline'
    //   463: astore #5
    //   465: goto -> 479
    //   468: ldc 'Italic'
    //   470: astore #5
    //   472: goto -> 479
    //   475: ldc 'Bold'
    //   477: astore #5
    //   479: aload_1
    //   480: bipush #15
    //   482: aload #5
    //   484: invokevirtual a : (ILjava/lang/String;)V
    //   487: aload_1
    //   488: bipush #16
    //   490: aload #6
    //   492: getfield h : [I
    //   495: invokevirtual a : (I[I)V
    //   498: aload_1
    //   499: bipush #17
    //   501: aload #6
    //   503: getfield i : Ljava/lang/String;
    //   506: invokevirtual a : (ILjava/lang/String;)V
    //   509: return
  }
  
  class a extends h {
    int b;
    
    int c;
    
    int[] d;
    
    long e;
    
    int f;
    
    int g;
    
    int[] h;
    
    String i;
    
    public a(m this$0, o param1o) {
      super(param1o);
      this.b = param1o.d();
      this.c = param1o.d();
      this.d = new int[] { param1o.h(), param1o.h(), param1o.h() };
      this.e = param1o.e();
      param1o.a(8L);
      this.f = param1o.h();
      this.g = param1o.h();
      param1o.a(1L);
      param1o.a(2L);
      this.h = new int[] { param1o.h(), param1o.h(), param1o.h() };
      this.i = param1o.c(param1o.j());
    }
  }
}


/* Location:              /home/yc/Downloads/LeaveHomeSafe.jar!/e/d/c/x/h/m.class
 * Java compiler version: 6 (50.0)
 * JD-Core Version:       1.1.3
 */