package e.e.l.d;

import android.os.SystemClock;
import e.e.e.d.i;
import e.e.e.d.j;
import e.e.e.d.l;
import e.e.e.g.b;
import java.util.ArrayList;
import java.util.Iterator;
import java.util.WeakHashMap;

public class h<K, V> implements p<K, V>, b {
  final g<K, d<K, V>> a;
  
  final g<K, d<K, V>> b;
  
  private final v<V> c;
  
  private final l<q> d;
  
  protected q e;
  
  private long f;
  
  public h(v<V> paramv, c paramc, l<q> paraml) {
    new WeakHashMap<Object, Object>();
    this.c = paramv;
    this.a = new g<K, d<K, V>>(a(paramv));
    this.b = new g<K, d<K, V>>(a(paramv));
    this.d = paraml;
    this.e = (q)this.d.get();
    this.f = SystemClock.uptimeMillis();
  }
  
  private v<d<K, V>> a(v<V> paramv) {
    return new a(this, paramv);
  }
  
  private ArrayList<d<K, V>> a(int paramInt1, int paramInt2) {
    // Byte code:
    //   0: aload_0
    //   1: monitorenter
    //   2: iload_1
    //   3: iconst_0
    //   4: invokestatic max : (II)I
    //   7: istore_1
    //   8: iload_2
    //   9: iconst_0
    //   10: invokestatic max : (II)I
    //   13: istore_2
    //   14: aload_0
    //   15: getfield a : Le/e/l/d/g;
    //   18: invokevirtual a : ()I
    //   21: iload_1
    //   22: if_icmpgt -> 42
    //   25: aload_0
    //   26: getfield a : Le/e/l/d/g;
    //   29: invokevirtual c : ()I
    //   32: istore_3
    //   33: iload_3
    //   34: iload_2
    //   35: if_icmpgt -> 42
    //   38: aload_0
    //   39: monitorexit
    //   40: aconst_null
    //   41: areturn
    //   42: new java/util/ArrayList
    //   45: dup
    //   46: invokespecial <init> : ()V
    //   49: astore #4
    //   51: aload_0
    //   52: getfield a : Le/e/l/d/g;
    //   55: invokevirtual a : ()I
    //   58: iload_1
    //   59: if_icmpgt -> 83
    //   62: aload_0
    //   63: getfield a : Le/e/l/d/g;
    //   66: invokevirtual c : ()I
    //   69: istore_3
    //   70: iload_3
    //   71: iload_2
    //   72: if_icmple -> 78
    //   75: goto -> 83
    //   78: aload_0
    //   79: monitorexit
    //   80: aload #4
    //   82: areturn
    //   83: aload_0
    //   84: getfield a : Le/e/l/d/g;
    //   87: invokevirtual b : ()Ljava/lang/Object;
    //   90: astore #5
    //   92: aload_0
    //   93: getfield a : Le/e/l/d/g;
    //   96: aload #5
    //   98: invokevirtual b : (Ljava/lang/Object;)Ljava/lang/Object;
    //   101: pop
    //   102: aload #4
    //   104: aload_0
    //   105: getfield b : Le/e/l/d/g;
    //   108: aload #5
    //   110: invokevirtual b : (Ljava/lang/Object;)Ljava/lang/Object;
    //   113: invokevirtual add : (Ljava/lang/Object;)Z
    //   116: pop
    //   117: goto -> 51
    //   120: astore #4
    //   122: aload_0
    //   123: monitorexit
    //   124: goto -> 130
    //   127: aload #4
    //   129: athrow
    //   130: goto -> 127
    // Exception table:
    //   from	to	target	type
    //   2	33	120	finally
    //   42	51	120	finally
    //   51	70	120	finally
    //   83	117	120	finally
  }
  
  private void a(d<K, V> paramd) {
    // Byte code:
    //   0: aload_0
    //   1: monitorenter
    //   2: aload_1
    //   3: invokestatic a : (Ljava/lang/Object;)Ljava/lang/Object;
    //   6: pop
    //   7: aload_1
    //   8: getfield c : I
    //   11: ifle -> 41
    //   14: iconst_1
    //   15: istore_2
    //   16: goto -> 19
    //   19: iload_2
    //   20: invokestatic b : (Z)V
    //   23: aload_1
    //   24: aload_1
    //   25: getfield c : I
    //   28: iconst_1
    //   29: isub
    //   30: putfield c : I
    //   33: aload_0
    //   34: monitorexit
    //   35: return
    //   36: astore_1
    //   37: aload_0
    //   38: monitorexit
    //   39: aload_1
    //   40: athrow
    //   41: iconst_0
    //   42: istore_2
    //   43: goto -> 19
    // Exception table:
    //   from	to	target	type
    //   2	14	36	finally
    //   19	33	36	finally
  }
  
  private void a(ArrayList<d<K, V>> paramArrayList) {
    // Byte code:
    //   0: aload_0
    //   1: monitorenter
    //   2: aload_1
    //   3: ifnull -> 41
    //   6: aload_1
    //   7: invokevirtual iterator : ()Ljava/util/Iterator;
    //   10: astore_1
    //   11: aload_1
    //   12: invokeinterface hasNext : ()Z
    //   17: ifeq -> 41
    //   20: aload_0
    //   21: aload_1
    //   22: invokeinterface next : ()Ljava/lang/Object;
    //   27: checkcast e/e/l/d/h$d
    //   30: invokespecial c : (Le/e/l/d/h$d;)V
    //   33: goto -> 11
    //   36: astore_1
    //   37: aload_0
    //   38: monitorexit
    //   39: aload_1
    //   40: athrow
    //   41: aload_0
    //   42: monitorexit
    //   43: return
    // Exception table:
    //   from	to	target	type
    //   6	11	36	finally
    //   11	33	36	finally
  }
  
  private void b(d<K, V> paramd) {
    // Byte code:
    //   0: aload_0
    //   1: monitorenter
    //   2: aload_1
    //   3: invokestatic a : (Ljava/lang/Object;)Ljava/lang/Object;
    //   6: pop
    //   7: aload_1
    //   8: getfield d : Z
    //   11: ifne -> 41
    //   14: iconst_1
    //   15: istore_2
    //   16: goto -> 19
    //   19: iload_2
    //   20: invokestatic b : (Z)V
    //   23: aload_1
    //   24: aload_1
    //   25: getfield c : I
    //   28: iconst_1
    //   29: iadd
    //   30: putfield c : I
    //   33: aload_0
    //   34: monitorexit
    //   35: return
    //   36: astore_1
    //   37: aload_0
    //   38: monitorexit
    //   39: aload_1
    //   40: athrow
    //   41: iconst_0
    //   42: istore_2
    //   43: goto -> 19
    // Exception table:
    //   from	to	target	type
    //   2	14	36	finally
    //   19	33	36	finally
  }
  
  private void b(ArrayList<d<K, V>> paramArrayList) {
    if (paramArrayList != null) {
      Iterator<d<K, V>> iterator = paramArrayList.iterator();
      while (iterator.hasNext())
        e.e.e.h.a.b(h(iterator.next())); 
    } 
  }
  
  private boolean b(V paramV) {
    // Byte code:
    //   0: aload_0
    //   1: monitorenter
    //   2: aload_0
    //   3: getfield c : Le/e/l/d/v;
    //   6: aload_1
    //   7: invokeinterface a : (Ljava/lang/Object;)I
    //   12: istore_2
    //   13: aload_0
    //   14: getfield e : Le/e/l/d/q;
    //   17: getfield e : I
    //   20: istore_3
    //   21: iconst_1
    //   22: istore #5
    //   24: iload_2
    //   25: iload_3
    //   26: if_icmpgt -> 70
    //   29: aload_0
    //   30: invokevirtual a : ()I
    //   33: aload_0
    //   34: getfield e : Le/e/l/d/q;
    //   37: getfield b : I
    //   40: iconst_1
    //   41: isub
    //   42: if_icmpgt -> 70
    //   45: aload_0
    //   46: invokevirtual b : ()I
    //   49: istore_3
    //   50: aload_0
    //   51: getfield e : Le/e/l/d/q;
    //   54: getfield a : I
    //   57: istore #4
    //   59: iload_3
    //   60: iload #4
    //   62: iload_2
    //   63: isub
    //   64: if_icmpgt -> 70
    //   67: goto -> 73
    //   70: iconst_0
    //   71: istore #5
    //   73: aload_0
    //   74: monitorexit
    //   75: iload #5
    //   77: ireturn
    //   78: astore_1
    //   79: aload_0
    //   80: monitorexit
    //   81: aload_1
    //   82: athrow
    // Exception table:
    //   from	to	target	type
    //   2	21	78	finally
    //   29	59	78	finally
  }
  
  private void c() {
    // Byte code:
    //   0: aload_0
    //   1: monitorenter
    //   2: aload_0
    //   3: aload_0
    //   4: getfield e : Le/e/l/d/q;
    //   7: getfield d : I
    //   10: aload_0
    //   11: getfield e : Le/e/l/d/q;
    //   14: getfield b : I
    //   17: aload_0
    //   18: invokevirtual a : ()I
    //   21: isub
    //   22: invokestatic min : (II)I
    //   25: aload_0
    //   26: getfield e : Le/e/l/d/q;
    //   29: getfield c : I
    //   32: aload_0
    //   33: getfield e : Le/e/l/d/q;
    //   36: getfield a : I
    //   39: aload_0
    //   40: invokevirtual b : ()I
    //   43: isub
    //   44: invokestatic min : (II)I
    //   47: invokespecial a : (II)Ljava/util/ArrayList;
    //   50: astore_1
    //   51: aload_0
    //   52: aload_1
    //   53: invokespecial a : (Ljava/util/ArrayList;)V
    //   56: aload_0
    //   57: monitorexit
    //   58: aload_0
    //   59: aload_1
    //   60: invokespecial b : (Ljava/util/ArrayList;)V
    //   63: aload_0
    //   64: aload_1
    //   65: invokespecial c : (Ljava/util/ArrayList;)V
    //   68: return
    //   69: astore_1
    //   70: aload_0
    //   71: monitorexit
    //   72: aload_1
    //   73: athrow
    // Exception table:
    //   from	to	target	type
    //   2	58	69	finally
    //   70	72	69	finally
  }
  
  private void c(d<K, V> paramd) {
    // Byte code:
    //   0: aload_0
    //   1: monitorenter
    //   2: aload_1
    //   3: invokestatic a : (Ljava/lang/Object;)Ljava/lang/Object;
    //   6: pop
    //   7: aload_1
    //   8: getfield d : Z
    //   11: ifne -> 36
    //   14: iconst_1
    //   15: istore_2
    //   16: goto -> 19
    //   19: iload_2
    //   20: invokestatic b : (Z)V
    //   23: aload_1
    //   24: iconst_1
    //   25: putfield d : Z
    //   28: aload_0
    //   29: monitorexit
    //   30: return
    //   31: astore_1
    //   32: aload_0
    //   33: monitorexit
    //   34: aload_1
    //   35: athrow
    //   36: iconst_0
    //   37: istore_2
    //   38: goto -> 19
    // Exception table:
    //   from	to	target	type
    //   2	14	31	finally
    //   19	28	31	finally
  }
  
  private void c(ArrayList<d<K, V>> paramArrayList) {
    if (paramArrayList != null) {
      Iterator<d<K, V>> iterator = paramArrayList.iterator();
      while (iterator.hasNext())
        f(iterator.next()); 
    } 
  }
  
  private void d() {
    // Byte code:
    //   0: aload_0
    //   1: monitorenter
    //   2: aload_0
    //   3: getfield f : J
    //   6: lstore_1
    //   7: aload_0
    //   8: getfield e : Le/e/l/d/q;
    //   11: getfield f : J
    //   14: lstore_3
    //   15: invokestatic uptimeMillis : ()J
    //   18: lstore #5
    //   20: lload_1
    //   21: lload_3
    //   22: ladd
    //   23: lload #5
    //   25: lcmp
    //   26: ifle -> 32
    //   29: aload_0
    //   30: monitorexit
    //   31: return
    //   32: aload_0
    //   33: invokestatic uptimeMillis : ()J
    //   36: putfield f : J
    //   39: aload_0
    //   40: aload_0
    //   41: getfield d : Le/e/e/d/l;
    //   44: invokeinterface get : ()Ljava/lang/Object;
    //   49: checkcast e/e/l/d/q
    //   52: putfield e : Le/e/l/d/q;
    //   55: aload_0
    //   56: monitorexit
    //   57: return
    //   58: astore #7
    //   60: aload_0
    //   61: monitorexit
    //   62: aload #7
    //   64: athrow
    // Exception table:
    //   from	to	target	type
    //   2	20	58	finally
    //   32	55	58	finally
  }
  
  private boolean d(d<K, V> paramd) {
    // Byte code:
    //   0: aload_0
    //   1: monitorenter
    //   2: aload_1
    //   3: getfield d : Z
    //   6: ifne -> 35
    //   9: aload_1
    //   10: getfield c : I
    //   13: ifne -> 35
    //   16: aload_0
    //   17: getfield a : Le/e/l/d/g;
    //   20: aload_1
    //   21: getfield a : Ljava/lang/Object;
    //   24: aload_1
    //   25: invokevirtual a : (Ljava/lang/Object;Ljava/lang/Object;)Ljava/lang/Object;
    //   28: pop
    //   29: iconst_1
    //   30: istore_2
    //   31: aload_0
    //   32: monitorexit
    //   33: iload_2
    //   34: ireturn
    //   35: iconst_0
    //   36: istore_2
    //   37: goto -> 31
    //   40: astore_1
    //   41: aload_0
    //   42: monitorexit
    //   43: goto -> 48
    //   46: aload_1
    //   47: athrow
    //   48: goto -> 46
    // Exception table:
    //   from	to	target	type
    //   2	29	40	finally
  }
  
  private static <K, V> void e(d<K, V> paramd) {
    if (paramd != null) {
      e<K> e = paramd.e;
      if (e != null)
        e.a(paramd.a, true); 
    } 
  }
  
  private static <K, V> void f(d<K, V> paramd) {
    if (paramd != null) {
      e<K> e = paramd.e;
      if (e != null)
        e.a(paramd.a, false); 
    } 
  }
  
  private e.e.e.h.a<V> g(d<K, V> paramd) {
    // Byte code:
    //   0: aload_0
    //   1: monitorenter
    //   2: aload_0
    //   3: aload_1
    //   4: invokespecial b : (Le/e/l/d/h$d;)V
    //   7: aload_1
    //   8: getfield b : Le/e/e/h/a;
    //   11: invokevirtual b : ()Ljava/lang/Object;
    //   14: new e/e/l/d/h$b
    //   17: dup
    //   18: aload_0
    //   19: aload_1
    //   20: invokespecial <init> : (Le/e/l/d/h;Le/e/l/d/h$d;)V
    //   23: invokestatic a : (Ljava/lang/Object;Le/e/e/h/c;)Le/e/e/h/a;
    //   26: astore_1
    //   27: aload_0
    //   28: monitorexit
    //   29: aload_1
    //   30: areturn
    //   31: astore_1
    //   32: aload_0
    //   33: monitorexit
    //   34: aload_1
    //   35: athrow
    // Exception table:
    //   from	to	target	type
    //   2	27	31	finally
  }
  
  private e.e.e.h.a<V> h(d<K, V> paramd) {
    // Byte code:
    //   0: aload_0
    //   1: monitorenter
    //   2: aload_1
    //   3: invokestatic a : (Ljava/lang/Object;)Ljava/lang/Object;
    //   6: pop
    //   7: aload_1
    //   8: getfield d : Z
    //   11: ifeq -> 29
    //   14: aload_1
    //   15: getfield c : I
    //   18: ifne -> 29
    //   21: aload_1
    //   22: getfield b : Le/e/e/h/a;
    //   25: astore_1
    //   26: goto -> 31
    //   29: aconst_null
    //   30: astore_1
    //   31: aload_0
    //   32: monitorexit
    //   33: aload_1
    //   34: areturn
    //   35: astore_1
    //   36: aload_0
    //   37: monitorexit
    //   38: aload_1
    //   39: athrow
    // Exception table:
    //   from	to	target	type
    //   2	26	35	finally
  }
  
  private void i(d<K, V> paramd) {
    // Byte code:
    //   0: aload_1
    //   1: invokestatic a : (Ljava/lang/Object;)Ljava/lang/Object;
    //   4: pop
    //   5: aload_0
    //   6: monitorenter
    //   7: aload_0
    //   8: aload_1
    //   9: invokespecial a : (Le/e/l/d/h$d;)V
    //   12: aload_0
    //   13: aload_1
    //   14: invokespecial d : (Le/e/l/d/h$d;)Z
    //   17: istore_2
    //   18: aload_0
    //   19: aload_1
    //   20: invokespecial h : (Le/e/l/d/h$d;)Le/e/e/h/a;
    //   23: astore_3
    //   24: aload_0
    //   25: monitorexit
    //   26: aload_3
    //   27: invokestatic b : (Le/e/e/h/a;)V
    //   30: iload_2
    //   31: ifeq -> 37
    //   34: goto -> 39
    //   37: aconst_null
    //   38: astore_1
    //   39: aload_1
    //   40: invokestatic e : (Le/e/l/d/h$d;)V
    //   43: aload_0
    //   44: invokespecial d : ()V
    //   47: aload_0
    //   48: invokespecial c : ()V
    //   51: return
    //   52: astore_1
    //   53: aload_0
    //   54: monitorexit
    //   55: aload_1
    //   56: athrow
    // Exception table:
    //   from	to	target	type
    //   7	26	52	finally
    //   53	55	52	finally
  }
  
  public int a() {
    // Byte code:
    //   0: aload_0
    //   1: monitorenter
    //   2: aload_0
    //   3: getfield b : Le/e/l/d/g;
    //   6: invokevirtual a : ()I
    //   9: istore_1
    //   10: aload_0
    //   11: getfield a : Le/e/l/d/g;
    //   14: invokevirtual a : ()I
    //   17: istore_2
    //   18: aload_0
    //   19: monitorexit
    //   20: iload_1
    //   21: iload_2
    //   22: isub
    //   23: ireturn
    //   24: astore_3
    //   25: aload_0
    //   26: monitorexit
    //   27: aload_3
    //   28: athrow
    // Exception table:
    //   from	to	target	type
    //   2	18	24	finally
  }
  
  public int a(j<K> paramj) {
    // Byte code:
    //   0: aload_0
    //   1: monitorenter
    //   2: aload_0
    //   3: getfield a : Le/e/l/d/g;
    //   6: aload_1
    //   7: invokevirtual b : (Le/e/e/d/j;)Ljava/util/ArrayList;
    //   10: astore_2
    //   11: aload_0
    //   12: getfield b : Le/e/l/d/g;
    //   15: aload_1
    //   16: invokevirtual b : (Le/e/e/d/j;)Ljava/util/ArrayList;
    //   19: astore_1
    //   20: aload_0
    //   21: aload_1
    //   22: invokespecial a : (Ljava/util/ArrayList;)V
    //   25: aload_0
    //   26: monitorexit
    //   27: aload_0
    //   28: aload_1
    //   29: invokespecial b : (Ljava/util/ArrayList;)V
    //   32: aload_0
    //   33: aload_2
    //   34: invokespecial c : (Ljava/util/ArrayList;)V
    //   37: aload_0
    //   38: invokespecial d : ()V
    //   41: aload_0
    //   42: invokespecial c : ()V
    //   45: aload_1
    //   46: invokevirtual size : ()I
    //   49: ireturn
    //   50: astore_1
    //   51: aload_0
    //   52: monitorexit
    //   53: aload_1
    //   54: athrow
    // Exception table:
    //   from	to	target	type
    //   2	27	50	finally
    //   51	53	50	finally
  }
  
  public e.e.e.h.a<V> a(K paramK, e.e.e.h.a<V> parama) {
    return a(paramK, parama, null);
  }
  
  public e.e.e.h.a<V> a(K paramK, e.e.e.h.a<V> parama, e<K> parame) {
    // Byte code:
    //   0: aload_1
    //   1: invokestatic a : (Ljava/lang/Object;)Ljava/lang/Object;
    //   4: pop
    //   5: aload_2
    //   6: invokestatic a : (Ljava/lang/Object;)Ljava/lang/Object;
    //   9: pop
    //   10: aload_0
    //   11: invokespecial d : ()V
    //   14: aload_0
    //   15: monitorenter
    //   16: aload_0
    //   17: getfield a : Le/e/l/d/g;
    //   20: aload_1
    //   21: invokevirtual b : (Ljava/lang/Object;)Ljava/lang/Object;
    //   24: checkcast e/e/l/d/h$d
    //   27: astore #6
    //   29: aload_0
    //   30: getfield b : Le/e/l/d/g;
    //   33: aload_1
    //   34: invokevirtual b : (Ljava/lang/Object;)Ljava/lang/Object;
    //   37: checkcast e/e/l/d/h$d
    //   40: astore #4
    //   42: aconst_null
    //   43: astore #5
    //   45: aload #4
    //   47: ifnull -> 126
    //   50: aload_0
    //   51: aload #4
    //   53: invokespecial c : (Le/e/l/d/h$d;)V
    //   56: aload_0
    //   57: aload #4
    //   59: invokespecial h : (Le/e/l/d/h$d;)Le/e/e/h/a;
    //   62: astore #4
    //   64: goto -> 67
    //   67: aload_0
    //   68: aload_2
    //   69: invokevirtual b : ()Ljava/lang/Object;
    //   72: invokespecial b : (Ljava/lang/Object;)Z
    //   75: ifeq -> 102
    //   78: aload_1
    //   79: aload_2
    //   80: aload_3
    //   81: invokestatic a : (Ljava/lang/Object;Le/e/e/h/a;Le/e/l/d/h$e;)Le/e/l/d/h$d;
    //   84: astore_2
    //   85: aload_0
    //   86: getfield b : Le/e/l/d/g;
    //   89: aload_1
    //   90: aload_2
    //   91: invokevirtual a : (Ljava/lang/Object;Ljava/lang/Object;)Ljava/lang/Object;
    //   94: pop
    //   95: aload_0
    //   96: aload_2
    //   97: invokespecial g : (Le/e/l/d/h$d;)Le/e/e/h/a;
    //   100: astore #5
    //   102: aload_0
    //   103: monitorexit
    //   104: aload #4
    //   106: invokestatic b : (Le/e/e/h/a;)V
    //   109: aload #6
    //   111: invokestatic f : (Le/e/l/d/h$d;)V
    //   114: aload_0
    //   115: invokespecial c : ()V
    //   118: aload #5
    //   120: areturn
    //   121: astore_1
    //   122: aload_0
    //   123: monitorexit
    //   124: aload_1
    //   125: athrow
    //   126: aconst_null
    //   127: astore #4
    //   129: goto -> 67
    // Exception table:
    //   from	to	target	type
    //   16	42	121	finally
    //   50	64	121	finally
    //   67	102	121	finally
    //   102	104	121	finally
    //   122	124	121	finally
  }
  
  public int b() {
    // Byte code:
    //   0: aload_0
    //   1: monitorenter
    //   2: aload_0
    //   3: getfield b : Le/e/l/d/g;
    //   6: invokevirtual c : ()I
    //   9: istore_1
    //   10: aload_0
    //   11: getfield a : Le/e/l/d/g;
    //   14: invokevirtual c : ()I
    //   17: istore_2
    //   18: aload_0
    //   19: monitorexit
    //   20: iload_1
    //   21: iload_2
    //   22: isub
    //   23: ireturn
    //   24: astore_3
    //   25: aload_0
    //   26: monitorexit
    //   27: aload_3
    //   28: athrow
    // Exception table:
    //   from	to	target	type
    //   2	18	24	finally
  }
  
  public boolean b(j<K> paramj) {
    // Byte code:
    //   0: aload_0
    //   1: monitorenter
    //   2: aload_0
    //   3: getfield b : Le/e/l/d/g;
    //   6: aload_1
    //   7: invokevirtual a : (Le/e/e/d/j;)Ljava/util/ArrayList;
    //   10: invokevirtual isEmpty : ()Z
    //   13: istore_2
    //   14: aload_0
    //   15: monitorexit
    //   16: iload_2
    //   17: iconst_1
    //   18: ixor
    //   19: ireturn
    //   20: astore_1
    //   21: aload_0
    //   22: monitorexit
    //   23: aload_1
    //   24: athrow
    // Exception table:
    //   from	to	target	type
    //   2	14	20	finally
  }
  
  public e.e.e.h.a<V> get(K paramK) {
    // Byte code:
    //   0: aload_1
    //   1: invokestatic a : (Ljava/lang/Object;)Ljava/lang/Object;
    //   4: pop
    //   5: aload_0
    //   6: monitorenter
    //   7: aload_0
    //   8: getfield a : Le/e/l/d/g;
    //   11: aload_1
    //   12: invokevirtual b : (Ljava/lang/Object;)Ljava/lang/Object;
    //   15: checkcast e/e/l/d/h$d
    //   18: astore_2
    //   19: aload_0
    //   20: getfield b : Le/e/l/d/g;
    //   23: aload_1
    //   24: invokevirtual a : (Ljava/lang/Object;)Ljava/lang/Object;
    //   27: checkcast e/e/l/d/h$d
    //   30: astore_1
    //   31: aload_1
    //   32: ifnull -> 65
    //   35: aload_0
    //   36: aload_1
    //   37: invokespecial g : (Le/e/l/d/h$d;)Le/e/e/h/a;
    //   40: astore_1
    //   41: goto -> 44
    //   44: aload_0
    //   45: monitorexit
    //   46: aload_2
    //   47: invokestatic f : (Le/e/l/d/h$d;)V
    //   50: aload_0
    //   51: invokespecial d : ()V
    //   54: aload_0
    //   55: invokespecial c : ()V
    //   58: aload_1
    //   59: areturn
    //   60: astore_1
    //   61: aload_0
    //   62: monitorexit
    //   63: aload_1
    //   64: athrow
    //   65: aconst_null
    //   66: astore_1
    //   67: goto -> 44
    // Exception table:
    //   from	to	target	type
    //   7	31	60	finally
    //   35	41	60	finally
    //   44	46	60	finally
    //   61	63	60	finally
  }
  
  class a implements v<d<K, V>> {
    a(h this$0, v param1v) {}
    
    public int a(h.d<K, V> param1d) {
      return this.a.a(param1d.b.b());
    }
  }
  
  class b implements e.e.e.h.c<V> {
    b(h this$0, h.d param1d) {}
    
    public void a(V param1V) {
      h.a(this.b, this.a);
    }
  }
  
  public static interface c {}
  
  static class d<K, V> {
    public final K a;
    
    public final e.e.e.h.a<V> b;
    
    public int c;
    
    public boolean d;
    
    public final h.e<K> e;
    
    private d(K param1K, e.e.e.h.a<V> param1a, h.e<K> param1e) {
      i.a(param1K);
      this.a = param1K;
      e.e.e.h.a<V> a1 = e.e.e.h.a.a(param1a);
      i.a(a1);
      this.b = a1;
      this.c = 0;
      this.d = false;
      this.e = param1e;
    }
    
    static <K, V> d<K, V> a(K param1K, e.e.e.h.a<V> param1a, h.e<K> param1e) {
      return new d<K, V>(param1K, param1a, param1e);
    }
  }
  
  public static interface e<K> {
    void a(K param1K, boolean param1Boolean);
  }
}


/* Location:              /home/yc/Downloads/LeaveHomeSafe.jar!/e/e/l/d/h.class
 * Java compiler version: 6 (50.0)
 * JD-Core Version:       1.1.3
 */