package e.e.l.d;

import e.e.c.a.d;

public class t implements n {
  private static t a;
  
  public static t h() {
    // Byte code:
    //   0: ldc e/e/l/d/t
    //   2: monitorenter
    //   3: getstatic e/e/l/d/t.a : Le/e/l/d/t;
    //   6: ifnonnull -> 19
    //   9: new e/e/l/d/t
    //   12: dup
    //   13: invokespecial <init> : ()V
    //   16: putstatic e/e/l/d/t.a : Le/e/l/d/t;
    //   19: getstatic e/e/l/d/t.a : Le/e/l/d/t;
    //   22: astore_0
    //   23: ldc e/e/l/d/t
    //   25: monitorexit
    //   26: aload_0
    //   27: areturn
    //   28: astore_0
    //   29: ldc e/e/l/d/t
    //   31: monitorexit
    //   32: aload_0
    //   33: athrow
    // Exception table:
    //   from	to	target	type
    //   3	19	28	finally
    //   19	23	28	finally
  }
  
  public void a() {}
  
  public void a(d paramd) {}
  
  public void a(h<?, ?> paramh) {}
  
  public void b() {}
  
  public void b(d paramd) {}
  
  public void b(h<?, ?> paramh) {}
  
  public void c() {}
  
  public void c(d paramd) {}
  
  public void d() {}
  
  public void d(d paramd) {}
  
  public void e() {}
  
  public void f() {}
  
  public void g() {}
}


/* Location:              /home/yc/Downloads/LeaveHomeSafe.jar!/e/e/l/d/t.class
 * Java compiler version: 6 (50.0)
 * JD-Core Version:       1.1.3
 */