package e.e.l.n;

import e.e.l.o.c;
import java.util.ArrayList;
import java.util.Iterator;
import java.util.List;

public class d implements k0 {
  private final c a;
  
  private final String b;
  
  private final m0 c;
  
  private final Object d;
  
  private final c.b e;
  
  private boolean f;
  
  private e.e.l.e.d g;
  
  private boolean h;
  
  private boolean i;
  
  private final List<l0> j;
  
  public d(c paramc, String paramString, m0 paramm0, Object paramObject, c.b paramb, boolean paramBoolean1, boolean paramBoolean2, e.e.l.e.d paramd) {
    this.a = paramc;
    this.b = paramString;
    this.c = paramm0;
    this.d = paramObject;
    this.e = paramb;
    this.f = paramBoolean1;
    this.g = paramd;
    this.h = paramBoolean2;
    this.i = false;
    this.j = new ArrayList<l0>();
  }
  
  public static void a(List<l0> paramList) {
    if (paramList == null)
      return; 
    Iterator<l0> iterator = paramList.iterator();
    while (iterator.hasNext())
      ((l0)iterator.next()).a(); 
  }
  
  public static void b(List<l0> paramList) {
    if (paramList == null)
      return; 
    Iterator<l0> iterator = paramList.iterator();
    while (iterator.hasNext())
      ((l0)iterator.next()).b(); 
  }
  
  public static void c(List<l0> paramList) {
    if (paramList == null)
      return; 
    Iterator<l0> iterator = paramList.iterator();
    while (iterator.hasNext())
      ((l0)iterator.next()).d(); 
  }
  
  public static void d(List<l0> paramList) {
    if (paramList == null)
      return; 
    Iterator<l0> iterator = paramList.iterator();
    while (iterator.hasNext())
      ((l0)iterator.next()).c(); 
  }
  
  public String a() {
    return this.b;
  }
  
  public List<l0> a(e.e.l.e.d paramd) {
    // Byte code:
    //   0: aload_0
    //   1: monitorenter
    //   2: aload_0
    //   3: getfield g : Le/e/l/e/d;
    //   6: astore_2
    //   7: aload_1
    //   8: aload_2
    //   9: if_acmpne -> 16
    //   12: aload_0
    //   13: monitorexit
    //   14: aconst_null
    //   15: areturn
    //   16: aload_0
    //   17: aload_1
    //   18: putfield g : Le/e/l/e/d;
    //   21: new java/util/ArrayList
    //   24: dup
    //   25: aload_0
    //   26: getfield j : Ljava/util/List;
    //   29: invokespecial <init> : (Ljava/util/Collection;)V
    //   32: astore_1
    //   33: aload_0
    //   34: monitorexit
    //   35: aload_1
    //   36: areturn
    //   37: astore_1
    //   38: aload_0
    //   39: monitorexit
    //   40: aload_1
    //   41: athrow
    // Exception table:
    //   from	to	target	type
    //   2	7	37	finally
    //   16	33	37	finally
  }
  
  public List<l0> a(boolean paramBoolean) {
    // Byte code:
    //   0: aload_0
    //   1: monitorenter
    //   2: aload_0
    //   3: getfield h : Z
    //   6: istore_2
    //   7: iload_1
    //   8: iload_2
    //   9: if_icmpne -> 16
    //   12: aload_0
    //   13: monitorexit
    //   14: aconst_null
    //   15: areturn
    //   16: aload_0
    //   17: iload_1
    //   18: putfield h : Z
    //   21: new java/util/ArrayList
    //   24: dup
    //   25: aload_0
    //   26: getfield j : Ljava/util/List;
    //   29: invokespecial <init> : (Ljava/util/Collection;)V
    //   32: astore_3
    //   33: aload_0
    //   34: monitorexit
    //   35: aload_3
    //   36: areturn
    //   37: astore_3
    //   38: aload_0
    //   39: monitorexit
    //   40: aload_3
    //   41: athrow
    // Exception table:
    //   from	to	target	type
    //   2	7	37	finally
    //   16	33	37	finally
  }
  
  public void a(l0 paraml0) {
    // Byte code:
    //   0: aload_0
    //   1: monitorenter
    //   2: aload_0
    //   3: getfield j : Ljava/util/List;
    //   6: aload_1
    //   7: invokeinterface add : (Ljava/lang/Object;)Z
    //   12: pop
    //   13: aload_0
    //   14: getfield i : Z
    //   17: istore_2
    //   18: aload_0
    //   19: monitorexit
    //   20: iload_2
    //   21: ifeq -> 30
    //   24: aload_1
    //   25: invokeinterface a : ()V
    //   30: return
    //   31: astore_1
    //   32: aload_0
    //   33: monitorexit
    //   34: aload_1
    //   35: athrow
    // Exception table:
    //   from	to	target	type
    //   2	20	31	finally
    //   32	34	31	finally
  }
  
  public Object b() {
    return this.d;
  }
  
  public List<l0> b(boolean paramBoolean) {
    // Byte code:
    //   0: aload_0
    //   1: monitorenter
    //   2: aload_0
    //   3: getfield f : Z
    //   6: istore_2
    //   7: iload_1
    //   8: iload_2
    //   9: if_icmpne -> 16
    //   12: aload_0
    //   13: monitorexit
    //   14: aconst_null
    //   15: areturn
    //   16: aload_0
    //   17: iload_1
    //   18: putfield f : Z
    //   21: new java/util/ArrayList
    //   24: dup
    //   25: aload_0
    //   26: getfield j : Ljava/util/List;
    //   29: invokespecial <init> : (Ljava/util/Collection;)V
    //   32: astore_3
    //   33: aload_0
    //   34: monitorexit
    //   35: aload_3
    //   36: areturn
    //   37: astore_3
    //   38: aload_0
    //   39: monitorexit
    //   40: aload_3
    //   41: athrow
    // Exception table:
    //   from	to	target	type
    //   2	7	37	finally
    //   16	33	37	finally
  }
  
  public e.e.l.e.d c() {
    // Byte code:
    //   0: aload_0
    //   1: monitorenter
    //   2: aload_0
    //   3: getfield g : Le/e/l/e/d;
    //   6: astore_1
    //   7: aload_0
    //   8: monitorexit
    //   9: aload_1
    //   10: areturn
    //   11: astore_1
    //   12: aload_0
    //   13: monitorexit
    //   14: aload_1
    //   15: athrow
    // Exception table:
    //   from	to	target	type
    //   2	7	11	finally
  }
  
  public boolean d() {
    // Byte code:
    //   0: aload_0
    //   1: monitorenter
    //   2: aload_0
    //   3: getfield f : Z
    //   6: istore_1
    //   7: aload_0
    //   8: monitorexit
    //   9: iload_1
    //   10: ireturn
    //   11: astore_2
    //   12: aload_0
    //   13: monitorexit
    //   14: aload_2
    //   15: athrow
    // Exception table:
    //   from	to	target	type
    //   2	7	11	finally
  }
  
  public m0 e() {
    return this.c;
  }
  
  public c f() {
    return this.a;
  }
  
  public boolean g() {
    // Byte code:
    //   0: aload_0
    //   1: monitorenter
    //   2: aload_0
    //   3: getfield h : Z
    //   6: istore_1
    //   7: aload_0
    //   8: monitorexit
    //   9: iload_1
    //   10: ireturn
    //   11: astore_2
    //   12: aload_0
    //   13: monitorexit
    //   14: aload_2
    //   15: athrow
    // Exception table:
    //   from	to	target	type
    //   2	7	11	finally
  }
  
  public c.b h() {
    return this.e;
  }
  
  public void i() {
    a(j());
  }
  
  public List<l0> j() {
    // Byte code:
    //   0: aload_0
    //   1: monitorenter
    //   2: aload_0
    //   3: getfield i : Z
    //   6: istore_1
    //   7: iload_1
    //   8: ifeq -> 15
    //   11: aload_0
    //   12: monitorexit
    //   13: aconst_null
    //   14: areturn
    //   15: aload_0
    //   16: iconst_1
    //   17: putfield i : Z
    //   20: new java/util/ArrayList
    //   23: dup
    //   24: aload_0
    //   25: getfield j : Ljava/util/List;
    //   28: invokespecial <init> : (Ljava/util/Collection;)V
    //   31: astore_2
    //   32: aload_0
    //   33: monitorexit
    //   34: aload_2
    //   35: areturn
    //   36: astore_2
    //   37: aload_0
    //   38: monitorexit
    //   39: aload_2
    //   40: athrow
    // Exception table:
    //   from	to	target	type
    //   2	7	36	finally
    //   15	32	36	finally
  }
}


/* Location:              /home/yc/Downloads/LeaveHomeSafe.jar!/e/e/l/n/d.class
 * Java compiler version: 6 (50.0)
 * JD-Core Version:       1.1.3
 */