package com.facebook.imagepipeline.memory;

public class b0 implements h0 {
  private static b0 a;
  
  public static b0 c() {
    // Byte code:
    //   0: ldc com/facebook/imagepipeline/memory/b0
    //   2: monitorenter
    //   3: getstatic com/facebook/imagepipeline/memory/b0.a : Lcom/facebook/imagepipeline/memory/b0;
    //   6: ifnonnull -> 19
    //   9: new com/facebook/imagepipeline/memory/b0
    //   12: dup
    //   13: invokespecial <init> : ()V
    //   16: putstatic com/facebook/imagepipeline/memory/b0.a : Lcom/facebook/imagepipeline/memory/b0;
    //   19: getstatic com/facebook/imagepipeline/memory/b0.a : Lcom/facebook/imagepipeline/memory/b0;
    //   22: astore_0
    //   23: ldc com/facebook/imagepipeline/memory/b0
    //   25: monitorexit
    //   26: aload_0
    //   27: areturn
    //   28: astore_0
    //   29: ldc com/facebook/imagepipeline/memory/b0
    //   31: monitorexit
    //   32: aload_0
    //   33: athrow
    // Exception table:
    //   from	to	target	type
    //   3	19	28	finally
    //   19	23	28	finally
  }
  
  public void a() {}
  
  public void a(int paramInt) {}
  
  public void a(a parama) {}
  
  public void b() {}
  
  public void b(int paramInt) {}
  
  public void c(int paramInt) {}
  
  public void d(int paramInt) {}
}


/* Location:              /home/yc/Downloads/LeaveHomeSafe.jar!/com/facebook/imagepipeline/memory/b0.class
 * Java compiler version: 6 (50.0)
 * JD-Core Version:       1.1.3
 */