package net.time4j.tz.t;

import java.io.ByteArrayInputStream;
import java.io.DataInputStream;
import java.io.IOException;
import java.io.ObjectInputStream;
import java.util.Collections;
import java.util.Map;
import java.util.Set;
import net.time4j.f0;
import net.time4j.g1.c;
import net.time4j.tz.m;
import net.time4j.tz.r;
import net.time4j.tz.s;

public class a implements r, c {
  private final String a;
  
  private final String b;
  
  private final Map<String, byte[]> c;
  
  private final Map<String, String> d;
  
  private final f0 e;
  
  private final Map<net.time4j.c1.a, Integer> f;
  
  public a() {
    // Byte code:
    //   0: ldc ''
    //   2: astore #17
    //   4: aload_0
    //   5: invokespecial <init> : ()V
    //   8: invokestatic I : ()Lnet/time4j/d1/i0;
    //   11: invokevirtual j : ()Lnet/time4j/d1/l0;
    //   14: checkcast net/time4j/f0
    //   17: astore #11
    //   19: new java/util/HashMap
    //   22: dup
    //   23: invokespecial <init> : ()V
    //   26: astore #18
    //   28: new java/util/HashMap
    //   31: dup
    //   32: invokespecial <init> : ()V
    //   35: astore #19
    //   37: ldc 'net.time4j.scale.leapseconds.path'
    //   39: invokestatic getProperty : (Ljava/lang/String;)Ljava/lang/String;
    //   42: ifnull -> 50
    //   45: iconst_1
    //   46: istore_1
    //   47: goto -> 52
    //   50: iconst_0
    //   51: istore_1
    //   52: iload_1
    //   53: ifeq -> 64
    //   56: invokestatic emptyMap : ()Ljava/util/Map;
    //   59: astore #7
    //   61: goto -> 75
    //   64: new java/util/LinkedHashMap
    //   67: dup
    //   68: bipush #50
    //   70: invokespecial <init> : (I)V
    //   73: astore #7
    //   75: aload_0
    //   76: aload #7
    //   78: putfield f : Ljava/util/Map;
    //   81: ldc 'net.time4j.tz.repository.path'
    //   83: invokestatic getProperty : (Ljava/lang/String;)Ljava/lang/String;
    //   86: astore #8
    //   88: ldc 'net.time4j.tz.repository.version'
    //   90: invokestatic getProperty : (Ljava/lang/String;)Ljava/lang/String;
    //   93: astore #7
    //   95: aload #7
    //   97: ifnonnull -> 107
    //   100: ldc 'tzdata.repository'
    //   102: astore #7
    //   104: goto -> 147
    //   107: new java/lang/StringBuilder
    //   110: dup
    //   111: invokespecial <init> : ()V
    //   114: astore #9
    //   116: aload #9
    //   118: ldc 'tzdata'
    //   120: invokevirtual append : (Ljava/lang/String;)Ljava/lang/StringBuilder;
    //   123: pop
    //   124: aload #9
    //   126: aload #7
    //   128: invokevirtual append : (Ljava/lang/String;)Ljava/lang/StringBuilder;
    //   131: pop
    //   132: aload #9
    //   134: ldc '.repository'
    //   136: invokevirtual append : (Ljava/lang/String;)Ljava/lang/StringBuilder;
    //   139: pop
    //   140: aload #9
    //   142: invokevirtual toString : ()Ljava/lang/String;
    //   145: astore #7
    //   147: new java/lang/StringBuilder
    //   150: dup
    //   151: invokespecial <init> : ()V
    //   154: astore #9
    //   156: aload #9
    //   158: ldc 'tzrepo/'
    //   160: invokevirtual append : (Ljava/lang/String;)Ljava/lang/StringBuilder;
    //   163: pop
    //   164: aload #9
    //   166: aload #7
    //   168: invokevirtual append : (Ljava/lang/String;)Ljava/lang/StringBuilder;
    //   171: pop
    //   172: aload #9
    //   174: invokevirtual toString : ()Ljava/lang/String;
    //   177: astore #20
    //   179: aload #8
    //   181: ifnull -> 287
    //   184: new java/io/File
    //   187: dup
    //   188: aload #8
    //   190: aload #7
    //   192: invokespecial <init> : (Ljava/lang/String;Ljava/lang/String;)V
    //   195: astore #7
    //   197: aload #7
    //   199: invokevirtual isAbsolute : ()Z
    //   202: ifeq -> 261
    //   205: aload #7
    //   207: invokevirtual exists : ()Z
    //   210: ifeq -> 223
    //   213: aload #7
    //   215: invokevirtual toURI : ()Ljava/net/URI;
    //   218: astore #7
    //   220: goto -> 302
    //   223: new java/lang/StringBuilder
    //   226: dup
    //   227: invokespecial <init> : ()V
    //   230: astore #8
    //   232: aload #8
    //   234: ldc 'Path to tz-repository not found: '
    //   236: invokevirtual append : (Ljava/lang/String;)Ljava/lang/StringBuilder;
    //   239: pop
    //   240: aload #8
    //   242: aload #7
    //   244: invokevirtual append : (Ljava/lang/Object;)Ljava/lang/StringBuilder;
    //   247: pop
    //   248: new java/io/FileNotFoundException
    //   251: dup
    //   252: aload #8
    //   254: invokevirtual toString : ()Ljava/lang/String;
    //   257: invokespecial <init> : (Ljava/lang/String;)V
    //   260: athrow
    //   261: invokestatic c : ()Lnet/time4j/c1/d;
    //   264: ldc 'tzdata'
    //   266: invokestatic j : ()Ljava/lang/Class;
    //   269: aload #7
    //   271: invokevirtual toString : ()Ljava/lang/String;
    //   274: invokevirtual a : (Ljava/lang/String;Ljava/lang/Class;Ljava/lang/String;)Ljava/net/URI;
    //   277: astore #7
    //   279: goto -> 302
    //   282: astore #12
    //   284: goto -> 1310
    //   287: invokestatic c : ()Lnet/time4j/c1/d;
    //   290: ldc 'tzdata'
    //   292: invokestatic j : ()Ljava/lang/Class;
    //   295: aload #20
    //   297: invokevirtual a : (Ljava/lang/String;Ljava/lang/Class;Ljava/lang/String;)Ljava/net/URI;
    //   300: astore #7
    //   302: aload #7
    //   304: ifnull -> 349
    //   307: invokestatic c : ()Lnet/time4j/c1/d;
    //   310: aload #7
    //   312: iconst_1
    //   313: invokevirtual a : (Ljava/net/URI;Z)Ljava/io/InputStream;
    //   316: astore #10
    //   318: aload #10
    //   320: astore #8
    //   322: aload #7
    //   324: invokevirtual toString : ()Ljava/lang/String;
    //   327: astore #13
    //   329: goto -> 356
    //   332: astore #7
    //   334: ldc ''
    //   336: astore #15
    //   338: aload #15
    //   340: astore #9
    //   342: aload #10
    //   344: astore #12
    //   346: goto -> 1273
    //   349: ldc ''
    //   351: astore #13
    //   353: aconst_null
    //   354: astore #10
    //   356: aload #10
    //   358: astore #9
    //   360: aload #13
    //   362: astore #7
    //   364: aload #10
    //   366: ifnonnull -> 660
    //   369: aload #10
    //   371: astore #8
    //   373: aload #17
    //   375: astore #16
    //   377: aload #11
    //   379: astore #14
    //   381: aload #10
    //   383: astore #12
    //   385: aload #13
    //   387: astore #15
    //   389: invokestatic j : ()Ljava/lang/Class;
    //   392: invokevirtual getClassLoader : ()Ljava/lang/ClassLoader;
    //   395: aload #20
    //   397: invokevirtual getResource : (Ljava/lang/String;)Ljava/net/URL;
    //   400: astore #7
    //   402: aload #7
    //   404: ifnull -> 542
    //   407: aload #10
    //   409: astore #8
    //   411: aload #17
    //   413: astore #16
    //   415: aload #11
    //   417: astore #14
    //   419: aload #10
    //   421: astore #12
    //   423: aload #13
    //   425: astore #15
    //   427: aload #7
    //   429: invokevirtual openConnection : ()Ljava/net/URLConnection;
    //   432: astore #9
    //   434: aload #10
    //   436: astore #8
    //   438: aload #17
    //   440: astore #16
    //   442: aload #11
    //   444: astore #14
    //   446: aload #10
    //   448: astore #12
    //   450: aload #13
    //   452: astore #15
    //   454: aload #9
    //   456: iconst_0
    //   457: invokevirtual setUseCaches : (Z)V
    //   460: aload #10
    //   462: astore #8
    //   464: aload #17
    //   466: astore #16
    //   468: aload #11
    //   470: astore #14
    //   472: aload #10
    //   474: astore #12
    //   476: aload #13
    //   478: astore #15
    //   480: aload #9
    //   482: invokevirtual connect : ()V
    //   485: aload #10
    //   487: astore #8
    //   489: aload #17
    //   491: astore #16
    //   493: aload #11
    //   495: astore #14
    //   497: aload #10
    //   499: astore #12
    //   501: aload #13
    //   503: astore #15
    //   505: aload #9
    //   507: invokevirtual getInputStream : ()Ljava/io/InputStream;
    //   510: astore #9
    //   512: aload #9
    //   514: astore #8
    //   516: aload #17
    //   518: astore #16
    //   520: aload #11
    //   522: astore #14
    //   524: aload #9
    //   526: astore #12
    //   528: aload #13
    //   530: astore #15
    //   532: aload #7
    //   534: invokevirtual toString : ()Ljava/lang/String;
    //   537: astore #7
    //   539: goto -> 660
    //   542: aload #10
    //   544: astore #8
    //   546: aload #17
    //   548: astore #16
    //   550: aload #11
    //   552: astore #14
    //   554: aload #10
    //   556: astore #12
    //   558: aload #13
    //   560: astore #15
    //   562: new java/lang/StringBuilder
    //   565: dup
    //   566: invokespecial <init> : ()V
    //   569: astore #7
    //   571: aload #10
    //   573: astore #8
    //   575: aload #17
    //   577: astore #16
    //   579: aload #11
    //   581: astore #14
    //   583: aload #10
    //   585: astore #12
    //   587: aload #13
    //   589: astore #15
    //   591: aload #7
    //   593: ldc 'Classloader cannot access tz-repository: '
    //   595: invokevirtual append : (Ljava/lang/String;)Ljava/lang/StringBuilder;
    //   598: pop
    //   599: aload #10
    //   601: astore #8
    //   603: aload #17
    //   605: astore #16
    //   607: aload #11
    //   609: astore #14
    //   611: aload #10
    //   613: astore #12
    //   615: aload #13
    //   617: astore #15
    //   619: aload #7
    //   621: aload #20
    //   623: invokevirtual append : (Ljava/lang/String;)Ljava/lang/StringBuilder;
    //   626: pop
    //   627: aload #10
    //   629: astore #8
    //   631: aload #17
    //   633: astore #16
    //   635: aload #11
    //   637: astore #14
    //   639: aload #10
    //   641: astore #12
    //   643: aload #13
    //   645: astore #15
    //   647: new java/io/FileNotFoundException
    //   650: dup
    //   651: aload #7
    //   653: invokevirtual toString : ()Ljava/lang/String;
    //   656: invokespecial <init> : (Ljava/lang/String;)V
    //   659: athrow
    //   660: aload #9
    //   662: astore #8
    //   664: aload #17
    //   666: astore #16
    //   668: aload #11
    //   670: astore #14
    //   672: aload #9
    //   674: astore #12
    //   676: aload #7
    //   678: astore #15
    //   680: new java/io/DataInputStream
    //   683: dup
    //   684: aload #9
    //   686: invokespecial <init> : (Ljava/io/InputStream;)V
    //   689: astore #20
    //   691: aload #9
    //   693: astore #8
    //   695: aload #17
    //   697: astore #16
    //   699: aload #11
    //   701: astore #14
    //   703: aload #9
    //   705: astore #12
    //   707: aload #7
    //   709: astore #15
    //   711: aload #20
    //   713: aload #7
    //   715: invokestatic a : (Ljava/io/DataInputStream;Ljava/lang/String;)V
    //   718: aload #9
    //   720: astore #8
    //   722: aload #17
    //   724: astore #16
    //   726: aload #11
    //   728: astore #14
    //   730: aload #9
    //   732: astore #12
    //   734: aload #7
    //   736: astore #15
    //   738: aload #20
    //   740: invokevirtual readUTF : ()Ljava/lang/String;
    //   743: astore #13
    //   745: aload #9
    //   747: astore #8
    //   749: aload #17
    //   751: astore #16
    //   753: aload #11
    //   755: astore #14
    //   757: aload #9
    //   759: astore #12
    //   761: aload #7
    //   763: astore #15
    //   765: aload #20
    //   767: invokevirtual readInt : ()I
    //   770: istore #5
    //   772: aload #9
    //   774: astore #8
    //   776: aload #17
    //   778: astore #16
    //   780: aload #11
    //   782: astore #14
    //   784: aload #9
    //   786: astore #12
    //   788: aload #7
    //   790: astore #15
    //   792: new java/util/ArrayList
    //   795: dup
    //   796: iload #5
    //   798: invokespecial <init> : (I)V
    //   801: astore #21
    //   803: iconst_0
    //   804: istore_2
    //   805: aload #11
    //   807: astore #10
    //   809: aload #17
    //   811: astore #11
    //   813: iload_2
    //   814: iload #5
    //   816: if_icmpge -> 1028
    //   819: aload #9
    //   821: astore #8
    //   823: aload #11
    //   825: astore #16
    //   827: aload #10
    //   829: astore #14
    //   831: aload #9
    //   833: astore #12
    //   835: aload #7
    //   837: astore #15
    //   839: aload #20
    //   841: invokevirtual readUTF : ()Ljava/lang/String;
    //   844: astore #17
    //   846: aload #9
    //   848: astore #8
    //   850: aload #11
    //   852: astore #16
    //   854: aload #10
    //   856: astore #14
    //   858: aload #9
    //   860: astore #12
    //   862: aload #7
    //   864: astore #15
    //   866: aload #20
    //   868: invokevirtual readInt : ()I
    //   871: istore #6
    //   873: aload #9
    //   875: astore #8
    //   877: aload #11
    //   879: astore #16
    //   881: aload #10
    //   883: astore #14
    //   885: aload #9
    //   887: astore #12
    //   889: aload #7
    //   891: astore #15
    //   893: iload #6
    //   895: newarray byte
    //   897: astore #22
    //   899: iconst_0
    //   900: istore_3
    //   901: aload #9
    //   903: astore #8
    //   905: iload_3
    //   906: aload #20
    //   908: aload #22
    //   910: iload_3
    //   911: iload #6
    //   913: iload_3
    //   914: isub
    //   915: invokevirtual read : ([BII)I
    //   918: iadd
    //   919: istore #4
    //   921: iload #4
    //   923: iconst_m1
    //   924: if_icmpeq -> 974
    //   927: iload #4
    //   929: istore_3
    //   930: iload #6
    //   932: iload #4
    //   934: if_icmpgt -> 901
    //   937: aload #9
    //   939: astore #8
    //   941: aload #21
    //   943: aload #17
    //   945: invokeinterface add : (Ljava/lang/Object;)Z
    //   950: pop
    //   951: aload #9
    //   953: astore #8
    //   955: aload #18
    //   957: aload #17
    //   959: aload #22
    //   961: invokeinterface put : (Ljava/lang/Object;Ljava/lang/Object;)Ljava/lang/Object;
    //   966: pop
    //   967: iload_2
    //   968: iconst_1
    //   969: iadd
    //   970: istore_2
    //   971: goto -> 813
    //   974: aload #9
    //   976: astore #8
    //   978: new java/lang/StringBuilder
    //   981: dup
    //   982: invokespecial <init> : ()V
    //   985: astore #12
    //   987: aload #9
    //   989: astore #8
    //   991: aload #12
    //   993: ldc 'Incomplete data: '
    //   995: invokevirtual append : (Ljava/lang/String;)Ljava/lang/StringBuilder;
    //   998: pop
    //   999: aload #9
    //   1001: astore #8
    //   1003: aload #12
    //   1005: aload #17
    //   1007: invokevirtual append : (Ljava/lang/String;)Ljava/lang/StringBuilder;
    //   1010: pop
    //   1011: aload #9
    //   1013: astore #8
    //   1015: new java/io/EOFException
    //   1018: dup
    //   1019: aload #12
    //   1021: invokevirtual toString : ()Ljava/lang/String;
    //   1024: invokespecial <init> : (Ljava/lang/String;)V
    //   1027: athrow
    //   1028: aload #9
    //   1030: astore #8
    //   1032: aload #20
    //   1034: invokevirtual readShort : ()S
    //   1037: istore_3
    //   1038: iconst_0
    //   1039: istore_2
    //   1040: iload_2
    //   1041: iload_3
    //   1042: if_icmpge -> 1084
    //   1045: aload #9
    //   1047: astore #8
    //   1049: aload #19
    //   1051: aload #20
    //   1053: invokevirtual readUTF : ()Ljava/lang/String;
    //   1056: aload #21
    //   1058: aload #20
    //   1060: invokevirtual readShort : ()S
    //   1063: invokeinterface get : (I)Ljava/lang/Object;
    //   1068: checkcast java/lang/String
    //   1071: invokeinterface put : (Ljava/lang/Object;Ljava/lang/Object;)Ljava/lang/Object;
    //   1076: pop
    //   1077: iload_2
    //   1078: iconst_1
    //   1079: iadd
    //   1080: istore_2
    //   1081: goto -> 1040
    //   1084: iload_1
    //   1085: ifne -> 1213
    //   1088: aload #9
    //   1090: astore #8
    //   1092: aload #20
    //   1094: invokevirtual readShort : ()S
    //   1097: istore_2
    //   1098: iconst_0
    //   1099: istore_1
    //   1100: iload_1
    //   1101: iload_2
    //   1102: if_icmpge -> 1182
    //   1105: aload #9
    //   1107: astore #8
    //   1109: aload #20
    //   1111: invokevirtual readShort : ()S
    //   1114: istore_3
    //   1115: aload #9
    //   1117: astore #8
    //   1119: aload #20
    //   1121: invokevirtual readByte : ()B
    //   1124: istore #4
    //   1126: aload #9
    //   1128: astore #8
    //   1130: aload #20
    //   1132: invokevirtual readByte : ()B
    //   1135: istore #5
    //   1137: aload #9
    //   1139: astore #8
    //   1141: aload #20
    //   1143: invokevirtual readByte : ()B
    //   1146: istore #6
    //   1148: aload #9
    //   1150: astore #8
    //   1152: aload_0
    //   1153: getfield f : Ljava/util/Map;
    //   1156: iload_3
    //   1157: iload #4
    //   1159: iload #5
    //   1161: invokestatic b : (III)Lnet/time4j/f0;
    //   1164: iload #6
    //   1166: invokestatic valueOf : (I)Ljava/lang/Integer;
    //   1169: invokeinterface put : (Ljava/lang/Object;Ljava/lang/Object;)Ljava/lang/Object;
    //   1174: pop
    //   1175: iload_1
    //   1176: iconst_1
    //   1177: iadd
    //   1178: istore_1
    //   1179: goto -> 1100
    //   1182: aload #9
    //   1184: astore #8
    //   1186: aload #20
    //   1188: invokevirtual readShort : ()S
    //   1191: aload #20
    //   1193: invokevirtual readByte : ()B
    //   1196: aload #20
    //   1198: invokevirtual readByte : ()B
    //   1201: invokestatic b : (III)Lnet/time4j/f0;
    //   1204: astore #12
    //   1206: aload #12
    //   1208: astore #8
    //   1210: goto -> 1217
    //   1213: aload #10
    //   1215: astore #8
    //   1217: aload #9
    //   1219: ifnull -> 1227
    //   1222: aload #9
    //   1224: invokevirtual close : ()V
    //   1227: aconst_null
    //   1228: astore #10
    //   1230: aload #13
    //   1232: astore #9
    //   1234: goto -> 1383
    //   1237: aload #10
    //   1239: astore #8
    //   1241: astore #10
    //   1243: aload #9
    //   1245: astore #12
    //   1247: aload #7
    //   1249: astore #15
    //   1251: aload #11
    //   1253: astore #9
    //   1255: goto -> 1281
    //   1258: astore #7
    //   1260: goto -> 1434
    //   1263: astore #7
    //   1265: aload #16
    //   1267: astore #9
    //   1269: aload #14
    //   1271: astore #11
    //   1273: aload #11
    //   1275: astore #8
    //   1277: aload #7
    //   1279: astore #10
    //   1281: aload #12
    //   1283: astore #11
    //   1285: aload #10
    //   1287: astore #12
    //   1289: aload #15
    //   1291: astore #7
    //   1293: aload #11
    //   1295: astore #10
    //   1297: goto -> 1325
    //   1300: astore #7
    //   1302: aconst_null
    //   1303: astore #8
    //   1305: goto -> 1434
    //   1308: astore #12
    //   1310: aload #11
    //   1312: astore #8
    //   1314: ldc ''
    //   1316: astore #9
    //   1318: ldc ''
    //   1320: astore #7
    //   1322: aconst_null
    //   1323: astore #10
    //   1325: new java/lang/StringBuilder
    //   1328: dup
    //   1329: invokespecial <init> : ()V
    //   1332: astore #11
    //   1334: aload #11
    //   1336: ldc '[ERROR] TZ-repository not available. => '
    //   1338: invokevirtual append : (Ljava/lang/String;)Ljava/lang/StringBuilder;
    //   1341: pop
    //   1342: aload #11
    //   1344: aload #12
    //   1346: invokevirtual getMessage : ()Ljava/lang/String;
    //   1349: invokevirtual append : (Ljava/lang/String;)Ljava/lang/StringBuilder;
    //   1352: pop
    //   1353: new java/lang/IllegalStateException
    //   1356: dup
    //   1357: aload #11
    //   1359: invokevirtual toString : ()Ljava/lang/String;
    //   1362: aload #12
    //   1364: invokespecial <init> : (Ljava/lang/String;Ljava/lang/Throwable;)V
    //   1367: astore #11
    //   1369: aload #10
    //   1371: ifnull -> 1379
    //   1374: aload #10
    //   1376: invokevirtual close : ()V
    //   1379: aload #11
    //   1381: astore #10
    //   1383: aload #10
    //   1385: ifnonnull -> 1425
    //   1388: aload_0
    //   1389: aload #9
    //   1391: putfield a : Ljava/lang/String;
    //   1394: aload_0
    //   1395: aload #7
    //   1397: putfield b : Ljava/lang/String;
    //   1400: aload_0
    //   1401: aload #18
    //   1403: invokestatic unmodifiableMap : (Ljava/util/Map;)Ljava/util/Map;
    //   1406: putfield c : Ljava/util/Map;
    //   1409: aload_0
    //   1410: aload #19
    //   1412: invokestatic unmodifiableMap : (Ljava/util/Map;)Ljava/util/Map;
    //   1415: putfield d : Ljava/util/Map;
    //   1418: aload_0
    //   1419: aload #8
    //   1421: putfield e : Lnet/time4j/f0;
    //   1424: return
    //   1425: aload #10
    //   1427: athrow
    //   1428: astore #7
    //   1430: aload #10
    //   1432: astore #8
    //   1434: aload #8
    //   1436: ifnull -> 1444
    //   1439: aload #8
    //   1441: invokevirtual close : ()V
    //   1444: goto -> 1450
    //   1447: aload #7
    //   1449: athrow
    //   1450: goto -> 1447
    //   1453: astore #9
    //   1455: goto -> 1227
    //   1458: astore #10
    //   1460: goto -> 1379
    //   1463: astore #8
    //   1465: goto -> 1444
    // Exception table:
    //   from	to	target	type
    //   147	179	1308	java/io/IOException
    //   147	179	1300	finally
    //   184	220	282	java/io/IOException
    //   184	220	1300	finally
    //   223	261	282	java/io/IOException
    //   223	261	1300	finally
    //   261	279	282	java/io/IOException
    //   261	279	1300	finally
    //   287	302	1308	java/io/IOException
    //   287	302	1300	finally
    //   307	318	282	java/io/IOException
    //   307	318	1300	finally
    //   322	329	332	java/io/IOException
    //   322	329	1258	finally
    //   389	402	1263	java/io/IOException
    //   389	402	1258	finally
    //   427	434	1263	java/io/IOException
    //   427	434	1258	finally
    //   454	460	1263	java/io/IOException
    //   454	460	1258	finally
    //   480	485	1263	java/io/IOException
    //   480	485	1258	finally
    //   505	512	1263	java/io/IOException
    //   505	512	1258	finally
    //   532	539	1263	java/io/IOException
    //   532	539	1258	finally
    //   562	571	1263	java/io/IOException
    //   562	571	1258	finally
    //   591	599	1263	java/io/IOException
    //   591	599	1258	finally
    //   619	627	1263	java/io/IOException
    //   619	627	1258	finally
    //   647	660	1263	java/io/IOException
    //   647	660	1258	finally
    //   680	691	1263	java/io/IOException
    //   680	691	1258	finally
    //   711	718	1263	java/io/IOException
    //   711	718	1258	finally
    //   738	745	1263	java/io/IOException
    //   738	745	1258	finally
    //   765	772	1263	java/io/IOException
    //   765	772	1258	finally
    //   792	803	1263	java/io/IOException
    //   792	803	1258	finally
    //   839	846	1263	java/io/IOException
    //   839	846	1258	finally
    //   866	873	1263	java/io/IOException
    //   866	873	1258	finally
    //   893	899	1263	java/io/IOException
    //   893	899	1258	finally
    //   905	921	1237	java/io/IOException
    //   905	921	1258	finally
    //   941	951	1237	java/io/IOException
    //   941	951	1258	finally
    //   955	967	1237	java/io/IOException
    //   955	967	1258	finally
    //   978	987	1237	java/io/IOException
    //   978	987	1258	finally
    //   991	999	1237	java/io/IOException
    //   991	999	1258	finally
    //   1003	1011	1237	java/io/IOException
    //   1003	1011	1258	finally
    //   1015	1028	1237	java/io/IOException
    //   1015	1028	1258	finally
    //   1032	1038	1237	java/io/IOException
    //   1032	1038	1258	finally
    //   1049	1077	1237	java/io/IOException
    //   1049	1077	1258	finally
    //   1092	1098	1237	java/io/IOException
    //   1092	1098	1258	finally
    //   1109	1115	1237	java/io/IOException
    //   1109	1115	1258	finally
    //   1119	1126	1237	java/io/IOException
    //   1119	1126	1258	finally
    //   1130	1137	1237	java/io/IOException
    //   1130	1137	1258	finally
    //   1141	1148	1237	java/io/IOException
    //   1141	1148	1258	finally
    //   1152	1175	1237	java/io/IOException
    //   1152	1175	1258	finally
    //   1186	1206	1237	java/io/IOException
    //   1186	1206	1258	finally
    //   1222	1227	1453	java/io/IOException
    //   1325	1369	1428	finally
    //   1374	1379	1458	java/io/IOException
    //   1439	1444	1463	java/io/IOException
  }
  
  private static void a(DataInputStream paramDataInputStream, String paramString) {
    byte b1 = paramDataInputStream.readByte();
    byte b2 = paramDataInputStream.readByte();
    byte b3 = paramDataInputStream.readByte();
    byte b4 = paramDataInputStream.readByte();
    byte b5 = paramDataInputStream.readByte();
    byte b6 = paramDataInputStream.readByte();
    if (b1 == 116 && b2 == 122 && b3 == 114 && b4 == 101 && b5 == 112 && b6 == 111)
      return; 
    StringBuilder stringBuilder = new StringBuilder();
    stringBuilder.append("Invalid tz-repository: ");
    stringBuilder.append(paramString);
    throw new IOException(stringBuilder.toString());
  }
  
  private static Class<?> j() {
    if (Boolean.getBoolean("test.environment"))
      try {
        return Class.forName("net.time4j.tz.spi.RepositoryTest");
      } catch (ClassNotFoundException classNotFoundException) {
        throw new AssertionError(classNotFoundException);
      }  
    return a.class;
  }
  
  public Set<String> a() {
    return this.c.keySet();
  }
  
  public m a(String paramString) {
    try {
      byte[] arrayOfByte = this.c.get(paramString);
      if (arrayOfByte != null)
        return (m)(new ObjectInputStream(new ByteArrayInputStream(arrayOfByte))).readObject(); 
    } catch (IOException iOException) {
      iOException.printStackTrace();
    } catch (ClassNotFoundException classNotFoundException) {
      classNotFoundException.printStackTrace();
    } 
    return null;
  }
  
  public String b() {
    return "";
  }
  
  public s c() {
    return null;
  }
  
  public Map<String, String> d() {
    return this.d;
  }
  
  public String e() {
    return this.a;
  }
  
  public String f() {
    return this.b;
  }
  
  public f0 g() {
    return this.e;
  }
  
  public String getName() {
    return "TZDB";
  }
  
  public boolean h() {
    return this.f.isEmpty() ^ true;
  }
  
  public Map<net.time4j.c1.a, Integer> i() {
    return Collections.unmodifiableMap(this.f);
  }
  
  public String toString() {
    StringBuilder stringBuilder = new StringBuilder();
    stringBuilder.append("TZ-REPOSITORY(");
    stringBuilder.append(this.a);
    stringBuilder.append(")");
    return stringBuilder.toString();
  }
}


/* Location:              /home/yc/Downloads/LeaveHomeSafe.jar!/net/time4j/tz/t/a.class
 * Java compiler version: 6 (50.0)
 * JD-Core Version:       1.1.3
 */