package b.e.b.k.m;

import b.e.b.k.e;

public class l extends m {
  public f k = new f(this);
  
  g l = null;
  
  public l(e parame) {
    super(parame);
    this.h.e = f.a.h;
    this.i.e = f.a.i;
    this.k.e = f.a.j;
    this.f = 1;
  }
  
  void a() {
    // Byte code:
    //   0: aload_0
    //   1: getfield b : Lb/e/b/k/e;
    //   4: astore #4
    //   6: aload #4
    //   8: getfield a : Z
    //   11: ifeq -> 26
    //   14: aload_0
    //   15: getfield e : Lb/e/b/k/m/g;
    //   18: aload #4
    //   20: invokevirtual j : ()I
    //   23: invokevirtual a : (I)V
    //   26: aload_0
    //   27: getfield e : Lb/e/b/k/m/g;
    //   30: getfield j : Z
    //   33: ifne -> 237
    //   36: aload_0
    //   37: aload_0
    //   38: getfield b : Lb/e/b/k/e;
    //   41: invokevirtual w : ()Lb/e/b/k/e$b;
    //   44: putfield d : Lb/e/b/k/e$b;
    //   47: aload_0
    //   48: getfield b : Lb/e/b/k/e;
    //   51: invokevirtual C : ()Z
    //   54: ifeq -> 69
    //   57: aload_0
    //   58: new b/e/b/k/m/a
    //   61: dup
    //   62: aload_0
    //   63: invokespecial <init> : (Lb/e/b/k/m/m;)V
    //   66: putfield l : Lb/e/b/k/m/g;
    //   69: aload_0
    //   70: getfield d : Lb/e/b/k/e$b;
    //   73: astore #4
    //   75: aload #4
    //   77: getstatic b/e/b/k/e$b.e : Lb/e/b/k/e$b;
    //   80: if_acmpeq -> 326
    //   83: aload #4
    //   85: getstatic b/e/b/k/e$b.f : Lb/e/b/k/e$b;
    //   88: if_acmpne -> 210
    //   91: aload_0
    //   92: getfield b : Lb/e/b/k/e;
    //   95: invokevirtual s : ()Lb/e/b/k/e;
    //   98: astore #4
    //   100: aload #4
    //   102: ifnull -> 210
    //   105: aload #4
    //   107: invokevirtual w : ()Lb/e/b/k/e$b;
    //   110: getstatic b/e/b/k/e$b.c : Lb/e/b/k/e$b;
    //   113: if_acmpne -> 210
    //   116: aload #4
    //   118: invokevirtual j : ()I
    //   121: istore_1
    //   122: aload_0
    //   123: getfield b : Lb/e/b/k/e;
    //   126: getfield z : Lb/e/b/k/d;
    //   129: invokevirtual a : ()I
    //   132: istore_2
    //   133: aload_0
    //   134: getfield b : Lb/e/b/k/e;
    //   137: getfield B : Lb/e/b/k/d;
    //   140: invokevirtual a : ()I
    //   143: istore_3
    //   144: aload_0
    //   145: aload_0
    //   146: getfield h : Lb/e/b/k/m/f;
    //   149: aload #4
    //   151: getfield e : Lb/e/b/k/m/l;
    //   154: getfield h : Lb/e/b/k/m/f;
    //   157: aload_0
    //   158: getfield b : Lb/e/b/k/e;
    //   161: getfield z : Lb/e/b/k/d;
    //   164: invokevirtual a : ()I
    //   167: invokevirtual a : (Lb/e/b/k/m/f;Lb/e/b/k/m/f;I)V
    //   170: aload_0
    //   171: aload_0
    //   172: getfield i : Lb/e/b/k/m/f;
    //   175: aload #4
    //   177: getfield e : Lb/e/b/k/m/l;
    //   180: getfield i : Lb/e/b/k/m/f;
    //   183: aload_0
    //   184: getfield b : Lb/e/b/k/e;
    //   187: getfield B : Lb/e/b/k/d;
    //   190: invokevirtual a : ()I
    //   193: ineg
    //   194: invokevirtual a : (Lb/e/b/k/m/f;Lb/e/b/k/m/f;I)V
    //   197: aload_0
    //   198: getfield e : Lb/e/b/k/m/g;
    //   201: iload_1
    //   202: iload_2
    //   203: isub
    //   204: iload_3
    //   205: isub
    //   206: invokevirtual a : (I)V
    //   209: return
    //   210: aload_0
    //   211: getfield d : Lb/e/b/k/e$b;
    //   214: getstatic b/e/b/k/e$b.c : Lb/e/b/k/e$b;
    //   217: if_acmpne -> 326
    //   220: aload_0
    //   221: getfield e : Lb/e/b/k/m/g;
    //   224: aload_0
    //   225: getfield b : Lb/e/b/k/e;
    //   228: invokevirtual j : ()I
    //   231: invokevirtual a : (I)V
    //   234: goto -> 326
    //   237: aload_0
    //   238: getfield d : Lb/e/b/k/e$b;
    //   241: getstatic b/e/b/k/e$b.f : Lb/e/b/k/e$b;
    //   244: if_acmpne -> 326
    //   247: aload_0
    //   248: getfield b : Lb/e/b/k/e;
    //   251: invokevirtual s : ()Lb/e/b/k/e;
    //   254: astore #4
    //   256: aload #4
    //   258: ifnull -> 326
    //   261: aload #4
    //   263: invokevirtual w : ()Lb/e/b/k/e$b;
    //   266: getstatic b/e/b/k/e$b.c : Lb/e/b/k/e$b;
    //   269: if_acmpne -> 326
    //   272: aload_0
    //   273: aload_0
    //   274: getfield h : Lb/e/b/k/m/f;
    //   277: aload #4
    //   279: getfield e : Lb/e/b/k/m/l;
    //   282: getfield h : Lb/e/b/k/m/f;
    //   285: aload_0
    //   286: getfield b : Lb/e/b/k/e;
    //   289: getfield z : Lb/e/b/k/d;
    //   292: invokevirtual a : ()I
    //   295: invokevirtual a : (Lb/e/b/k/m/f;Lb/e/b/k/m/f;I)V
    //   298: aload_0
    //   299: aload_0
    //   300: getfield i : Lb/e/b/k/m/f;
    //   303: aload #4
    //   305: getfield e : Lb/e/b/k/m/l;
    //   308: getfield i : Lb/e/b/k/m/f;
    //   311: aload_0
    //   312: getfield b : Lb/e/b/k/e;
    //   315: getfield B : Lb/e/b/k/d;
    //   318: invokevirtual a : ()I
    //   321: ineg
    //   322: invokevirtual a : (Lb/e/b/k/m/f;Lb/e/b/k/m/f;I)V
    //   325: return
    //   326: aload_0
    //   327: getfield e : Lb/e/b/k/m/g;
    //   330: getfield j : Z
    //   333: ifeq -> 916
    //   336: aload_0
    //   337: getfield b : Lb/e/b/k/e;
    //   340: astore #4
    //   342: aload #4
    //   344: getfield a : Z
    //   347: ifeq -> 916
    //   350: aload #4
    //   352: getfield G : [Lb/e/b/k/d;
    //   355: astore #5
    //   357: aload #5
    //   359: iconst_2
    //   360: aaload
    //   361: getfield d : Lb/e/b/k/d;
    //   364: ifnull -> 568
    //   367: aload #5
    //   369: iconst_3
    //   370: aaload
    //   371: getfield d : Lb/e/b/k/d;
    //   374: ifnull -> 568
    //   377: aload #4
    //   379: invokevirtual F : ()Z
    //   382: ifeq -> 427
    //   385: aload_0
    //   386: getfield h : Lb/e/b/k/m/f;
    //   389: aload_0
    //   390: getfield b : Lb/e/b/k/e;
    //   393: getfield G : [Lb/e/b/k/d;
    //   396: iconst_2
    //   397: aaload
    //   398: invokevirtual a : ()I
    //   401: putfield f : I
    //   404: aload_0
    //   405: getfield i : Lb/e/b/k/m/f;
    //   408: aload_0
    //   409: getfield b : Lb/e/b/k/e;
    //   412: getfield G : [Lb/e/b/k/d;
    //   415: iconst_3
    //   416: aaload
    //   417: invokevirtual a : ()I
    //   420: ineg
    //   421: putfield f : I
    //   424: goto -> 528
    //   427: aload_0
    //   428: aload_0
    //   429: getfield b : Lb/e/b/k/e;
    //   432: getfield G : [Lb/e/b/k/d;
    //   435: iconst_2
    //   436: aaload
    //   437: invokevirtual a : (Lb/e/b/k/d;)Lb/e/b/k/m/f;
    //   440: astore #4
    //   442: aload #4
    //   444: ifnull -> 469
    //   447: aload_0
    //   448: aload_0
    //   449: getfield h : Lb/e/b/k/m/f;
    //   452: aload #4
    //   454: aload_0
    //   455: getfield b : Lb/e/b/k/e;
    //   458: getfield G : [Lb/e/b/k/d;
    //   461: iconst_2
    //   462: aaload
    //   463: invokevirtual a : ()I
    //   466: invokevirtual a : (Lb/e/b/k/m/f;Lb/e/b/k/m/f;I)V
    //   469: aload_0
    //   470: aload_0
    //   471: getfield b : Lb/e/b/k/e;
    //   474: getfield G : [Lb/e/b/k/d;
    //   477: iconst_3
    //   478: aaload
    //   479: invokevirtual a : (Lb/e/b/k/d;)Lb/e/b/k/m/f;
    //   482: astore #4
    //   484: aload #4
    //   486: ifnull -> 512
    //   489: aload_0
    //   490: aload_0
    //   491: getfield i : Lb/e/b/k/m/f;
    //   494: aload #4
    //   496: aload_0
    //   497: getfield b : Lb/e/b/k/e;
    //   500: getfield G : [Lb/e/b/k/d;
    //   503: iconst_3
    //   504: aaload
    //   505: invokevirtual a : ()I
    //   508: ineg
    //   509: invokevirtual a : (Lb/e/b/k/m/f;Lb/e/b/k/m/f;I)V
    //   512: aload_0
    //   513: getfield h : Lb/e/b/k/m/f;
    //   516: iconst_1
    //   517: putfield b : Z
    //   520: aload_0
    //   521: getfield i : Lb/e/b/k/m/f;
    //   524: iconst_1
    //   525: putfield b : Z
    //   528: aload_0
    //   529: getfield b : Lb/e/b/k/e;
    //   532: invokevirtual C : ()Z
    //   535: ifeq -> 1792
    //   538: aload_0
    //   539: getfield k : Lb/e/b/k/m/f;
    //   542: astore #4
    //   544: aload_0
    //   545: getfield h : Lb/e/b/k/m/f;
    //   548: astore #5
    //   550: aload_0
    //   551: getfield b : Lb/e/b/k/e;
    //   554: invokevirtual d : ()I
    //   557: istore_1
    //   558: aload_0
    //   559: aload #4
    //   561: aload #5
    //   563: iload_1
    //   564: invokevirtual a : (Lb/e/b/k/m/f;Lb/e/b/k/m/f;I)V
    //   567: return
    //   568: aload_0
    //   569: getfield b : Lb/e/b/k/e;
    //   572: astore #4
    //   574: aload #4
    //   576: getfield G : [Lb/e/b/k/d;
    //   579: astore #5
    //   581: aload #5
    //   583: iconst_2
    //   584: aaload
    //   585: getfield d : Lb/e/b/k/d;
    //   588: ifnull -> 660
    //   591: aload_0
    //   592: aload #5
    //   594: iconst_2
    //   595: aaload
    //   596: invokevirtual a : (Lb/e/b/k/d;)Lb/e/b/k/m/f;
    //   599: astore #4
    //   601: aload #4
    //   603: ifnull -> 1792
    //   606: aload_0
    //   607: aload_0
    //   608: getfield h : Lb/e/b/k/m/f;
    //   611: aload #4
    //   613: aload_0
    //   614: getfield b : Lb/e/b/k/e;
    //   617: getfield G : [Lb/e/b/k/d;
    //   620: iconst_2
    //   621: aaload
    //   622: invokevirtual a : ()I
    //   625: invokevirtual a : (Lb/e/b/k/m/f;Lb/e/b/k/m/f;I)V
    //   628: aload_0
    //   629: aload_0
    //   630: getfield i : Lb/e/b/k/m/f;
    //   633: aload_0
    //   634: getfield h : Lb/e/b/k/m/f;
    //   637: aload_0
    //   638: getfield e : Lb/e/b/k/m/g;
    //   641: getfield g : I
    //   644: invokevirtual a : (Lb/e/b/k/m/f;Lb/e/b/k/m/f;I)V
    //   647: aload_0
    //   648: getfield b : Lb/e/b/k/e;
    //   651: invokevirtual C : ()Z
    //   654: ifeq -> 1792
    //   657: goto -> 538
    //   660: aload #5
    //   662: iconst_3
    //   663: aaload
    //   664: getfield d : Lb/e/b/k/d;
    //   667: ifnull -> 741
    //   670: aload_0
    //   671: aload #5
    //   673: iconst_3
    //   674: aaload
    //   675: invokevirtual a : (Lb/e/b/k/d;)Lb/e/b/k/m/f;
    //   678: astore #4
    //   680: aload #4
    //   682: ifnull -> 728
    //   685: aload_0
    //   686: aload_0
    //   687: getfield i : Lb/e/b/k/m/f;
    //   690: aload #4
    //   692: aload_0
    //   693: getfield b : Lb/e/b/k/e;
    //   696: getfield G : [Lb/e/b/k/d;
    //   699: iconst_3
    //   700: aaload
    //   701: invokevirtual a : ()I
    //   704: ineg
    //   705: invokevirtual a : (Lb/e/b/k/m/f;Lb/e/b/k/m/f;I)V
    //   708: aload_0
    //   709: aload_0
    //   710: getfield h : Lb/e/b/k/m/f;
    //   713: aload_0
    //   714: getfield i : Lb/e/b/k/m/f;
    //   717: aload_0
    //   718: getfield e : Lb/e/b/k/m/g;
    //   721: getfield g : I
    //   724: ineg
    //   725: invokevirtual a : (Lb/e/b/k/m/f;Lb/e/b/k/m/f;I)V
    //   728: aload_0
    //   729: getfield b : Lb/e/b/k/e;
    //   732: invokevirtual C : ()Z
    //   735: ifeq -> 1792
    //   738: goto -> 538
    //   741: aload #5
    //   743: iconst_4
    //   744: aaload
    //   745: getfield d : Lb/e/b/k/d;
    //   748: ifnull -> 820
    //   751: aload_0
    //   752: aload #5
    //   754: iconst_4
    //   755: aaload
    //   756: invokevirtual a : (Lb/e/b/k/d;)Lb/e/b/k/m/f;
    //   759: astore #4
    //   761: aload #4
    //   763: ifnull -> 1792
    //   766: aload_0
    //   767: aload_0
    //   768: getfield k : Lb/e/b/k/m/f;
    //   771: aload #4
    //   773: iconst_0
    //   774: invokevirtual a : (Lb/e/b/k/m/f;Lb/e/b/k/m/f;I)V
    //   777: aload_0
    //   778: aload_0
    //   779: getfield h : Lb/e/b/k/m/f;
    //   782: aload_0
    //   783: getfield k : Lb/e/b/k/m/f;
    //   786: aload_0
    //   787: getfield b : Lb/e/b/k/e;
    //   790: invokevirtual d : ()I
    //   793: ineg
    //   794: invokevirtual a : (Lb/e/b/k/m/f;Lb/e/b/k/m/f;I)V
    //   797: aload_0
    //   798: getfield i : Lb/e/b/k/m/f;
    //   801: astore #4
    //   803: aload_0
    //   804: getfield h : Lb/e/b/k/m/f;
    //   807: astore #5
    //   809: aload_0
    //   810: getfield e : Lb/e/b/k/m/g;
    //   813: getfield g : I
    //   816: istore_1
    //   817: goto -> 558
    //   820: aload #4
    //   822: instanceof b/e/b/k/h
    //   825: ifne -> 1792
    //   828: aload #4
    //   830: invokevirtual s : ()Lb/e/b/k/e;
    //   833: ifnull -> 1792
    //   836: aload_0
    //   837: getfield b : Lb/e/b/k/e;
    //   840: getstatic b/e/b/k/d$b.i : Lb/e/b/k/d$b;
    //   843: invokevirtual a : (Lb/e/b/k/d$b;)Lb/e/b/k/d;
    //   846: getfield d : Lb/e/b/k/d;
    //   849: ifnonnull -> 1792
    //   852: aload_0
    //   853: getfield b : Lb/e/b/k/e;
    //   856: invokevirtual s : ()Lb/e/b/k/e;
    //   859: getfield e : Lb/e/b/k/m/l;
    //   862: getfield h : Lb/e/b/k/m/f;
    //   865: astore #4
    //   867: aload_0
    //   868: aload_0
    //   869: getfield h : Lb/e/b/k/m/f;
    //   872: aload #4
    //   874: aload_0
    //   875: getfield b : Lb/e/b/k/e;
    //   878: invokevirtual B : ()I
    //   881: invokevirtual a : (Lb/e/b/k/m/f;Lb/e/b/k/m/f;I)V
    //   884: aload_0
    //   885: aload_0
    //   886: getfield i : Lb/e/b/k/m/f;
    //   889: aload_0
    //   890: getfield h : Lb/e/b/k/m/f;
    //   893: aload_0
    //   894: getfield e : Lb/e/b/k/m/g;
    //   897: getfield g : I
    //   900: invokevirtual a : (Lb/e/b/k/m/f;Lb/e/b/k/m/f;I)V
    //   903: aload_0
    //   904: getfield b : Lb/e/b/k/e;
    //   907: invokevirtual C : ()Z
    //   910: ifeq -> 1792
    //   913: goto -> 538
    //   916: aload_0
    //   917: getfield e : Lb/e/b/k/m/g;
    //   920: getfield j : Z
    //   923: ifne -> 1103
    //   926: aload_0
    //   927: getfield d : Lb/e/b/k/e$b;
    //   930: getstatic b/e/b/k/e$b.e : Lb/e/b/k/e$b;
    //   933: if_acmpne -> 1103
    //   936: aload_0
    //   937: getfield b : Lb/e/b/k/e;
    //   940: astore #4
    //   942: aload #4
    //   944: getfield k : I
    //   947: istore_1
    //   948: iload_1
    //   949: iconst_2
    //   950: if_icmpeq -> 997
    //   953: iload_1
    //   954: iconst_3
    //   955: if_icmpeq -> 961
    //   958: goto -> 1111
    //   961: aload #4
    //   963: invokevirtual F : ()Z
    //   966: ifne -> 1111
    //   969: aload_0
    //   970: getfield b : Lb/e/b/k/e;
    //   973: astore #4
    //   975: aload #4
    //   977: getfield j : I
    //   980: iconst_3
    //   981: if_icmpne -> 987
    //   984: goto -> 1111
    //   987: aload #4
    //   989: getfield d : Lb/e/b/k/m/j;
    //   992: astore #4
    //   994: goto -> 1019
    //   997: aload #4
    //   999: invokevirtual s : ()Lb/e/b/k/e;
    //   1002: astore #4
    //   1004: aload #4
    //   1006: ifnonnull -> 1012
    //   1009: goto -> 1111
    //   1012: aload #4
    //   1014: getfield e : Lb/e/b/k/m/l;
    //   1017: astore #4
    //   1019: aload #4
    //   1021: getfield e : Lb/e/b/k/m/g;
    //   1024: astore #4
    //   1026: aload_0
    //   1027: getfield e : Lb/e/b/k/m/g;
    //   1030: getfield l : Ljava/util/List;
    //   1033: aload #4
    //   1035: invokeinterface add : (Ljava/lang/Object;)Z
    //   1040: pop
    //   1041: aload #4
    //   1043: getfield k : Ljava/util/List;
    //   1046: aload_0
    //   1047: getfield e : Lb/e/b/k/m/g;
    //   1050: invokeinterface add : (Ljava/lang/Object;)Z
    //   1055: pop
    //   1056: aload_0
    //   1057: getfield e : Lb/e/b/k/m/g;
    //   1060: astore #4
    //   1062: aload #4
    //   1064: iconst_1
    //   1065: putfield b : Z
    //   1068: aload #4
    //   1070: getfield k : Ljava/util/List;
    //   1073: aload_0
    //   1074: getfield h : Lb/e/b/k/m/f;
    //   1077: invokeinterface add : (Ljava/lang/Object;)Z
    //   1082: pop
    //   1083: aload_0
    //   1084: getfield e : Lb/e/b/k/m/g;
    //   1087: getfield k : Ljava/util/List;
    //   1090: aload_0
    //   1091: getfield i : Lb/e/b/k/m/f;
    //   1094: invokeinterface add : (Ljava/lang/Object;)Z
    //   1099: pop
    //   1100: goto -> 1111
    //   1103: aload_0
    //   1104: getfield e : Lb/e/b/k/m/g;
    //   1107: aload_0
    //   1108: invokevirtual b : (Lb/e/b/k/m/d;)V
    //   1111: aload_0
    //   1112: getfield b : Lb/e/b/k/e;
    //   1115: astore #4
    //   1117: aload #4
    //   1119: getfield G : [Lb/e/b/k/d;
    //   1122: astore #5
    //   1124: aload #5
    //   1126: iconst_2
    //   1127: aaload
    //   1128: getfield d : Lb/e/b/k/d;
    //   1131: ifnull -> 1285
    //   1134: aload #5
    //   1136: iconst_3
    //   1137: aaload
    //   1138: getfield d : Lb/e/b/k/d;
    //   1141: ifnull -> 1285
    //   1144: aload #4
    //   1146: invokevirtual F : ()Z
    //   1149: ifeq -> 1194
    //   1152: aload_0
    //   1153: getfield h : Lb/e/b/k/m/f;
    //   1156: aload_0
    //   1157: getfield b : Lb/e/b/k/e;
    //   1160: getfield G : [Lb/e/b/k/d;
    //   1163: iconst_2
    //   1164: aaload
    //   1165: invokevirtual a : ()I
    //   1168: putfield f : I
    //   1171: aload_0
    //   1172: getfield i : Lb/e/b/k/m/f;
    //   1175: aload_0
    //   1176: getfield b : Lb/e/b/k/e;
    //   1179: getfield G : [Lb/e/b/k/d;
    //   1182: iconst_3
    //   1183: aaload
    //   1184: invokevirtual a : ()I
    //   1187: ineg
    //   1188: putfield f : I
    //   1191: goto -> 1243
    //   1194: aload_0
    //   1195: aload_0
    //   1196: getfield b : Lb/e/b/k/e;
    //   1199: getfield G : [Lb/e/b/k/d;
    //   1202: iconst_2
    //   1203: aaload
    //   1204: invokevirtual a : (Lb/e/b/k/d;)Lb/e/b/k/m/f;
    //   1207: astore #4
    //   1209: aload_0
    //   1210: aload_0
    //   1211: getfield b : Lb/e/b/k/e;
    //   1214: getfield G : [Lb/e/b/k/d;
    //   1217: iconst_3
    //   1218: aaload
    //   1219: invokevirtual a : (Lb/e/b/k/d;)Lb/e/b/k/m/f;
    //   1222: astore #5
    //   1224: aload #4
    //   1226: aload_0
    //   1227: invokevirtual b : (Lb/e/b/k/m/d;)V
    //   1230: aload #5
    //   1232: aload_0
    //   1233: invokevirtual b : (Lb/e/b/k/m/d;)V
    //   1236: aload_0
    //   1237: getstatic b/e/b/k/m/m$b.f : Lb/e/b/k/m/m$b;
    //   1240: putfield j : Lb/e/b/k/m/m$b;
    //   1243: aload_0
    //   1244: getfield b : Lb/e/b/k/e;
    //   1247: invokevirtual C : ()Z
    //   1250: ifeq -> 1769
    //   1253: aload_0
    //   1254: getfield k : Lb/e/b/k/m/f;
    //   1257: astore #4
    //   1259: aload_0
    //   1260: getfield h : Lb/e/b/k/m/f;
    //   1263: astore #5
    //   1265: aload_0
    //   1266: getfield l : Lb/e/b/k/m/g;
    //   1269: astore #6
    //   1271: aload_0
    //   1272: aload #4
    //   1274: aload #5
    //   1276: iconst_1
    //   1277: aload #6
    //   1279: invokevirtual a : (Lb/e/b/k/m/f;Lb/e/b/k/m/f;ILb/e/b/k/m/g;)V
    //   1282: goto -> 1769
    //   1285: aload_0
    //   1286: getfield b : Lb/e/b/k/e;
    //   1289: astore #4
    //   1291: aload #4
    //   1293: getfield G : [Lb/e/b/k/d;
    //   1296: astore #5
    //   1298: aload #5
    //   1300: iconst_2
    //   1301: aaload
    //   1302: getfield d : Lb/e/b/k/d;
    //   1305: ifnull -> 1434
    //   1308: aload_0
    //   1309: aload #5
    //   1311: iconst_2
    //   1312: aaload
    //   1313: invokevirtual a : (Lb/e/b/k/d;)Lb/e/b/k/m/f;
    //   1316: astore #4
    //   1318: aload #4
    //   1320: ifnull -> 1769
    //   1323: aload_0
    //   1324: aload_0
    //   1325: getfield h : Lb/e/b/k/m/f;
    //   1328: aload #4
    //   1330: aload_0
    //   1331: getfield b : Lb/e/b/k/e;
    //   1334: getfield G : [Lb/e/b/k/d;
    //   1337: iconst_2
    //   1338: aaload
    //   1339: invokevirtual a : ()I
    //   1342: invokevirtual a : (Lb/e/b/k/m/f;Lb/e/b/k/m/f;I)V
    //   1345: aload_0
    //   1346: aload_0
    //   1347: getfield i : Lb/e/b/k/m/f;
    //   1350: aload_0
    //   1351: getfield h : Lb/e/b/k/m/f;
    //   1354: iconst_1
    //   1355: aload_0
    //   1356: getfield e : Lb/e/b/k/m/g;
    //   1359: invokevirtual a : (Lb/e/b/k/m/f;Lb/e/b/k/m/f;ILb/e/b/k/m/g;)V
    //   1362: aload_0
    //   1363: getfield b : Lb/e/b/k/e;
    //   1366: invokevirtual C : ()Z
    //   1369: ifeq -> 1389
    //   1372: aload_0
    //   1373: aload_0
    //   1374: getfield k : Lb/e/b/k/m/f;
    //   1377: aload_0
    //   1378: getfield h : Lb/e/b/k/m/f;
    //   1381: iconst_1
    //   1382: aload_0
    //   1383: getfield l : Lb/e/b/k/m/g;
    //   1386: invokevirtual a : (Lb/e/b/k/m/f;Lb/e/b/k/m/f;ILb/e/b/k/m/g;)V
    //   1389: aload_0
    //   1390: getfield d : Lb/e/b/k/e$b;
    //   1393: getstatic b/e/b/k/e$b.e : Lb/e/b/k/e$b;
    //   1396: if_acmpne -> 1769
    //   1399: aload_0
    //   1400: getfield b : Lb/e/b/k/e;
    //   1403: invokevirtual h : ()F
    //   1406: fconst_0
    //   1407: fcmpl
    //   1408: ifle -> 1769
    //   1411: aload_0
    //   1412: getfield b : Lb/e/b/k/e;
    //   1415: getfield d : Lb/e/b/k/m/j;
    //   1418: astore #4
    //   1420: aload #4
    //   1422: getfield d : Lb/e/b/k/e$b;
    //   1425: getstatic b/e/b/k/e$b.e : Lb/e/b/k/e$b;
    //   1428: if_acmpne -> 1769
    //   1431: goto -> 1720
    //   1434: aload #5
    //   1436: iconst_3
    //   1437: aaload
    //   1438: getfield d : Lb/e/b/k/d;
    //   1441: ifnull -> 1512
    //   1444: aload_0
    //   1445: aload #5
    //   1447: iconst_3
    //   1448: aaload
    //   1449: invokevirtual a : (Lb/e/b/k/d;)Lb/e/b/k/m/f;
    //   1452: astore #4
    //   1454: aload #4
    //   1456: ifnull -> 1769
    //   1459: aload_0
    //   1460: aload_0
    //   1461: getfield i : Lb/e/b/k/m/f;
    //   1464: aload #4
    //   1466: aload_0
    //   1467: getfield b : Lb/e/b/k/e;
    //   1470: getfield G : [Lb/e/b/k/d;
    //   1473: iconst_3
    //   1474: aaload
    //   1475: invokevirtual a : ()I
    //   1478: ineg
    //   1479: invokevirtual a : (Lb/e/b/k/m/f;Lb/e/b/k/m/f;I)V
    //   1482: aload_0
    //   1483: aload_0
    //   1484: getfield h : Lb/e/b/k/m/f;
    //   1487: aload_0
    //   1488: getfield i : Lb/e/b/k/m/f;
    //   1491: iconst_m1
    //   1492: aload_0
    //   1493: getfield e : Lb/e/b/k/m/g;
    //   1496: invokevirtual a : (Lb/e/b/k/m/f;Lb/e/b/k/m/f;ILb/e/b/k/m/g;)V
    //   1499: aload_0
    //   1500: getfield b : Lb/e/b/k/e;
    //   1503: invokevirtual C : ()Z
    //   1506: ifeq -> 1769
    //   1509: goto -> 1253
    //   1512: aload #5
    //   1514: iconst_4
    //   1515: aaload
    //   1516: getfield d : Lb/e/b/k/d;
    //   1519: ifnull -> 1586
    //   1522: aload_0
    //   1523: aload #5
    //   1525: iconst_4
    //   1526: aaload
    //   1527: invokevirtual a : (Lb/e/b/k/d;)Lb/e/b/k/m/f;
    //   1530: astore #4
    //   1532: aload #4
    //   1534: ifnull -> 1769
    //   1537: aload_0
    //   1538: aload_0
    //   1539: getfield k : Lb/e/b/k/m/f;
    //   1542: aload #4
    //   1544: iconst_0
    //   1545: invokevirtual a : (Lb/e/b/k/m/f;Lb/e/b/k/m/f;I)V
    //   1548: aload_0
    //   1549: aload_0
    //   1550: getfield h : Lb/e/b/k/m/f;
    //   1553: aload_0
    //   1554: getfield k : Lb/e/b/k/m/f;
    //   1557: iconst_m1
    //   1558: aload_0
    //   1559: getfield l : Lb/e/b/k/m/g;
    //   1562: invokevirtual a : (Lb/e/b/k/m/f;Lb/e/b/k/m/f;ILb/e/b/k/m/g;)V
    //   1565: aload_0
    //   1566: getfield i : Lb/e/b/k/m/f;
    //   1569: astore #4
    //   1571: aload_0
    //   1572: getfield h : Lb/e/b/k/m/f;
    //   1575: astore #5
    //   1577: aload_0
    //   1578: getfield e : Lb/e/b/k/m/g;
    //   1581: astore #6
    //   1583: goto -> 1271
    //   1586: aload #4
    //   1588: instanceof b/e/b/k/h
    //   1591: ifne -> 1769
    //   1594: aload #4
    //   1596: invokevirtual s : ()Lb/e/b/k/e;
    //   1599: ifnull -> 1769
    //   1602: aload_0
    //   1603: getfield b : Lb/e/b/k/e;
    //   1606: invokevirtual s : ()Lb/e/b/k/e;
    //   1609: getfield e : Lb/e/b/k/m/l;
    //   1612: getfield h : Lb/e/b/k/m/f;
    //   1615: astore #4
    //   1617: aload_0
    //   1618: aload_0
    //   1619: getfield h : Lb/e/b/k/m/f;
    //   1622: aload #4
    //   1624: aload_0
    //   1625: getfield b : Lb/e/b/k/e;
    //   1628: invokevirtual B : ()I
    //   1631: invokevirtual a : (Lb/e/b/k/m/f;Lb/e/b/k/m/f;I)V
    //   1634: aload_0
    //   1635: aload_0
    //   1636: getfield i : Lb/e/b/k/m/f;
    //   1639: aload_0
    //   1640: getfield h : Lb/e/b/k/m/f;
    //   1643: iconst_1
    //   1644: aload_0
    //   1645: getfield e : Lb/e/b/k/m/g;
    //   1648: invokevirtual a : (Lb/e/b/k/m/f;Lb/e/b/k/m/f;ILb/e/b/k/m/g;)V
    //   1651: aload_0
    //   1652: getfield b : Lb/e/b/k/e;
    //   1655: invokevirtual C : ()Z
    //   1658: ifeq -> 1678
    //   1661: aload_0
    //   1662: aload_0
    //   1663: getfield k : Lb/e/b/k/m/f;
    //   1666: aload_0
    //   1667: getfield h : Lb/e/b/k/m/f;
    //   1670: iconst_1
    //   1671: aload_0
    //   1672: getfield l : Lb/e/b/k/m/g;
    //   1675: invokevirtual a : (Lb/e/b/k/m/f;Lb/e/b/k/m/f;ILb/e/b/k/m/g;)V
    //   1678: aload_0
    //   1679: getfield d : Lb/e/b/k/e$b;
    //   1682: getstatic b/e/b/k/e$b.e : Lb/e/b/k/e$b;
    //   1685: if_acmpne -> 1769
    //   1688: aload_0
    //   1689: getfield b : Lb/e/b/k/e;
    //   1692: invokevirtual h : ()F
    //   1695: fconst_0
    //   1696: fcmpl
    //   1697: ifle -> 1769
    //   1700: aload_0
    //   1701: getfield b : Lb/e/b/k/e;
    //   1704: getfield d : Lb/e/b/k/m/j;
    //   1707: astore #4
    //   1709: aload #4
    //   1711: getfield d : Lb/e/b/k/e$b;
    //   1714: getstatic b/e/b/k/e$b.e : Lb/e/b/k/e$b;
    //   1717: if_acmpne -> 1769
    //   1720: aload #4
    //   1722: getfield e : Lb/e/b/k/m/g;
    //   1725: getfield k : Ljava/util/List;
    //   1728: aload_0
    //   1729: getfield e : Lb/e/b/k/m/g;
    //   1732: invokeinterface add : (Ljava/lang/Object;)Z
    //   1737: pop
    //   1738: aload_0
    //   1739: getfield e : Lb/e/b/k/m/g;
    //   1742: getfield l : Ljava/util/List;
    //   1745: aload_0
    //   1746: getfield b : Lb/e/b/k/e;
    //   1749: getfield d : Lb/e/b/k/m/j;
    //   1752: getfield e : Lb/e/b/k/m/g;
    //   1755: invokeinterface add : (Ljava/lang/Object;)Z
    //   1760: pop
    //   1761: aload_0
    //   1762: getfield e : Lb/e/b/k/m/g;
    //   1765: aload_0
    //   1766: putfield a : Lb/e/b/k/m/d;
    //   1769: aload_0
    //   1770: getfield e : Lb/e/b/k/m/g;
    //   1773: getfield l : Ljava/util/List;
    //   1776: invokeinterface size : ()I
    //   1781: ifne -> 1792
    //   1784: aload_0
    //   1785: getfield e : Lb/e/b/k/m/g;
    //   1788: iconst_1
    //   1789: putfield c : Z
    //   1792: return
  }
  
  public void a(d paramd) {
    // Byte code:
    //   0: getstatic b/e/b/k/m/l$a.a : [I
    //   3: aload_0
    //   4: getfield j : Lb/e/b/k/m/m$b;
    //   7: invokevirtual ordinal : ()I
    //   10: iaload
    //   11: istore_3
    //   12: iload_3
    //   13: iconst_1
    //   14: if_icmpeq -> 61
    //   17: iload_3
    //   18: iconst_2
    //   19: if_icmpeq -> 53
    //   22: iload_3
    //   23: iconst_3
    //   24: if_icmpeq -> 30
    //   27: goto -> 66
    //   30: aload_0
    //   31: getfield b : Lb/e/b/k/e;
    //   34: astore #6
    //   36: aload_0
    //   37: aload_1
    //   38: aload #6
    //   40: getfield z : Lb/e/b/k/d;
    //   43: aload #6
    //   45: getfield B : Lb/e/b/k/d;
    //   48: iconst_1
    //   49: invokevirtual a : (Lb/e/b/k/m/d;Lb/e/b/k/d;Lb/e/b/k/d;I)V
    //   52: return
    //   53: aload_0
    //   54: aload_1
    //   55: invokevirtual b : (Lb/e/b/k/m/d;)V
    //   58: goto -> 66
    //   61: aload_0
    //   62: aload_1
    //   63: invokevirtual c : (Lb/e/b/k/m/d;)V
    //   66: aload_0
    //   67: getfield e : Lb/e/b/k/m/g;
    //   70: astore_1
    //   71: aload_1
    //   72: getfield c : Z
    //   75: ifeq -> 263
    //   78: aload_1
    //   79: getfield j : Z
    //   82: ifne -> 263
    //   85: aload_0
    //   86: getfield d : Lb/e/b/k/e$b;
    //   89: getstatic b/e/b/k/e$b.e : Lb/e/b/k/e$b;
    //   92: if_acmpne -> 263
    //   95: aload_0
    //   96: getfield b : Lb/e/b/k/e;
    //   99: astore_1
    //   100: aload_1
    //   101: getfield k : I
    //   104: istore_3
    //   105: iload_3
    //   106: iconst_2
    //   107: if_icmpeq -> 211
    //   110: iload_3
    //   111: iconst_3
    //   112: if_icmpeq -> 118
    //   115: goto -> 263
    //   118: aload_1
    //   119: getfield d : Lb/e/b/k/m/j;
    //   122: getfield e : Lb/e/b/k/m/g;
    //   125: getfield j : Z
    //   128: ifeq -> 263
    //   131: aload_1
    //   132: invokevirtual i : ()I
    //   135: istore_3
    //   136: iload_3
    //   137: iconst_m1
    //   138: if_icmpeq -> 180
    //   141: iload_3
    //   142: ifeq -> 155
    //   145: iload_3
    //   146: iconst_1
    //   147: if_icmpeq -> 180
    //   150: iconst_0
    //   151: istore_3
    //   152: goto -> 255
    //   155: aload_0
    //   156: getfield b : Lb/e/b/k/e;
    //   159: astore_1
    //   160: aload_1
    //   161: getfield d : Lb/e/b/k/m/j;
    //   164: getfield e : Lb/e/b/k/m/g;
    //   167: getfield g : I
    //   170: i2f
    //   171: aload_1
    //   172: invokevirtual h : ()F
    //   175: fmul
    //   176: fstore_2
    //   177: goto -> 202
    //   180: aload_0
    //   181: getfield b : Lb/e/b/k/e;
    //   184: astore_1
    //   185: aload_1
    //   186: getfield d : Lb/e/b/k/m/j;
    //   189: getfield e : Lb/e/b/k/m/g;
    //   192: getfield g : I
    //   195: i2f
    //   196: aload_1
    //   197: invokevirtual h : ()F
    //   200: fdiv
    //   201: fstore_2
    //   202: fload_2
    //   203: ldc 0.5
    //   205: fadd
    //   206: f2i
    //   207: istore_3
    //   208: goto -> 255
    //   211: aload_1
    //   212: invokevirtual s : ()Lb/e/b/k/e;
    //   215: astore_1
    //   216: aload_1
    //   217: ifnull -> 263
    //   220: aload_1
    //   221: getfield e : Lb/e/b/k/m/l;
    //   224: getfield e : Lb/e/b/k/m/g;
    //   227: astore_1
    //   228: aload_1
    //   229: getfield j : Z
    //   232: ifeq -> 263
    //   235: aload_0
    //   236: getfield b : Lb/e/b/k/e;
    //   239: getfield r : F
    //   242: fstore_2
    //   243: aload_1
    //   244: getfield g : I
    //   247: i2f
    //   248: fload_2
    //   249: fmul
    //   250: ldc 0.5
    //   252: fadd
    //   253: f2i
    //   254: istore_3
    //   255: aload_0
    //   256: getfield e : Lb/e/b/k/m/g;
    //   259: iload_3
    //   260: invokevirtual a : (I)V
    //   263: aload_0
    //   264: getfield h : Lb/e/b/k/m/f;
    //   267: astore_1
    //   268: aload_1
    //   269: getfield c : Z
    //   272: ifeq -> 796
    //   275: aload_0
    //   276: getfield i : Lb/e/b/k/m/f;
    //   279: astore #6
    //   281: aload #6
    //   283: getfield c : Z
    //   286: ifne -> 290
    //   289: return
    //   290: aload_1
    //   291: getfield j : Z
    //   294: ifeq -> 316
    //   297: aload #6
    //   299: getfield j : Z
    //   302: ifeq -> 316
    //   305: aload_0
    //   306: getfield e : Lb/e/b/k/m/g;
    //   309: getfield j : Z
    //   312: ifeq -> 316
    //   315: return
    //   316: aload_0
    //   317: getfield e : Lb/e/b/k/m/g;
    //   320: getfield j : Z
    //   323: ifne -> 451
    //   326: aload_0
    //   327: getfield d : Lb/e/b/k/e$b;
    //   330: getstatic b/e/b/k/e$b.e : Lb/e/b/k/e$b;
    //   333: if_acmpne -> 451
    //   336: aload_0
    //   337: getfield b : Lb/e/b/k/e;
    //   340: astore_1
    //   341: aload_1
    //   342: getfield j : I
    //   345: ifne -> 451
    //   348: aload_1
    //   349: invokevirtual F : ()Z
    //   352: ifne -> 451
    //   355: aload_0
    //   356: getfield h : Lb/e/b/k/m/f;
    //   359: getfield l : Ljava/util/List;
    //   362: iconst_0
    //   363: invokeinterface get : (I)Ljava/lang/Object;
    //   368: checkcast b/e/b/k/m/f
    //   371: astore #6
    //   373: aload_0
    //   374: getfield i : Lb/e/b/k/m/f;
    //   377: getfield l : Ljava/util/List;
    //   380: iconst_0
    //   381: invokeinterface get : (I)Ljava/lang/Object;
    //   386: checkcast b/e/b/k/m/f
    //   389: astore_1
    //   390: aload #6
    //   392: getfield g : I
    //   395: istore_3
    //   396: aload_0
    //   397: getfield h : Lb/e/b/k/m/f;
    //   400: astore #6
    //   402: iload_3
    //   403: aload #6
    //   405: getfield f : I
    //   408: iadd
    //   409: istore_3
    //   410: aload_1
    //   411: getfield g : I
    //   414: aload_0
    //   415: getfield i : Lb/e/b/k/m/f;
    //   418: getfield f : I
    //   421: iadd
    //   422: istore #4
    //   424: aload #6
    //   426: iload_3
    //   427: invokevirtual a : (I)V
    //   430: aload_0
    //   431: getfield i : Lb/e/b/k/m/f;
    //   434: iload #4
    //   436: invokevirtual a : (I)V
    //   439: aload_0
    //   440: getfield e : Lb/e/b/k/m/g;
    //   443: iload #4
    //   445: iload_3
    //   446: isub
    //   447: invokevirtual a : (I)V
    //   450: return
    //   451: aload_0
    //   452: getfield e : Lb/e/b/k/m/g;
    //   455: getfield j : Z
    //   458: ifne -> 608
    //   461: aload_0
    //   462: getfield d : Lb/e/b/k/e$b;
    //   465: getstatic b/e/b/k/e$b.e : Lb/e/b/k/e$b;
    //   468: if_acmpne -> 608
    //   471: aload_0
    //   472: getfield a : I
    //   475: iconst_1
    //   476: if_icmpne -> 608
    //   479: aload_0
    //   480: getfield h : Lb/e/b/k/m/f;
    //   483: getfield l : Ljava/util/List;
    //   486: invokeinterface size : ()I
    //   491: ifle -> 608
    //   494: aload_0
    //   495: getfield i : Lb/e/b/k/m/f;
    //   498: getfield l : Ljava/util/List;
    //   501: invokeinterface size : ()I
    //   506: ifle -> 608
    //   509: aload_0
    //   510: getfield h : Lb/e/b/k/m/f;
    //   513: getfield l : Ljava/util/List;
    //   516: iconst_0
    //   517: invokeinterface get : (I)Ljava/lang/Object;
    //   522: checkcast b/e/b/k/m/f
    //   525: astore_1
    //   526: aload_0
    //   527: getfield i : Lb/e/b/k/m/f;
    //   530: getfield l : Ljava/util/List;
    //   533: iconst_0
    //   534: invokeinterface get : (I)Ljava/lang/Object;
    //   539: checkcast b/e/b/k/m/f
    //   542: astore #6
    //   544: aload_1
    //   545: getfield g : I
    //   548: istore_3
    //   549: aload_0
    //   550: getfield h : Lb/e/b/k/m/f;
    //   553: getfield f : I
    //   556: istore #4
    //   558: aload #6
    //   560: getfield g : I
    //   563: aload_0
    //   564: getfield i : Lb/e/b/k/m/f;
    //   567: getfield f : I
    //   570: iadd
    //   571: iload_3
    //   572: iload #4
    //   574: iadd
    //   575: isub
    //   576: istore_3
    //   577: aload_0
    //   578: getfield e : Lb/e/b/k/m/g;
    //   581: astore_1
    //   582: aload_1
    //   583: getfield m : I
    //   586: istore #4
    //   588: iload_3
    //   589: iload #4
    //   591: if_icmpge -> 602
    //   594: aload_1
    //   595: iload_3
    //   596: invokevirtual a : (I)V
    //   599: goto -> 608
    //   602: aload_1
    //   603: iload #4
    //   605: invokevirtual a : (I)V
    //   608: aload_0
    //   609: getfield e : Lb/e/b/k/m/g;
    //   612: getfield j : Z
    //   615: ifne -> 619
    //   618: return
    //   619: aload_0
    //   620: getfield h : Lb/e/b/k/m/f;
    //   623: getfield l : Ljava/util/List;
    //   626: invokeinterface size : ()I
    //   631: ifle -> 796
    //   634: aload_0
    //   635: getfield i : Lb/e/b/k/m/f;
    //   638: getfield l : Ljava/util/List;
    //   641: invokeinterface size : ()I
    //   646: ifle -> 796
    //   649: aload_0
    //   650: getfield h : Lb/e/b/k/m/f;
    //   653: getfield l : Ljava/util/List;
    //   656: iconst_0
    //   657: invokeinterface get : (I)Ljava/lang/Object;
    //   662: checkcast b/e/b/k/m/f
    //   665: astore_1
    //   666: aload_0
    //   667: getfield i : Lb/e/b/k/m/f;
    //   670: getfield l : Ljava/util/List;
    //   673: iconst_0
    //   674: invokeinterface get : (I)Ljava/lang/Object;
    //   679: checkcast b/e/b/k/m/f
    //   682: astore #6
    //   684: aload_1
    //   685: getfield g : I
    //   688: aload_0
    //   689: getfield h : Lb/e/b/k/m/f;
    //   692: getfield f : I
    //   695: iadd
    //   696: istore_3
    //   697: aload #6
    //   699: getfield g : I
    //   702: aload_0
    //   703: getfield i : Lb/e/b/k/m/f;
    //   706: getfield f : I
    //   709: iadd
    //   710: istore #4
    //   712: aload_0
    //   713: getfield b : Lb/e/b/k/e;
    //   716: invokevirtual u : ()F
    //   719: fstore_2
    //   720: aload_1
    //   721: aload #6
    //   723: if_acmpne -> 741
    //   726: aload_1
    //   727: getfield g : I
    //   730: istore_3
    //   731: aload #6
    //   733: getfield g : I
    //   736: istore #4
    //   738: ldc 0.5
    //   740: fstore_2
    //   741: aload_0
    //   742: getfield e : Lb/e/b/k/m/g;
    //   745: getfield g : I
    //   748: istore #5
    //   750: aload_0
    //   751: getfield h : Lb/e/b/k/m/f;
    //   754: iload_3
    //   755: i2f
    //   756: ldc 0.5
    //   758: fadd
    //   759: iload #4
    //   761: iload_3
    //   762: isub
    //   763: iload #5
    //   765: isub
    //   766: i2f
    //   767: fload_2
    //   768: fmul
    //   769: fadd
    //   770: f2i
    //   771: invokevirtual a : (I)V
    //   774: aload_0
    //   775: getfield i : Lb/e/b/k/m/f;
    //   778: aload_0
    //   779: getfield h : Lb/e/b/k/m/f;
    //   782: getfield g : I
    //   785: aload_0
    //   786: getfield e : Lb/e/b/k/m/g;
    //   789: getfield g : I
    //   792: iadd
    //   793: invokevirtual a : (I)V
    //   796: return
  }
  
  public void b() {
    f f1 = this.h;
    if (f1.j)
      this.b.r(f1.g); 
  }
  
  void c() {
    this.c = null;
    this.h.a();
    this.i.a();
    this.k.a();
    this.e.a();
    this.g = false;
  }
  
  boolean f() {
    return (this.d == e.b.e) ? ((this.b.k == 0)) : true;
  }
  
  void g() {
    this.g = false;
    this.h.a();
    this.h.j = false;
    this.i.a();
    this.i.j = false;
    this.k.a();
    this.k.j = false;
    this.e.j = false;
  }
  
  public String toString() {
    StringBuilder stringBuilder = new StringBuilder();
    stringBuilder.append("VerticalRun ");
    stringBuilder.append(this.b.g());
    return stringBuilder.toString();
  }
}


/* Location:              /home/yc/Downloads/LeaveHomeSafe.jar!/b/e/b/k/m/l.class
 * Java compiler version: 6 (50.0)
 * JD-Core Version:       1.1.3
 */