package e.f.c.w;

import e.f.c.e;
import e.f.c.j;
import e.f.c.n;
import e.f.c.s.a;
import java.util.Map;

public final class b extends k {
  static final int[][] a;
  
  static {
    int[] arrayOfInt1 = { 1, 3, 1, 2, 2, 2 };
    int[] arrayOfInt2 = { 1, 2, 2, 2, 1, 3 };
    int[] arrayOfInt3 = { 1, 2, 2, 3, 1, 2 };
    int[] arrayOfInt4 = { 2, 3, 1, 2, 1, 2 };
    int[] arrayOfInt5 = { 1, 1, 2, 2, 3, 2 };
    int[] arrayOfInt6 = { 1, 2, 2, 1, 3, 2 };
    int[] arrayOfInt7 = { 2, 2, 1, 1, 3, 2 };
    int[] arrayOfInt8 = { 2, 1, 1, 3, 1, 3 };
    int[] arrayOfInt9 = { 2, 3, 1, 1, 1, 3 };
    int[] arrayOfInt10 = { 2, 3, 1, 3, 1, 1 };
    int[] arrayOfInt11 = { 1, 1, 3, 1, 2, 3 };
    int[] arrayOfInt12 = { 1, 1, 3, 3, 2, 1 };
    int[] arrayOfInt13 = { 2, 1, 3, 3, 1, 1 };
    int[] arrayOfInt14 = { 1, 2, 2, 1, 1, 4 };
    int[] arrayOfInt15 = { 2, 4, 1, 1, 1, 2 };
    int[] arrayOfInt16 = { 1, 2, 4, 1, 1, 2 };
    a = new int[][] { 
        { 2, 1, 2, 2, 2, 2 }, { 2, 2, 2, 1, 2, 2 }, { 2, 2, 2, 2, 2, 1 }, { 1, 2, 1, 2, 2, 3 }, { 1, 2, 1, 3, 2, 2 }, arrayOfInt1, arrayOfInt2, arrayOfInt3, { 1, 3, 2, 2, 1, 2 }, { 2, 2, 1, 2, 1, 3 }, 
        { 2, 2, 1, 3, 1, 2 }, arrayOfInt4, arrayOfInt5, arrayOfInt6, { 1, 2, 2, 2, 3, 1 }, { 1, 1, 3, 2, 2, 2 }, { 1, 2, 3, 1, 2, 2 }, { 1, 2, 3, 2, 2, 1 }, { 2, 2, 3, 2, 1, 1 }, arrayOfInt7, 
        { 2, 2, 1, 2, 3, 1 }, { 2, 1, 3, 2, 1, 2 }, { 2, 2, 3, 1, 1, 2 }, { 3, 1, 2, 1, 3, 1 }, { 3, 1, 1, 2, 2, 2 }, { 3, 2, 1, 1, 2, 2 }, { 3, 2, 1, 2, 2, 1 }, { 3, 1, 2, 2, 1, 2 }, { 3, 2, 2, 1, 1, 2 }, { 3, 2, 2, 2, 1, 1 }, 
        { 2, 1, 2, 1, 2, 3 }, { 2, 1, 2, 3, 2, 1 }, { 2, 3, 2, 1, 2, 1 }, { 1, 1, 1, 3, 2, 3 }, { 1, 3, 1, 1, 2, 3 }, { 1, 3, 1, 3, 2, 1 }, { 1, 1, 2, 3, 1, 3 }, { 1, 3, 2, 1, 1, 3 }, { 1, 3, 2, 3, 1, 1 }, arrayOfInt8, 
        arrayOfInt9, arrayOfInt10, { 1, 1, 2, 1, 3, 3 }, { 1, 1, 2, 3, 3, 1 }, { 1, 3, 2, 1, 3, 1 }, arrayOfInt11, arrayOfInt12, { 1, 3, 3, 1, 2, 1 }, { 3, 1, 3, 1, 2, 1 }, { 2, 1, 1, 3, 3, 1 }, 
        { 2, 3, 1, 1, 3, 1 }, { 2, 1, 3, 1, 1, 3 }, arrayOfInt13, { 2, 1, 3, 1, 3, 1 }, { 3, 1, 1, 1, 2, 3 }, { 3, 1, 1, 3, 2, 1 }, { 3, 3, 1, 1, 2, 1 }, { 3, 1, 2, 1, 1, 3 }, { 3, 1, 2, 3, 1, 1 }, { 3, 3, 2, 1, 1, 1 }, 
        { 3, 1, 4, 1, 1, 1 }, { 2, 2, 1, 4, 1, 1 }, { 4, 3, 1, 1, 1, 1 }, { 1, 1, 1, 2, 2, 4 }, { 1, 1, 1, 4, 2, 2 }, { 1, 2, 1, 1, 2, 4 }, { 1, 2, 1, 4, 2, 1 }, { 1, 4, 1, 1, 2, 2 }, { 1, 4, 1, 2, 2, 1 }, { 1, 1, 2, 2, 1, 4 }, 
        { 1, 1, 2, 4, 1, 2 }, arrayOfInt14, { 1, 2, 2, 4, 1, 1 }, { 1, 4, 2, 1, 1, 2 }, { 1, 4, 2, 2, 1, 1 }, { 2, 4, 1, 2, 1, 1 }, { 2, 2, 1, 1, 1, 4 }, { 4, 1, 3, 1, 1, 1 }, arrayOfInt15, { 1, 3, 4, 1, 1, 1 }, 
        { 1, 1, 1, 2, 4, 2 }, { 1, 2, 1, 1, 4, 2 }, { 1, 2, 1, 2, 4, 1 }, { 1, 1, 4, 2, 1, 2 }, arrayOfInt16, { 1, 2, 4, 2, 1, 1 }, { 4, 1, 1, 2, 1, 2 }, { 4, 2, 1, 1, 1, 2 }, { 4, 2, 1, 2, 1, 1 }, { 2, 1, 2, 1, 4, 1 }, 
        { 2, 1, 4, 1, 2, 1 }, { 4, 1, 2, 1, 2, 1 }, { 1, 1, 1, 1, 4, 3 }, { 1, 1, 1, 3, 4, 1 }, { 1, 3, 1, 1, 4, 1 }, { 1, 1, 4, 1, 1, 3 }, { 1, 1, 4, 3, 1, 1 }, { 4, 1, 1, 1, 1, 3 }, { 4, 1, 1, 3, 1, 1 }, { 1, 1, 3, 1, 4, 1 }, 
        { 1, 1, 4, 1, 3, 1 }, { 3, 1, 1, 1, 4, 1 }, { 4, 1, 1, 1, 3, 1 }, { 2, 1, 1, 4, 1, 2 }, { 2, 1, 1, 2, 1, 4 }, { 2, 1, 1, 2, 3, 2 }, { 2, 3, 3, 1, 1, 1, 2 } };
  }
  
  private static int a(a parama, int[] paramArrayOfint, int paramInt) {
    k.a(parama, paramInt, paramArrayOfint);
    float f = 0.25F;
    int i = -1;
    paramInt = 0;
    while (true) {
      int[][] arrayOfInt = a;
      if (paramInt < arrayOfInt.length) {
        float f2 = k.a(paramArrayOfint, arrayOfInt[paramInt], 0.7F);
        float f1 = f;
        if (f2 < f) {
          i = paramInt;
          f1 = f2;
        } 
        paramInt++;
        f = f1;
        continue;
      } 
      if (i >= 0)
        return i; 
      j j = j.a();
      throw j;
    } 
  }
  
  private static int[] a(a parama) {
    int i1 = parama.c();
    int m = parama.b(0);
    int[] arrayOfInt = new int[6];
    int i = m;
    boolean bool = false;
    int n = 0;
    while (m < i1) {
      int i2;
      if (parama.a(m) != bool) {
        arrayOfInt[n] = arrayOfInt[n] + 1;
        i2 = i;
      } else {
        if (n == 5) {
          float f = 0.25F;
          i2 = 103;
          int i4 = -1;
          while (i2 <= 105) {
            float f2 = k.a(arrayOfInt, a[i2], 0.7F);
            float f1 = f;
            if (f2 < f) {
              i4 = i2;
              f1 = f2;
            } 
            i2++;
            f = f1;
          } 
          if (i4 >= 0 && parama.a(Math.max(0, i - (m - i) / 2), i, false))
            return new int[] { i, m, i4 }; 
          i2 = i + arrayOfInt[0] + arrayOfInt[1];
          i = n - 1;
          System.arraycopy(arrayOfInt, 2, arrayOfInt, 0, i);
          arrayOfInt[i] = 0;
          arrayOfInt[n] = 0;
          i = n - 1;
        } else {
          n++;
          i2 = i;
          i = n;
        } 
        arrayOfInt[i] = 1;
        int i3 = bool ^ true;
        n = i;
      } 
      m++;
      i = i2;
    } 
    j j = j.a();
    throw j;
  }
  
  public n a(int paramInt, a parama, Map<e, ?> paramMap) {
    // Byte code:
    //   0: aload_3
    //   1: ifnull -> 22
    //   4: aload_3
    //   5: getstatic e/f/c/e.j : Le/f/c/e;
    //   8: invokeinterface containsKey : (Ljava/lang/Object;)Z
    //   13: ifeq -> 22
    //   16: iconst_1
    //   17: istore #18
    //   19: goto -> 25
    //   22: iconst_0
    //   23: istore #18
    //   25: aload_2
    //   26: invokestatic a : (Le/f/c/s/a;)[I
    //   29: astore #25
    //   31: aload #25
    //   33: iconst_2
    //   34: iaload
    //   35: istore #14
    //   37: new java/util/ArrayList
    //   40: dup
    //   41: bipush #20
    //   43: invokespecial <init> : (I)V
    //   46: astore_3
    //   47: aload_3
    //   48: iload #14
    //   50: i2b
    //   51: invokestatic valueOf : (B)Ljava/lang/Byte;
    //   54: invokeinterface add : (Ljava/lang/Object;)Z
    //   59: pop
    //   60: iload #14
    //   62: tableswitch default -> 88, 103 -> 106, 104 -> 99, 105 -> 92
    //   88: invokestatic a : ()Le/f/c/f;
    //   91: athrow
    //   92: bipush #99
    //   94: istore #8
    //   96: goto -> 110
    //   99: bipush #100
    //   101: istore #8
    //   103: goto -> 110
    //   106: bipush #101
    //   108: istore #8
    //   110: new java/lang/StringBuilder
    //   113: dup
    //   114: bipush #20
    //   116: invokespecial <init> : (I)V
    //   119: astore #24
    //   121: aload #25
    //   123: iconst_0
    //   124: iaload
    //   125: istore #17
    //   127: aload #25
    //   129: iconst_1
    //   130: iaload
    //   131: istore #13
    //   133: bipush #6
    //   135: newarray int
    //   137: astore #26
    //   139: iload #8
    //   141: istore #10
    //   143: iconst_0
    //   144: istore #12
    //   146: iconst_0
    //   147: istore #11
    //   149: iconst_0
    //   150: istore #23
    //   152: iconst_0
    //   153: istore #15
    //   155: iconst_0
    //   156: istore #9
    //   158: iconst_0
    //   159: istore #16
    //   161: iconst_1
    //   162: istore #8
    //   164: iconst_0
    //   165: istore #19
    //   167: iload #9
    //   169: istore #20
    //   171: iload #11
    //   173: ifne -> 1173
    //   176: aload_2
    //   177: aload #26
    //   179: iload #13
    //   181: invokestatic a : (Le/f/c/s/a;[II)I
    //   184: istore #23
    //   186: aload_3
    //   187: iload #23
    //   189: i2b
    //   190: invokestatic valueOf : (B)Ljava/lang/Byte;
    //   193: invokeinterface add : (Ljava/lang/Object;)Z
    //   198: pop
    //   199: iload #23
    //   201: bipush #106
    //   203: if_icmpeq -> 209
    //   206: iconst_1
    //   207: istore #8
    //   209: iload #14
    //   211: istore #22
    //   213: iload #16
    //   215: istore #21
    //   217: iload #23
    //   219: bipush #106
    //   221: if_icmpeq -> 240
    //   224: iload #16
    //   226: iconst_1
    //   227: iadd
    //   228: istore #21
    //   230: iload #14
    //   232: iload #21
    //   234: iload #23
    //   236: imul
    //   237: iadd
    //   238: istore #22
    //   240: iload #13
    //   242: istore #16
    //   244: iconst_0
    //   245: istore #9
    //   247: iload #9
    //   249: bipush #6
    //   251: if_icmpge -> 273
    //   254: iload #16
    //   256: aload #26
    //   258: iload #9
    //   260: iaload
    //   261: iadd
    //   262: istore #16
    //   264: iload #9
    //   266: iconst_1
    //   267: iadd
    //   268: istore #9
    //   270: goto -> 247
    //   273: iload #23
    //   275: tableswitch default -> 300, 103 -> 335, 104 -> 335, 105 -> 335
    //   300: iload #10
    //   302: tableswitch default -> 328, 99 -> 909, 100 -> 606, 101 -> 339
    //   328: iload #8
    //   330: istore #9
    //   332: goto -> 1081
    //   335: invokestatic a : ()Le/f/c/f;
    //   338: athrow
    //   339: iload #23
    //   341: bipush #64
    //   343: if_icmpge -> 377
    //   346: iload #12
    //   348: iload #15
    //   350: if_icmpne -> 363
    //   353: iload #23
    //   355: bipush #32
    //   357: iadd
    //   358: istore #9
    //   360: goto -> 641
    //   363: iload #23
    //   365: bipush #32
    //   367: iadd
    //   368: sipush #128
    //   371: iadd
    //   372: istore #9
    //   374: goto -> 641
    //   377: iload #23
    //   379: bipush #96
    //   381: if_icmpge -> 411
    //   384: iload #12
    //   386: iload #15
    //   388: if_icmpne -> 401
    //   391: iload #23
    //   393: bipush #64
    //   395: isub
    //   396: istore #9
    //   398: goto -> 641
    //   401: iload #23
    //   403: bipush #64
    //   405: iadd
    //   406: istore #9
    //   408: goto -> 641
    //   411: iload #23
    //   413: bipush #106
    //   415: if_icmpeq -> 421
    //   418: iconst_0
    //   419: istore #8
    //   421: iload #8
    //   423: istore #9
    //   425: iload #23
    //   427: bipush #106
    //   429: if_icmpeq -> 880
    //   432: iload #8
    //   434: istore #14
    //   436: iload #11
    //   438: istore #17
    //   440: iload #8
    //   442: istore #9
    //   444: iload #23
    //   446: tableswitch default -> 488, 96 -> 883, 97 -> 883, 98 -> 599, 99 -> 859, 100 -> 592, 101 -> 558, 102 -> 499
    //   488: iload #11
    //   490: istore #17
    //   492: iload #8
    //   494: istore #9
    //   496: goto -> 883
    //   499: iload #11
    //   501: istore #17
    //   503: iload #8
    //   505: istore #9
    //   507: iload #18
    //   509: ifeq -> 883
    //   512: iload #8
    //   514: istore #9
    //   516: aload #24
    //   518: invokevirtual length : ()I
    //   521: ifne -> 543
    //   524: aload #24
    //   526: ldc ']C1'
    //   528: invokevirtual append : (Ljava/lang/String;)Ljava/lang/StringBuilder;
    //   531: pop
    //   532: iload #11
    //   534: istore #17
    //   536: iload #8
    //   538: istore #9
    //   540: goto -> 883
    //   543: aload #24
    //   545: bipush #29
    //   547: invokevirtual append : (C)Ljava/lang/StringBuilder;
    //   550: pop
    //   551: iload #11
    //   553: istore #17
    //   555: goto -> 883
    //   558: iload #15
    //   560: ifne -> 571
    //   563: iload #12
    //   565: ifeq -> 571
    //   568: goto -> 808
    //   571: iload #8
    //   573: istore #14
    //   575: iload #15
    //   577: ifeq -> 838
    //   580: iload #8
    //   582: istore #14
    //   584: iload #12
    //   586: ifeq -> 838
    //   589: goto -> 832
    //   592: bipush #100
    //   594: istore #10
    //   596: goto -> 891
    //   599: bipush #100
    //   601: istore #10
    //   603: goto -> 874
    //   606: iload #23
    //   608: bipush #96
    //   610: if_icmpge -> 675
    //   613: iload #12
    //   615: iload #15
    //   617: if_icmpne -> 630
    //   620: iload #23
    //   622: bipush #32
    //   624: iadd
    //   625: istore #9
    //   627: goto -> 641
    //   630: iload #23
    //   632: bipush #32
    //   634: iadd
    //   635: sipush #128
    //   638: iadd
    //   639: istore #9
    //   641: aload #24
    //   643: iload #9
    //   645: i2c
    //   646: invokevirtual append : (C)Ljava/lang/StringBuilder;
    //   649: pop
    //   650: iload #15
    //   652: istore #14
    //   654: iconst_0
    //   655: istore #9
    //   657: iconst_0
    //   658: istore #17
    //   660: iload #10
    //   662: istore #12
    //   664: iload #14
    //   666: istore #15
    //   668: iload #17
    //   670: istore #10
    //   672: goto -> 1100
    //   675: iload #23
    //   677: bipush #106
    //   679: if_icmpeq -> 685
    //   682: iconst_0
    //   683: istore #8
    //   685: iload #8
    //   687: istore #9
    //   689: iload #23
    //   691: bipush #106
    //   693: if_icmpeq -> 880
    //   696: iload #8
    //   698: istore #14
    //   700: iload #11
    //   702: istore #17
    //   704: iload #8
    //   706: istore #9
    //   708: iload #23
    //   710: tableswitch default -> 752, 96 -> 883, 97 -> 883, 98 -> 870, 99 -> 859, 100 -> 798, 101 -> 791, 102 -> 763
    //   752: iload #11
    //   754: istore #17
    //   756: iload #8
    //   758: istore #9
    //   760: goto -> 883
    //   763: iload #11
    //   765: istore #17
    //   767: iload #8
    //   769: istore #9
    //   771: iload #18
    //   773: ifeq -> 883
    //   776: iload #8
    //   778: istore #9
    //   780: aload #24
    //   782: invokevirtual length : ()I
    //   785: ifne -> 543
    //   788: goto -> 524
    //   791: bipush #101
    //   793: istore #10
    //   795: goto -> 891
    //   798: iload #15
    //   800: ifne -> 814
    //   803: iload #12
    //   805: ifeq -> 814
    //   808: iconst_1
    //   809: istore #14
    //   811: goto -> 654
    //   814: iload #8
    //   816: istore #14
    //   818: iload #15
    //   820: ifeq -> 838
    //   823: iload #8
    //   825: istore #14
    //   827: iload #12
    //   829: ifeq -> 838
    //   832: iconst_0
    //   833: istore #14
    //   835: goto -> 654
    //   838: iconst_0
    //   839: istore #9
    //   841: iconst_1
    //   842: istore #8
    //   844: iload #10
    //   846: istore #12
    //   848: iload #8
    //   850: istore #10
    //   852: iload #14
    //   854: istore #8
    //   856: goto -> 1100
    //   859: bipush #99
    //   861: istore #10
    //   863: iload #14
    //   865: istore #8
    //   867: goto -> 891
    //   870: bipush #101
    //   872: istore #10
    //   874: iconst_1
    //   875: istore #9
    //   877: goto -> 894
    //   880: iconst_1
    //   881: istore #17
    //   883: iload #9
    //   885: istore #8
    //   887: iload #17
    //   889: istore #11
    //   891: iconst_0
    //   892: istore #9
    //   894: iload #12
    //   896: istore #14
    //   898: iload #10
    //   900: istore #12
    //   902: iload #14
    //   904: istore #10
    //   906: goto -> 1100
    //   909: iload #23
    //   911: bipush #100
    //   913: if_icmpge -> 946
    //   916: iload #23
    //   918: bipush #10
    //   920: if_icmpge -> 931
    //   923: aload #24
    //   925: bipush #48
    //   927: invokevirtual append : (C)Ljava/lang/StringBuilder;
    //   930: pop
    //   931: aload #24
    //   933: iload #23
    //   935: invokevirtual append : (I)Ljava/lang/StringBuilder;
    //   938: pop
    //   939: iload #8
    //   941: istore #9
    //   943: goto -> 1081
    //   946: iload #23
    //   948: bipush #106
    //   950: if_icmpeq -> 956
    //   953: iconst_0
    //   954: istore #8
    //   956: iload #23
    //   958: bipush #106
    //   960: if_icmpeq -> 1060
    //   963: iload #23
    //   965: tableswitch default -> 992, 100 -> 1053, 101 -> 1046, 102 -> 999
    //   992: iload #8
    //   994: istore #9
    //   996: goto -> 1081
    //   999: iload #8
    //   1001: istore #9
    //   1003: iload #18
    //   1005: ifeq -> 1081
    //   1008: aload #24
    //   1010: invokevirtual length : ()I
    //   1013: ifne -> 1031
    //   1016: aload #24
    //   1018: ldc ']C1'
    //   1020: invokevirtual append : (Ljava/lang/String;)Ljava/lang/StringBuilder;
    //   1023: pop
    //   1024: iload #8
    //   1026: istore #9
    //   1028: goto -> 1081
    //   1031: aload #24
    //   1033: bipush #29
    //   1035: invokevirtual append : (C)Ljava/lang/StringBuilder;
    //   1038: pop
    //   1039: iload #8
    //   1041: istore #9
    //   1043: goto -> 1081
    //   1046: bipush #101
    //   1048: istore #14
    //   1050: goto -> 1089
    //   1053: bipush #100
    //   1055: istore #14
    //   1057: goto -> 1089
    //   1060: iload #12
    //   1062: istore #14
    //   1064: iconst_0
    //   1065: istore #9
    //   1067: iconst_1
    //   1068: istore #11
    //   1070: iload #10
    //   1072: istore #12
    //   1074: iload #14
    //   1076: istore #10
    //   1078: goto -> 1100
    //   1081: iload #9
    //   1083: istore #8
    //   1085: iload #10
    //   1087: istore #14
    //   1089: iload #12
    //   1091: istore #10
    //   1093: iconst_0
    //   1094: istore #9
    //   1096: iload #14
    //   1098: istore #12
    //   1100: iload #19
    //   1102: ifeq -> 1126
    //   1105: iload #12
    //   1107: bipush #101
    //   1109: if_icmpne -> 1119
    //   1112: bipush #100
    //   1114: istore #12
    //   1116: goto -> 1126
    //   1119: bipush #101
    //   1121: istore #12
    //   1123: goto -> 1126
    //   1126: iload #10
    //   1128: istore #19
    //   1130: iload #13
    //   1132: istore #17
    //   1134: iload #16
    //   1136: istore #13
    //   1138: iload #23
    //   1140: istore #14
    //   1142: iload #12
    //   1144: istore #10
    //   1146: iload #19
    //   1148: istore #12
    //   1150: iload #20
    //   1152: istore #23
    //   1154: iload #9
    //   1156: istore #19
    //   1158: iload #14
    //   1160: istore #9
    //   1162: iload #22
    //   1164: istore #14
    //   1166: iload #21
    //   1168: istore #16
    //   1170: goto -> 167
    //   1173: aload_2
    //   1174: iload #13
    //   1176: invokevirtual c : (I)I
    //   1179: istore #9
    //   1181: aload_2
    //   1182: iload #9
    //   1184: aload_2
    //   1185: invokevirtual c : ()I
    //   1188: iload #9
    //   1190: iload #17
    //   1192: isub
    //   1193: iconst_2
    //   1194: idiv
    //   1195: iload #9
    //   1197: iadd
    //   1198: invokestatic min : (II)I
    //   1201: iconst_0
    //   1202: invokevirtual a : (IIZ)Z
    //   1205: ifeq -> 1435
    //   1208: iload #14
    //   1210: iload #16
    //   1212: iload #23
    //   1214: imul
    //   1215: isub
    //   1216: bipush #103
    //   1218: irem
    //   1219: iload #23
    //   1221: if_icmpne -> 1431
    //   1224: aload #24
    //   1226: invokevirtual length : ()I
    //   1229: istore #9
    //   1231: iload #9
    //   1233: ifeq -> 1427
    //   1236: iload #9
    //   1238: ifle -> 1278
    //   1241: iload #8
    //   1243: ifeq -> 1278
    //   1246: iload #10
    //   1248: bipush #99
    //   1250: if_icmpne -> 1262
    //   1253: iload #9
    //   1255: iconst_2
    //   1256: isub
    //   1257: istore #8
    //   1259: goto -> 1268
    //   1262: iload #9
    //   1264: iconst_1
    //   1265: isub
    //   1266: istore #8
    //   1268: aload #24
    //   1270: iload #8
    //   1272: iload #9
    //   1274: invokevirtual delete : (II)Ljava/lang/StringBuilder;
    //   1277: pop
    //   1278: aload #25
    //   1280: iconst_1
    //   1281: iaload
    //   1282: aload #25
    //   1284: iconst_0
    //   1285: iaload
    //   1286: iadd
    //   1287: i2f
    //   1288: fconst_2
    //   1289: fdiv
    //   1290: fstore #4
    //   1292: iload #17
    //   1294: i2f
    //   1295: fstore #5
    //   1297: iload #13
    //   1299: iload #17
    //   1301: isub
    //   1302: i2f
    //   1303: fconst_2
    //   1304: fdiv
    //   1305: fstore #6
    //   1307: aload_3
    //   1308: invokeinterface size : ()I
    //   1313: istore #9
    //   1315: iload #9
    //   1317: newarray byte
    //   1319: astore_2
    //   1320: iconst_0
    //   1321: istore #8
    //   1323: iload #8
    //   1325: iload #9
    //   1327: if_icmpge -> 1357
    //   1330: aload_2
    //   1331: iload #8
    //   1333: aload_3
    //   1334: iload #8
    //   1336: invokeinterface get : (I)Ljava/lang/Object;
    //   1341: checkcast java/lang/Byte
    //   1344: invokevirtual byteValue : ()B
    //   1347: bastore
    //   1348: iload #8
    //   1350: iconst_1
    //   1351: iadd
    //   1352: istore #8
    //   1354: goto -> 1323
    //   1357: aload #24
    //   1359: invokevirtual toString : ()Ljava/lang/String;
    //   1362: astore_3
    //   1363: iload_1
    //   1364: i2f
    //   1365: fstore #7
    //   1367: new e/f/c/p
    //   1370: dup
    //   1371: fload #4
    //   1373: fload #7
    //   1375: invokespecial <init> : (FF)V
    //   1378: astore #24
    //   1380: new e/f/c/p
    //   1383: dup
    //   1384: fload #5
    //   1386: fload #6
    //   1388: fadd
    //   1389: fload #7
    //   1391: invokespecial <init> : (FF)V
    //   1394: astore #25
    //   1396: getstatic e/f/c/a.g : Le/f/c/a;
    //   1399: astore #26
    //   1401: new e/f/c/n
    //   1404: dup
    //   1405: aload_3
    //   1406: aload_2
    //   1407: iconst_2
    //   1408: anewarray e/f/c/p
    //   1411: dup
    //   1412: iconst_0
    //   1413: aload #24
    //   1415: aastore
    //   1416: dup
    //   1417: iconst_1
    //   1418: aload #25
    //   1420: aastore
    //   1421: aload #26
    //   1423: invokespecial <init> : (Ljava/lang/String;[B[Le/f/c/p;Le/f/c/a;)V
    //   1426: areturn
    //   1427: invokestatic a : ()Le/f/c/j;
    //   1430: athrow
    //   1431: invokestatic a : ()Le/f/c/d;
    //   1434: athrow
    //   1435: invokestatic a : ()Le/f/c/j;
    //   1438: astore_2
    //   1439: goto -> 1444
    //   1442: aload_2
    //   1443: athrow
    //   1444: goto -> 1442
  }
}


/* Location:              /home/yc/Downloads/LeaveHomeSafe.jar!/e/f/c/w/b.class
 * Java compiler version: 6 (50.0)
 * JD-Core Version:       1.1.3
 */