package e.e.j.c;

import android.graphics.drawable.Animatable;
import java.util.ArrayList;
import java.util.List;

public class f<INFO> implements d<INFO> {
  private final List<d<? super INFO>> a = new ArrayList<d<? super INFO>>(2);
  
  private void c(String paramString, Throwable paramThrowable) {
    // Byte code:
    //   0: aload_0
    //   1: monitorenter
    //   2: ldc 'FdingControllerListener'
    //   4: aload_1
    //   5: aload_2
    //   6: invokestatic e : (Ljava/lang/String;Ljava/lang/String;Ljava/lang/Throwable;)I
    //   9: pop
    //   10: aload_0
    //   11: monitorexit
    //   12: return
    //   13: astore_1
    //   14: aload_0
    //   15: monitorexit
    //   16: aload_1
    //   17: athrow
    // Exception table:
    //   from	to	target	type
    //   2	10	13	finally
  }
  
  public void a() {
    // Byte code:
    //   0: aload_0
    //   1: monitorenter
    //   2: aload_0
    //   3: getfield a : Ljava/util/List;
    //   6: invokeinterface clear : ()V
    //   11: aload_0
    //   12: monitorexit
    //   13: return
    //   14: astore_1
    //   15: aload_0
    //   16: monitorexit
    //   17: aload_1
    //   18: athrow
    // Exception table:
    //   from	to	target	type
    //   2	11	14	finally
  }
  
  public void a(d<? super INFO> paramd) {
    // Byte code:
    //   0: aload_0
    //   1: monitorenter
    //   2: aload_0
    //   3: getfield a : Ljava/util/List;
    //   6: aload_1
    //   7: invokeinterface add : (Ljava/lang/Object;)Z
    //   12: pop
    //   13: aload_0
    //   14: monitorexit
    //   15: return
    //   16: astore_1
    //   17: aload_0
    //   18: monitorexit
    //   19: aload_1
    //   20: athrow
    // Exception table:
    //   from	to	target	type
    //   2	13	16	finally
  }
  
  public void a(String paramString) {
    // Byte code:
    //   0: aload_0
    //   1: monitorenter
    //   2: aload_0
    //   3: getfield a : Ljava/util/List;
    //   6: invokeinterface size : ()I
    //   11: istore_3
    //   12: iconst_0
    //   13: istore_2
    //   14: iload_2
    //   15: iload_3
    //   16: if_icmpge -> 67
    //   19: aload_0
    //   20: getfield a : Ljava/util/List;
    //   23: iload_2
    //   24: invokeinterface get : (I)Ljava/lang/Object;
    //   29: checkcast e/e/j/c/d
    //   32: astore #4
    //   34: aload #4
    //   36: ifnull -> 60
    //   39: aload #4
    //   41: aload_1
    //   42: invokeinterface a : (Ljava/lang/String;)V
    //   47: goto -> 60
    //   50: astore #4
    //   52: aload_0
    //   53: ldc 'InternalListener exception in onRelease'
    //   55: aload #4
    //   57: invokespecial c : (Ljava/lang/String;Ljava/lang/Throwable;)V
    //   60: iload_2
    //   61: iconst_1
    //   62: iadd
    //   63: istore_2
    //   64: goto -> 14
    //   67: aload_0
    //   68: monitorexit
    //   69: return
    //   70: astore_1
    //   71: aload_0
    //   72: monitorexit
    //   73: goto -> 78
    //   76: aload_1
    //   77: athrow
    //   78: goto -> 76
    // Exception table:
    //   from	to	target	type
    //   2	12	70	finally
    //   19	34	50	java/lang/Exception
    //   19	34	70	finally
    //   39	47	50	java/lang/Exception
    //   39	47	70	finally
    //   52	60	70	finally
  }
  
  public void a(String paramString, INFO paramINFO) {
    int j = this.a.size();
    for (int i = 0; i < j; i++) {
      try {
        d<INFO> d1 = (d)this.a.get(i);
        if (d1 != null)
          d1.a(paramString, paramINFO); 
      } catch (Exception exception) {
        c("InternalListener exception in onIntermediateImageSet", exception);
      } 
    } 
  }
  
  public void a(String paramString, INFO paramINFO, Animatable paramAnimatable) {
    // Byte code:
    //   0: aload_0
    //   1: monitorenter
    //   2: aload_0
    //   3: getfield a : Ljava/util/List;
    //   6: invokeinterface size : ()I
    //   11: istore #5
    //   13: iconst_0
    //   14: istore #4
    //   16: iload #4
    //   18: iload #5
    //   20: if_icmpge -> 76
    //   23: aload_0
    //   24: getfield a : Ljava/util/List;
    //   27: iload #4
    //   29: invokeinterface get : (I)Ljava/lang/Object;
    //   34: checkcast e/e/j/c/d
    //   37: astore #6
    //   39: aload #6
    //   41: ifnull -> 67
    //   44: aload #6
    //   46: aload_1
    //   47: aload_2
    //   48: aload_3
    //   49: invokeinterface a : (Ljava/lang/String;Ljava/lang/Object;Landroid/graphics/drawable/Animatable;)V
    //   54: goto -> 67
    //   57: astore #6
    //   59: aload_0
    //   60: ldc 'InternalListener exception in onFinalImageSet'
    //   62: aload #6
    //   64: invokespecial c : (Ljava/lang/String;Ljava/lang/Throwable;)V
    //   67: iload #4
    //   69: iconst_1
    //   70: iadd
    //   71: istore #4
    //   73: goto -> 16
    //   76: aload_0
    //   77: monitorexit
    //   78: return
    //   79: astore_1
    //   80: aload_0
    //   81: monitorexit
    //   82: goto -> 87
    //   85: aload_1
    //   86: athrow
    //   87: goto -> 85
    // Exception table:
    //   from	to	target	type
    //   2	13	79	finally
    //   23	39	57	java/lang/Exception
    //   23	39	79	finally
    //   44	54	57	java/lang/Exception
    //   44	54	79	finally
    //   59	67	79	finally
  }
  
  public void a(String paramString, Throwable paramThrowable) {
    int j = this.a.size();
    for (int i = 0; i < j; i++) {
      try {
        d d1 = this.a.get(i);
        if (d1 != null)
          d1.a(paramString, paramThrowable); 
      } catch (Exception exception) {
        c("InternalListener exception in onIntermediateImageFailed", exception);
      } 
    } 
  }
  
  public void b(d<? super INFO> paramd) {
    // Byte code:
    //   0: aload_0
    //   1: monitorenter
    //   2: aload_0
    //   3: getfield a : Ljava/util/List;
    //   6: aload_1
    //   7: invokeinterface indexOf : (Ljava/lang/Object;)I
    //   12: istore_2
    //   13: iload_2
    //   14: iconst_m1
    //   15: if_icmpeq -> 30
    //   18: aload_0
    //   19: getfield a : Ljava/util/List;
    //   22: iload_2
    //   23: aconst_null
    //   24: invokeinterface set : (ILjava/lang/Object;)Ljava/lang/Object;
    //   29: pop
    //   30: aload_0
    //   31: monitorexit
    //   32: return
    //   33: astore_1
    //   34: aload_0
    //   35: monitorexit
    //   36: aload_1
    //   37: athrow
    // Exception table:
    //   from	to	target	type
    //   2	13	33	finally
    //   18	30	33	finally
  }
  
  public void b(String paramString, Object paramObject) {
    // Byte code:
    //   0: aload_0
    //   1: monitorenter
    //   2: aload_0
    //   3: getfield a : Ljava/util/List;
    //   6: invokeinterface size : ()I
    //   11: istore #4
    //   13: iconst_0
    //   14: istore_3
    //   15: iload_3
    //   16: iload #4
    //   18: if_icmpge -> 70
    //   21: aload_0
    //   22: getfield a : Ljava/util/List;
    //   25: iload_3
    //   26: invokeinterface get : (I)Ljava/lang/Object;
    //   31: checkcast e/e/j/c/d
    //   34: astore #5
    //   36: aload #5
    //   38: ifnull -> 63
    //   41: aload #5
    //   43: aload_1
    //   44: aload_2
    //   45: invokeinterface b : (Ljava/lang/String;Ljava/lang/Object;)V
    //   50: goto -> 63
    //   53: astore #5
    //   55: aload_0
    //   56: ldc 'InternalListener exception in onSubmit'
    //   58: aload #5
    //   60: invokespecial c : (Ljava/lang/String;Ljava/lang/Throwable;)V
    //   63: iload_3
    //   64: iconst_1
    //   65: iadd
    //   66: istore_3
    //   67: goto -> 15
    //   70: aload_0
    //   71: monitorexit
    //   72: return
    //   73: astore_1
    //   74: aload_0
    //   75: monitorexit
    //   76: goto -> 81
    //   79: aload_1
    //   80: athrow
    //   81: goto -> 79
    // Exception table:
    //   from	to	target	type
    //   2	13	73	finally
    //   21	36	53	java/lang/Exception
    //   21	36	73	finally
    //   41	50	53	java/lang/Exception
    //   41	50	73	finally
    //   55	63	73	finally
  }
  
  public void b(String paramString, Throwable paramThrowable) {
    // Byte code:
    //   0: aload_0
    //   1: monitorenter
    //   2: aload_0
    //   3: getfield a : Ljava/util/List;
    //   6: invokeinterface size : ()I
    //   11: istore #4
    //   13: iconst_0
    //   14: istore_3
    //   15: iload_3
    //   16: iload #4
    //   18: if_icmpge -> 70
    //   21: aload_0
    //   22: getfield a : Ljava/util/List;
    //   25: iload_3
    //   26: invokeinterface get : (I)Ljava/lang/Object;
    //   31: checkcast e/e/j/c/d
    //   34: astore #5
    //   36: aload #5
    //   38: ifnull -> 63
    //   41: aload #5
    //   43: aload_1
    //   44: aload_2
    //   45: invokeinterface b : (Ljava/lang/String;Ljava/lang/Throwable;)V
    //   50: goto -> 63
    //   53: astore #5
    //   55: aload_0
    //   56: ldc 'InternalListener exception in onFailure'
    //   58: aload #5
    //   60: invokespecial c : (Ljava/lang/String;Ljava/lang/Throwable;)V
    //   63: iload_3
    //   64: iconst_1
    //   65: iadd
    //   66: istore_3
    //   67: goto -> 15
    //   70: aload_0
    //   71: monitorexit
    //   72: return
    //   73: astore_1
    //   74: aload_0
    //   75: monitorexit
    //   76: goto -> 81
    //   79: aload_1
    //   80: athrow
    //   81: goto -> 79
    // Exception table:
    //   from	to	target	type
    //   2	13	73	finally
    //   21	36	53	java/lang/Exception
    //   21	36	73	finally
    //   41	50	53	java/lang/Exception
    //   41	50	73	finally
    //   55	63	73	finally
  }
}


/* Location:              /home/yc/Downloads/LeaveHomeSafe.jar!/e/e/j/c/f.class
 * Java compiler version: 6 (50.0)
 * JD-Core Version:       1.1.3
 */