package e.a.a.j;

import e.a.a.a;
import e.a.a.e;
import e.a.a.f;
import e.a.a.k.b;
import e.a.a.k.e;

public class k implements f, a {
  private m c = new m(null, null, null);
  
  public k() {}
  
  public k(m paramm) {}
  
  public e a(String paramString1, String paramString2, b paramb) {
    return new j(this, paramString1, paramString2, paramb);
  }
  
  public m a() {
    return this.c;
  }
  
  public void a(String paramString) {}
  
  public void a(String paramString1, String paramString2, String paramString3, String paramString4, String paramString5, e parame) {
    // Byte code:
    //   0: aload_1
    //   1: invokestatic d : (Ljava/lang/String;)V
    //   4: aload_2
    //   5: invokestatic a : (Ljava/lang/String;)V
    //   8: aload #4
    //   10: invokestatic e : (Ljava/lang/String;)V
    //   13: aload_3
    //   14: ifnull -> 25
    //   17: aload_3
    //   18: invokestatic d : (Ljava/lang/String;)Ljava/lang/String;
    //   21: astore_3
    //   22: goto -> 27
    //   25: aconst_null
    //   26: astore_3
    //   27: aload #4
    //   29: invokestatic d : (Ljava/lang/String;)Ljava/lang/String;
    //   32: astore #6
    //   34: aload_1
    //   35: aload_2
    //   36: invokestatic a : (Ljava/lang/String;Ljava/lang/String;)Le/a/a/j/q/b;
    //   39: astore_1
    //   40: aload_0
    //   41: getfield c : Le/a/a/j/m;
    //   44: aload_1
    //   45: iconst_1
    //   46: new e/a/a/k/e
    //   49: dup
    //   50: sipush #7680
    //   53: invokespecial <init> : (I)V
    //   56: invokestatic a : (Le/a/a/j/m;Le/a/a/j/q/b;ZLe/a/a/k/e;)Le/a/a/j/m;
    //   59: astore #4
    //   61: aload #4
    //   63: ifnull -> 623
    //   66: aload #4
    //   68: invokevirtual r : ()Le/a/a/k/e;
    //   71: invokevirtual e : ()Z
    //   74: ifne -> 121
    //   77: aload #4
    //   79: invokevirtual w : ()Z
    //   82: ifne -> 109
    //   85: aload #4
    //   87: invokevirtual r : ()Le/a/a/k/e;
    //   90: invokevirtual f : ()Z
    //   93: ifeq -> 109
    //   96: aload #4
    //   98: invokevirtual r : ()Le/a/a/k/e;
    //   101: iconst_1
    //   102: invokevirtual b : (Z)Le/a/a/k/e;
    //   105: pop
    //   106: goto -> 121
    //   109: new e/a/a/d
    //   112: dup
    //   113: ldc 'Specified property is no alt-text array'
    //   115: bipush #102
    //   117: invokespecial <init> : (Ljava/lang/String;I)V
    //   120: athrow
    //   121: aload #4
    //   123: invokevirtual A : ()Ljava/util/Iterator;
    //   126: astore_2
    //   127: aload_2
    //   128: invokeinterface hasNext : ()Z
    //   133: ifeq -> 203
    //   136: aload_2
    //   137: invokeinterface next : ()Ljava/lang/Object;
    //   142: checkcast e/a/a/j/m
    //   145: astore_1
    //   146: aload_1
    //   147: invokevirtual x : ()Z
    //   150: ifeq -> 191
    //   153: ldc 'xml:lang'
    //   155: aload_1
    //   156: iconst_1
    //   157: invokevirtual g : (I)Le/a/a/j/m;
    //   160: invokevirtual q : ()Ljava/lang/String;
    //   163: invokevirtual equals : (Ljava/lang/Object;)Z
    //   166: ifeq -> 191
    //   169: ldc 'x-default'
    //   171: aload_1
    //   172: iconst_1
    //   173: invokevirtual g : (I)Le/a/a/j/m;
    //   176: invokevirtual v : ()Ljava/lang/String;
    //   179: invokevirtual equals : (Ljava/lang/Object;)Z
    //   182: ifeq -> 127
    //   185: iconst_1
    //   186: istore #7
    //   188: goto -> 208
    //   191: new e/a/a/d
    //   194: dup
    //   195: ldc 'Language qualifier must be first'
    //   197: bipush #102
    //   199: invokespecial <init> : (Ljava/lang/String;I)V
    //   202: athrow
    //   203: aconst_null
    //   204: astore_1
    //   205: iconst_0
    //   206: istore #7
    //   208: aload_1
    //   209: ifnull -> 234
    //   212: aload #4
    //   214: invokevirtual b : ()I
    //   217: iconst_1
    //   218: if_icmple -> 234
    //   221: aload #4
    //   223: aload_1
    //   224: invokevirtual d : (Le/a/a/j/m;)V
    //   227: aload #4
    //   229: iconst_1
    //   230: aload_1
    //   231: invokevirtual a : (ILe/a/a/j/m;)V
    //   234: aload #4
    //   236: aload_3
    //   237: aload #6
    //   239: invokestatic b : (Le/a/a/j/m;Ljava/lang/String;Ljava/lang/String;)[Ljava/lang/Object;
    //   242: astore_2
    //   243: aload_2
    //   244: iconst_0
    //   245: aaload
    //   246: checkcast java/lang/Integer
    //   249: invokevirtual intValue : ()I
    //   252: istore #8
    //   254: aload_2
    //   255: iconst_1
    //   256: aaload
    //   257: checkcast e/a/a/j/m
    //   260: astore_2
    //   261: ldc 'x-default'
    //   263: aload #6
    //   265: invokevirtual equals : (Ljava/lang/Object;)Z
    //   268: istore #9
    //   270: iload #8
    //   272: ifeq -> 573
    //   275: iload #8
    //   277: iconst_1
    //   278: if_icmpeq -> 441
    //   281: iload #8
    //   283: iconst_2
    //   284: if_icmpeq -> 394
    //   287: iload #8
    //   289: iconst_3
    //   290: if_icmpeq -> 373
    //   293: iload #8
    //   295: iconst_4
    //   296: if_icmpeq -> 338
    //   299: iload #8
    //   301: iconst_5
    //   302: if_icmpne -> 326
    //   305: aload #4
    //   307: aload #6
    //   309: aload #5
    //   311: invokestatic a : (Le/a/a/j/m;Ljava/lang/String;Ljava/lang/String;)V
    //   314: iload #7
    //   316: istore #8
    //   318: iload #9
    //   320: ifeq -> 599
    //   323: goto -> 596
    //   326: new e/a/a/d
    //   329: dup
    //   330: ldc 'Unexpected result from ChooseLocalizedText'
    //   332: bipush #9
    //   334: invokespecial <init> : (Ljava/lang/String;I)V
    //   337: athrow
    //   338: aload_1
    //   339: ifnull -> 357
    //   342: aload #4
    //   344: invokevirtual b : ()I
    //   347: iconst_1
    //   348: if_icmpne -> 357
    //   351: aload_1
    //   352: aload #5
    //   354: invokevirtual d : (Ljava/lang/String;)V
    //   357: aload #4
    //   359: aload #6
    //   361: aload #5
    //   363: invokestatic a : (Le/a/a/j/m;Ljava/lang/String;Ljava/lang/String;)V
    //   366: iload #7
    //   368: istore #8
    //   370: goto -> 599
    //   373: aload #4
    //   375: aload #6
    //   377: aload #5
    //   379: invokestatic a : (Le/a/a/j/m;Ljava/lang/String;Ljava/lang/String;)V
    //   382: iload #7
    //   384: istore #8
    //   386: iload #9
    //   388: ifeq -> 599
    //   391: goto -> 596
    //   394: iload #7
    //   396: ifeq -> 428
    //   399: aload_1
    //   400: aload_2
    //   401: if_acmpeq -> 428
    //   404: aload_1
    //   405: ifnull -> 428
    //   408: aload_1
    //   409: invokevirtual v : ()Ljava/lang/String;
    //   412: aload_2
    //   413: invokevirtual v : ()Ljava/lang/String;
    //   416: invokevirtual equals : (Ljava/lang/Object;)Z
    //   419: ifeq -> 428
    //   422: aload_1
    //   423: aload #5
    //   425: invokevirtual d : (Ljava/lang/String;)V
    //   428: aload_2
    //   429: aload #5
    //   431: invokevirtual d : (Ljava/lang/String;)V
    //   434: iload #7
    //   436: istore #8
    //   438: goto -> 599
    //   441: iload #9
    //   443: ifne -> 477
    //   446: iload #7
    //   448: ifeq -> 428
    //   451: aload_1
    //   452: aload_2
    //   453: if_acmpeq -> 428
    //   456: aload_1
    //   457: ifnull -> 428
    //   460: aload_1
    //   461: invokevirtual v : ()Ljava/lang/String;
    //   464: aload_2
    //   465: invokevirtual v : ()Ljava/lang/String;
    //   468: invokevirtual equals : (Ljava/lang/Object;)Z
    //   471: ifeq -> 428
    //   474: goto -> 422
    //   477: aload #4
    //   479: invokevirtual A : ()Ljava/util/Iterator;
    //   482: astore_3
    //   483: aload_3
    //   484: invokeinterface hasNext : ()Z
    //   489: ifeq -> 552
    //   492: aload_3
    //   493: invokeinterface next : ()Ljava/lang/Object;
    //   498: checkcast e/a/a/j/m
    //   501: astore #6
    //   503: aload #6
    //   505: aload_1
    //   506: if_acmpeq -> 483
    //   509: aload #6
    //   511: invokevirtual v : ()Ljava/lang/String;
    //   514: astore #10
    //   516: aload_1
    //   517: ifnull -> 528
    //   520: aload_1
    //   521: invokevirtual v : ()Ljava/lang/String;
    //   524: astore_2
    //   525: goto -> 530
    //   528: aconst_null
    //   529: astore_2
    //   530: aload #10
    //   532: aload_2
    //   533: invokevirtual equals : (Ljava/lang/Object;)Z
    //   536: ifne -> 542
    //   539: goto -> 483
    //   542: aload #6
    //   544: aload #5
    //   546: invokevirtual d : (Ljava/lang/String;)V
    //   549: goto -> 483
    //   552: iload #7
    //   554: istore #8
    //   556: aload_1
    //   557: ifnull -> 599
    //   560: aload_1
    //   561: aload #5
    //   563: invokevirtual d : (Ljava/lang/String;)V
    //   566: iload #7
    //   568: istore #8
    //   570: goto -> 599
    //   573: aload #4
    //   575: ldc 'x-default'
    //   577: aload #5
    //   579: invokestatic a : (Le/a/a/j/m;Ljava/lang/String;Ljava/lang/String;)V
    //   582: iload #9
    //   584: ifne -> 596
    //   587: aload #4
    //   589: aload #6
    //   591: aload #5
    //   593: invokestatic a : (Le/a/a/j/m;Ljava/lang/String;Ljava/lang/String;)V
    //   596: iconst_1
    //   597: istore #8
    //   599: iload #8
    //   601: ifne -> 622
    //   604: aload #4
    //   606: invokevirtual b : ()I
    //   609: iconst_1
    //   610: if_icmpne -> 622
    //   613: aload #4
    //   615: ldc 'x-default'
    //   617: aload #5
    //   619: invokestatic a : (Le/a/a/j/m;Ljava/lang/String;Ljava/lang/String;)V
    //   622: return
    //   623: new e/a/a/d
    //   626: dup
    //   627: ldc 'Failed to find or create array node'
    //   629: bipush #102
    //   631: invokespecial <init> : (Ljava/lang/String;I)V
    //   634: astore_1
    //   635: goto -> 640
    //   638: aload_1
    //   639: athrow
    //   640: goto -> 638
  }
  
  public Object clone() {
    return new k((m)this.c.clone());
  }
  
  public e iterator() {
    return a(null, null, null);
  }
}


/* Location:              /home/yc/Downloads/LeaveHomeSafe.jar!/e/a/a/j/k.class
 * Java compiler version: 6 (50.0)
 * JD-Core Version:       1.1.3
 */