package b.e.b.k;

import b.e.b.d;

class b {
  static void a(f paramf, d paramd, int paramInt) {
    byte b1;
    int i;
    c[] arrayOfC;
    int j = 0;
    if (paramInt == 0) {
      i = paramf.p0;
      arrayOfC = paramf.s0;
      b1 = 0;
    } else {
      b1 = 2;
      i = paramf.q0;
      arrayOfC = paramf.r0;
    } 
    while (j < i) {
      c c = arrayOfC[j];
      c.a();
      a(paramf, paramd, paramInt, b1, c);
      j++;
    } 
  }
  
  static void a(f paramf, d paramd, int paramInt1, int paramInt2, c paramc) {
    // Byte code:
    //   0: aload #4
    //   2: getfield a : Lb/e/b/k/e;
    //   5: astore #25
    //   7: aload #4
    //   9: getfield c : Lb/e/b/k/e;
    //   12: astore #23
    //   14: aload #4
    //   16: getfield b : Lb/e/b/k/e;
    //   19: astore #20
    //   21: aload #4
    //   23: getfield d : Lb/e/b/k/e;
    //   26: astore #24
    //   28: aload #4
    //   30: getfield e : Lb/e/b/k/e;
    //   33: astore #18
    //   35: aload #4
    //   37: getfield k : F
    //   40: fstore #5
    //   42: aload #4
    //   44: getfield f : Lb/e/b/k/e;
    //   47: astore #17
    //   49: aload #4
    //   51: getfield g : Lb/e/b/k/e;
    //   54: astore #17
    //   56: aload_0
    //   57: getfield J : [Lb/e/b/k/e$b;
    //   60: iload_2
    //   61: aaload
    //   62: getstatic b/e/b/k/e$b.d : Lb/e/b/k/e$b;
    //   65: if_acmpne -> 74
    //   68: iconst_1
    //   69: istore #12
    //   71: goto -> 77
    //   74: iconst_0
    //   75: istore #12
    //   77: iload_2
    //   78: ifne -> 136
    //   81: aload #18
    //   83: getfield a0 : I
    //   86: ifne -> 95
    //   89: iconst_1
    //   90: istore #8
    //   92: goto -> 98
    //   95: iconst_0
    //   96: istore #8
    //   98: aload #18
    //   100: getfield a0 : I
    //   103: iconst_1
    //   104: if_icmpne -> 113
    //   107: iconst_1
    //   108: istore #9
    //   110: goto -> 116
    //   113: iconst_0
    //   114: istore #9
    //   116: iload #8
    //   118: istore #10
    //   120: iload #9
    //   122: istore #11
    //   124: aload #18
    //   126: getfield a0 : I
    //   129: iconst_2
    //   130: if_icmpne -> 198
    //   133: goto -> 188
    //   136: aload #18
    //   138: getfield b0 : I
    //   141: ifne -> 150
    //   144: iconst_1
    //   145: istore #8
    //   147: goto -> 153
    //   150: iconst_0
    //   151: istore #8
    //   153: aload #18
    //   155: getfield b0 : I
    //   158: iconst_1
    //   159: if_icmpne -> 168
    //   162: iconst_1
    //   163: istore #9
    //   165: goto -> 171
    //   168: iconst_0
    //   169: istore #9
    //   171: iload #8
    //   173: istore #10
    //   175: iload #9
    //   177: istore #11
    //   179: aload #18
    //   181: getfield b0 : I
    //   184: iconst_2
    //   185: if_icmpne -> 198
    //   188: iconst_1
    //   189: istore #13
    //   191: iload #9
    //   193: istore #11
    //   195: goto -> 205
    //   198: iconst_0
    //   199: istore #13
    //   201: iload #10
    //   203: istore #8
    //   205: aload #25
    //   207: astore #19
    //   209: iconst_0
    //   210: istore #9
    //   212: iload #8
    //   214: istore #10
    //   216: iload #9
    //   218: istore #8
    //   220: aconst_null
    //   221: astore #21
    //   223: iload #8
    //   225: ifne -> 632
    //   228: aload #19
    //   230: getfield G : [Lb/e/b/k/d;
    //   233: iload_3
    //   234: aaload
    //   235: astore #17
    //   237: iload #13
    //   239: ifeq -> 248
    //   242: iconst_1
    //   243: istore #9
    //   245: goto -> 251
    //   248: iconst_4
    //   249: istore #9
    //   251: aload #17
    //   253: invokevirtual a : ()I
    //   256: istore #16
    //   258: aload #19
    //   260: getfield J : [Lb/e/b/k/e$b;
    //   263: iload_2
    //   264: aaload
    //   265: getstatic b/e/b/k/e$b.e : Lb/e/b/k/e$b;
    //   268: if_acmpne -> 287
    //   271: aload #19
    //   273: getfield l : [I
    //   276: iload_2
    //   277: iaload
    //   278: ifne -> 287
    //   281: iconst_1
    //   282: istore #15
    //   284: goto -> 290
    //   287: iconst_0
    //   288: istore #15
    //   290: aload #17
    //   292: getfield d : Lb/e/b/k/d;
    //   295: astore #22
    //   297: iload #16
    //   299: istore #14
    //   301: aload #22
    //   303: ifnull -> 327
    //   306: iload #16
    //   308: istore #14
    //   310: aload #19
    //   312: aload #25
    //   314: if_acmpeq -> 327
    //   317: iload #16
    //   319: aload #22
    //   321: invokevirtual a : ()I
    //   324: iadd
    //   325: istore #14
    //   327: iload #13
    //   329: ifeq -> 352
    //   332: aload #19
    //   334: aload #25
    //   336: if_acmpeq -> 352
    //   339: aload #19
    //   341: aload #20
    //   343: if_acmpeq -> 352
    //   346: iconst_5
    //   347: istore #9
    //   349: goto -> 352
    //   352: aload #17
    //   354: getfield d : Lb/e/b/k/d;
    //   357: astore #22
    //   359: aload #22
    //   361: ifnull -> 451
    //   364: aload #19
    //   366: aload #20
    //   368: if_acmpne -> 392
    //   371: aload_1
    //   372: aload #17
    //   374: getfield g : Lb/e/b/i;
    //   377: aload #22
    //   379: getfield g : Lb/e/b/i;
    //   382: iload #14
    //   384: bipush #6
    //   386: invokevirtual b : (Lb/e/b/i;Lb/e/b/i;II)V
    //   389: goto -> 410
    //   392: aload_1
    //   393: aload #17
    //   395: getfield g : Lb/e/b/i;
    //   398: aload #22
    //   400: getfield g : Lb/e/b/i;
    //   403: iload #14
    //   405: bipush #8
    //   407: invokevirtual b : (Lb/e/b/i;Lb/e/b/i;II)V
    //   410: iload #15
    //   412: ifeq -> 426
    //   415: iload #13
    //   417: ifne -> 426
    //   420: iconst_5
    //   421: istore #9
    //   423: goto -> 426
    //   426: aload_1
    //   427: aload #17
    //   429: getfield g : Lb/e/b/i;
    //   432: aload #17
    //   434: getfield d : Lb/e/b/k/d;
    //   437: getfield g : Lb/e/b/i;
    //   440: iload #14
    //   442: iload #9
    //   444: invokevirtual a : (Lb/e/b/i;Lb/e/b/i;II)Lb/e/b/b;
    //   447: pop
    //   448: goto -> 451
    //   451: iload #12
    //   453: ifeq -> 537
    //   456: aload #19
    //   458: invokevirtual y : ()I
    //   461: bipush #8
    //   463: if_icmpeq -> 511
    //   466: aload #19
    //   468: getfield J : [Lb/e/b/k/e$b;
    //   471: iload_2
    //   472: aaload
    //   473: getstatic b/e/b/k/e$b.e : Lb/e/b/k/e$b;
    //   476: if_acmpne -> 511
    //   479: aload #19
    //   481: getfield G : [Lb/e/b/k/d;
    //   484: astore #17
    //   486: aload_1
    //   487: aload #17
    //   489: iload_3
    //   490: iconst_1
    //   491: iadd
    //   492: aaload
    //   493: getfield g : Lb/e/b/i;
    //   496: aload #17
    //   498: iload_3
    //   499: aaload
    //   500: getfield g : Lb/e/b/i;
    //   503: iconst_0
    //   504: iconst_5
    //   505: invokevirtual b : (Lb/e/b/i;Lb/e/b/i;II)V
    //   508: goto -> 511
    //   511: aload_1
    //   512: aload #19
    //   514: getfield G : [Lb/e/b/k/d;
    //   517: iload_3
    //   518: aaload
    //   519: getfield g : Lb/e/b/i;
    //   522: aload_0
    //   523: getfield G : [Lb/e/b/k/d;
    //   526: iload_3
    //   527: aaload
    //   528: getfield g : Lb/e/b/i;
    //   531: iconst_0
    //   532: bipush #8
    //   534: invokevirtual b : (Lb/e/b/i;Lb/e/b/i;II)V
    //   537: aload #19
    //   539: getfield G : [Lb/e/b/k/d;
    //   542: iload_3
    //   543: iconst_1
    //   544: iadd
    //   545: aaload
    //   546: getfield d : Lb/e/b/k/d;
    //   549: astore #22
    //   551: aload #21
    //   553: astore #17
    //   555: aload #22
    //   557: ifnull -> 614
    //   560: aload #22
    //   562: getfield b : Lb/e/b/k/e;
    //   565: astore #22
    //   567: aload #22
    //   569: getfield G : [Lb/e/b/k/d;
    //   572: astore #26
    //   574: aload #21
    //   576: astore #17
    //   578: aload #26
    //   580: iload_3
    //   581: aaload
    //   582: getfield d : Lb/e/b/k/d;
    //   585: ifnull -> 614
    //   588: aload #26
    //   590: iload_3
    //   591: aaload
    //   592: getfield d : Lb/e/b/k/d;
    //   595: getfield b : Lb/e/b/k/e;
    //   598: aload #19
    //   600: if_acmpeq -> 610
    //   603: aload #21
    //   605: astore #17
    //   607: goto -> 614
    //   610: aload #22
    //   612: astore #17
    //   614: aload #17
    //   616: ifnull -> 626
    //   619: aload #17
    //   621: astore #19
    //   623: goto -> 629
    //   626: iconst_1
    //   627: istore #8
    //   629: goto -> 220
    //   632: aload #24
    //   634: ifnull -> 830
    //   637: aload #23
    //   639: getfield G : [Lb/e/b/k/d;
    //   642: astore #17
    //   644: iload_3
    //   645: iconst_1
    //   646: iadd
    //   647: istore #9
    //   649: aload #17
    //   651: iload #9
    //   653: aaload
    //   654: getfield d : Lb/e/b/k/d;
    //   657: ifnull -> 830
    //   660: aload #24
    //   662: getfield G : [Lb/e/b/k/d;
    //   665: iload #9
    //   667: aaload
    //   668: astore #17
    //   670: aload #24
    //   672: getfield J : [Lb/e/b/k/e$b;
    //   675: iload_2
    //   676: aaload
    //   677: getstatic b/e/b/k/e$b.e : Lb/e/b/k/e$b;
    //   680: if_acmpne -> 699
    //   683: aload #24
    //   685: getfield l : [I
    //   688: iload_2
    //   689: iaload
    //   690: ifne -> 699
    //   693: iconst_1
    //   694: istore #8
    //   696: goto -> 702
    //   699: iconst_0
    //   700: istore #8
    //   702: iload #8
    //   704: ifeq -> 753
    //   707: iload #13
    //   709: ifne -> 753
    //   712: aload #17
    //   714: getfield d : Lb/e/b/k/d;
    //   717: astore #19
    //   719: aload #19
    //   721: getfield b : Lb/e/b/k/e;
    //   724: aload_0
    //   725: if_acmpne -> 753
    //   728: aload_1
    //   729: aload #17
    //   731: getfield g : Lb/e/b/i;
    //   734: aload #19
    //   736: getfield g : Lb/e/b/i;
    //   739: aload #17
    //   741: invokevirtual a : ()I
    //   744: ineg
    //   745: iconst_5
    //   746: invokevirtual a : (Lb/e/b/i;Lb/e/b/i;II)Lb/e/b/b;
    //   749: pop
    //   750: goto -> 796
    //   753: iload #13
    //   755: ifeq -> 796
    //   758: aload #17
    //   760: getfield d : Lb/e/b/k/d;
    //   763: astore #19
    //   765: aload #19
    //   767: getfield b : Lb/e/b/k/e;
    //   770: aload_0
    //   771: if_acmpne -> 796
    //   774: aload_1
    //   775: aload #17
    //   777: getfield g : Lb/e/b/i;
    //   780: aload #19
    //   782: getfield g : Lb/e/b/i;
    //   785: aload #17
    //   787: invokevirtual a : ()I
    //   790: ineg
    //   791: iconst_4
    //   792: invokevirtual a : (Lb/e/b/i;Lb/e/b/i;II)Lb/e/b/b;
    //   795: pop
    //   796: aload_1
    //   797: aload #17
    //   799: getfield g : Lb/e/b/i;
    //   802: aload #23
    //   804: getfield G : [Lb/e/b/k/d;
    //   807: iload #9
    //   809: aaload
    //   810: getfield d : Lb/e/b/k/d;
    //   813: getfield g : Lb/e/b/i;
    //   816: aload #17
    //   818: invokevirtual a : ()I
    //   821: ineg
    //   822: bipush #6
    //   824: invokevirtual c : (Lb/e/b/i;Lb/e/b/i;II)V
    //   827: goto -> 830
    //   830: iload #12
    //   832: ifeq -> 883
    //   835: aload_0
    //   836: getfield G : [Lb/e/b/k/d;
    //   839: astore_0
    //   840: iload_3
    //   841: iconst_1
    //   842: iadd
    //   843: istore #8
    //   845: aload_0
    //   846: iload #8
    //   848: aaload
    //   849: getfield g : Lb/e/b/i;
    //   852: astore_0
    //   853: aload #23
    //   855: getfield G : [Lb/e/b/k/d;
    //   858: astore #17
    //   860: aload_1
    //   861: aload_0
    //   862: aload #17
    //   864: iload #8
    //   866: aaload
    //   867: getfield g : Lb/e/b/i;
    //   870: aload #17
    //   872: iload #8
    //   874: aaload
    //   875: invokevirtual a : ()I
    //   878: bipush #8
    //   880: invokevirtual b : (Lb/e/b/i;Lb/e/b/i;II)V
    //   883: aload #4
    //   885: getfield h : Ljava/util/ArrayList;
    //   888: astore_0
    //   889: aload_0
    //   890: ifnull -> 1185
    //   893: aload_0
    //   894: invokevirtual size : ()I
    //   897: istore #8
    //   899: iload #8
    //   901: iconst_1
    //   902: if_icmple -> 1185
    //   905: aload #4
    //   907: getfield q : Z
    //   910: ifeq -> 932
    //   913: aload #4
    //   915: getfield s : Z
    //   918: ifne -> 932
    //   921: aload #4
    //   923: getfield j : I
    //   926: i2f
    //   927: fstore #6
    //   929: goto -> 936
    //   932: fload #5
    //   934: fstore #6
    //   936: aconst_null
    //   937: astore #17
    //   939: iconst_0
    //   940: istore #9
    //   942: fconst_0
    //   943: fstore #7
    //   945: iload #9
    //   947: iload #8
    //   949: if_icmpge -> 1185
    //   952: aload_0
    //   953: iload #9
    //   955: invokevirtual get : (I)Ljava/lang/Object;
    //   958: checkcast b/e/b/k/e
    //   961: astore #19
    //   963: aload #19
    //   965: getfield c0 : [F
    //   968: iload_2
    //   969: faload
    //   970: fstore #5
    //   972: fload #5
    //   974: fconst_0
    //   975: fcmpg
    //   976: ifge -> 1026
    //   979: aload #4
    //   981: getfield s : Z
    //   984: ifeq -> 1020
    //   987: aload #19
    //   989: getfield G : [Lb/e/b/k/d;
    //   992: astore #19
    //   994: aload_1
    //   995: aload #19
    //   997: iload_3
    //   998: iconst_1
    //   999: iadd
    //   1000: aaload
    //   1001: getfield g : Lb/e/b/i;
    //   1004: aload #19
    //   1006: iload_3
    //   1007: aaload
    //   1008: getfield g : Lb/e/b/i;
    //   1011: iconst_0
    //   1012: iconst_4
    //   1013: invokevirtual a : (Lb/e/b/i;Lb/e/b/i;II)Lb/e/b/b;
    //   1016: pop
    //   1017: goto -> 1064
    //   1020: fconst_1
    //   1021: fstore #5
    //   1023: goto -> 1026
    //   1026: fload #5
    //   1028: fconst_0
    //   1029: fcmpl
    //   1030: ifne -> 1071
    //   1033: aload #19
    //   1035: getfield G : [Lb/e/b/k/d;
    //   1038: astore #19
    //   1040: aload_1
    //   1041: aload #19
    //   1043: iload_3
    //   1044: iconst_1
    //   1045: iadd
    //   1046: aaload
    //   1047: getfield g : Lb/e/b/i;
    //   1050: aload #19
    //   1052: iload_3
    //   1053: aaload
    //   1054: getfield g : Lb/e/b/i;
    //   1057: iconst_0
    //   1058: bipush #8
    //   1060: invokevirtual a : (Lb/e/b/i;Lb/e/b/i;II)Lb/e/b/b;
    //   1063: pop
    //   1064: fload #7
    //   1066: fstore #5
    //   1068: goto -> 1172
    //   1071: aload #17
    //   1073: ifnull -> 1168
    //   1076: aload #17
    //   1078: getfield G : [Lb/e/b/k/d;
    //   1081: astore #21
    //   1083: aload #21
    //   1085: iload_3
    //   1086: aaload
    //   1087: getfield g : Lb/e/b/i;
    //   1090: astore #17
    //   1092: iload_3
    //   1093: iconst_1
    //   1094: iadd
    //   1095: istore #12
    //   1097: aload #21
    //   1099: iload #12
    //   1101: aaload
    //   1102: getfield g : Lb/e/b/i;
    //   1105: astore #21
    //   1107: aload #19
    //   1109: getfield G : [Lb/e/b/k/d;
    //   1112: astore #26
    //   1114: aload #26
    //   1116: iload_3
    //   1117: aaload
    //   1118: getfield g : Lb/e/b/i;
    //   1121: astore #22
    //   1123: aload #26
    //   1125: iload #12
    //   1127: aaload
    //   1128: getfield g : Lb/e/b/i;
    //   1131: astore #26
    //   1133: aload_1
    //   1134: invokevirtual b : ()Lb/e/b/b;
    //   1137: astore #27
    //   1139: aload #27
    //   1141: fload #7
    //   1143: fload #6
    //   1145: fload #5
    //   1147: aload #17
    //   1149: aload #21
    //   1151: aload #22
    //   1153: aload #26
    //   1155: invokevirtual a : (FFFLb/e/b/i;Lb/e/b/i;Lb/e/b/i;Lb/e/b/i;)Lb/e/b/b;
    //   1158: pop
    //   1159: aload_1
    //   1160: aload #27
    //   1162: invokevirtual a : (Lb/e/b/b;)V
    //   1165: goto -> 1168
    //   1168: aload #19
    //   1170: astore #17
    //   1172: iload #9
    //   1174: iconst_1
    //   1175: iadd
    //   1176: istore #9
    //   1178: fload #5
    //   1180: fstore #7
    //   1182: goto -> 945
    //   1185: aload #20
    //   1187: ifnull -> 1362
    //   1190: aload #20
    //   1192: aload #24
    //   1194: if_acmpeq -> 1202
    //   1197: iload #13
    //   1199: ifeq -> 1362
    //   1202: aload #25
    //   1204: getfield G : [Lb/e/b/k/d;
    //   1207: iload_3
    //   1208: aaload
    //   1209: astore_0
    //   1210: aload #23
    //   1212: getfield G : [Lb/e/b/k/d;
    //   1215: astore #4
    //   1217: iload_3
    //   1218: iconst_1
    //   1219: iadd
    //   1220: istore #8
    //   1222: aload #4
    //   1224: iload #8
    //   1226: aaload
    //   1227: astore #4
    //   1229: aload_0
    //   1230: getfield d : Lb/e/b/k/d;
    //   1233: astore_0
    //   1234: aload_0
    //   1235: ifnull -> 1246
    //   1238: aload_0
    //   1239: getfield g : Lb/e/b/i;
    //   1242: astore_0
    //   1243: goto -> 1248
    //   1246: aconst_null
    //   1247: astore_0
    //   1248: aload #4
    //   1250: getfield d : Lb/e/b/k/d;
    //   1253: astore #4
    //   1255: aload #4
    //   1257: ifnull -> 1270
    //   1260: aload #4
    //   1262: getfield g : Lb/e/b/i;
    //   1265: astore #4
    //   1267: goto -> 1273
    //   1270: aconst_null
    //   1271: astore #4
    //   1273: aload #20
    //   1275: getfield G : [Lb/e/b/k/d;
    //   1278: iload_3
    //   1279: aaload
    //   1280: astore #17
    //   1282: aload #24
    //   1284: getfield G : [Lb/e/b/k/d;
    //   1287: iload #8
    //   1289: aaload
    //   1290: astore #19
    //   1292: aload_0
    //   1293: ifnull -> 2423
    //   1296: aload #4
    //   1298: ifnull -> 2423
    //   1301: iload_2
    //   1302: ifne -> 1315
    //   1305: aload #18
    //   1307: getfield U : F
    //   1310: fstore #5
    //   1312: goto -> 1322
    //   1315: aload #18
    //   1317: getfield V : F
    //   1320: fstore #5
    //   1322: aload #17
    //   1324: invokevirtual a : ()I
    //   1327: istore_2
    //   1328: aload #19
    //   1330: invokevirtual a : ()I
    //   1333: istore #8
    //   1335: aload_1
    //   1336: aload #17
    //   1338: getfield g : Lb/e/b/i;
    //   1341: aload_0
    //   1342: iload_2
    //   1343: fload #5
    //   1345: aload #4
    //   1347: aload #19
    //   1349: getfield g : Lb/e/b/i;
    //   1352: iload #8
    //   1354: bipush #7
    //   1356: invokevirtual a : (Lb/e/b/i;Lb/e/b/i;IFLb/e/b/i;Lb/e/b/i;II)V
    //   1359: goto -> 2423
    //   1362: iload #10
    //   1364: ifeq -> 1856
    //   1367: aload #20
    //   1369: ifnull -> 1856
    //   1372: aload #4
    //   1374: getfield j : I
    //   1377: istore #8
    //   1379: iload #8
    //   1381: ifle -> 1400
    //   1384: aload #4
    //   1386: getfield i : I
    //   1389: iload #8
    //   1391: if_icmpne -> 1400
    //   1394: iconst_1
    //   1395: istore #12
    //   1397: goto -> 1403
    //   1400: iconst_0
    //   1401: istore #12
    //   1403: aload #20
    //   1405: astore_0
    //   1406: aload_0
    //   1407: astore #19
    //   1409: aload_0
    //   1410: ifnull -> 2423
    //   1413: aload_0
    //   1414: getfield e0 : [Lb/e/b/k/e;
    //   1417: iload_2
    //   1418: aaload
    //   1419: astore #4
    //   1421: aload #4
    //   1423: ifnull -> 1448
    //   1426: aload #4
    //   1428: invokevirtual y : ()I
    //   1431: bipush #8
    //   1433: if_icmpne -> 1448
    //   1436: aload #4
    //   1438: getfield e0 : [Lb/e/b/k/e;
    //   1441: iload_2
    //   1442: aaload
    //   1443: astore #4
    //   1445: goto -> 1421
    //   1448: aload #4
    //   1450: ifnonnull -> 1465
    //   1453: aload_0
    //   1454: aload #24
    //   1456: if_acmpne -> 1462
    //   1459: goto -> 1465
    //   1462: goto -> 1838
    //   1465: aload_0
    //   1466: getfield G : [Lb/e/b/k/d;
    //   1469: iload_3
    //   1470: aaload
    //   1471: astore #21
    //   1473: aload #21
    //   1475: getfield g : Lb/e/b/i;
    //   1478: astore #27
    //   1480: aload #21
    //   1482: getfield d : Lb/e/b/k/d;
    //   1485: astore #17
    //   1487: aload #17
    //   1489: ifnull -> 1502
    //   1492: aload #17
    //   1494: getfield g : Lb/e/b/i;
    //   1497: astore #18
    //   1499: goto -> 1505
    //   1502: aconst_null
    //   1503: astore #18
    //   1505: aload #19
    //   1507: aload_0
    //   1508: if_acmpeq -> 1532
    //   1511: aload #19
    //   1513: getfield G : [Lb/e/b/k/d;
    //   1516: iload_3
    //   1517: iconst_1
    //   1518: iadd
    //   1519: aaload
    //   1520: astore #17
    //   1522: aload #17
    //   1524: getfield g : Lb/e/b/i;
    //   1527: astore #17
    //   1529: goto -> 1584
    //   1532: aload #18
    //   1534: astore #17
    //   1536: aload_0
    //   1537: aload #20
    //   1539: if_acmpne -> 1584
    //   1542: aload #18
    //   1544: astore #17
    //   1546: aload #19
    //   1548: aload_0
    //   1549: if_acmpne -> 1584
    //   1552: aload #25
    //   1554: getfield G : [Lb/e/b/k/d;
    //   1557: astore #17
    //   1559: aload #17
    //   1561: iload_3
    //   1562: aaload
    //   1563: getfield d : Lb/e/b/k/d;
    //   1566: ifnull -> 1581
    //   1569: aload #17
    //   1571: iload_3
    //   1572: aaload
    //   1573: getfield d : Lb/e/b/k/d;
    //   1576: astore #17
    //   1578: goto -> 1522
    //   1581: aconst_null
    //   1582: astore #17
    //   1584: aload #21
    //   1586: invokevirtual a : ()I
    //   1589: istore #13
    //   1591: aload_0
    //   1592: getfield G : [Lb/e/b/k/d;
    //   1595: astore #18
    //   1597: iload_3
    //   1598: iconst_1
    //   1599: iadd
    //   1600: istore #14
    //   1602: aload #18
    //   1604: iload #14
    //   1606: aaload
    //   1607: invokevirtual a : ()I
    //   1610: istore #9
    //   1612: aload #4
    //   1614: ifnull -> 1648
    //   1617: aload #4
    //   1619: getfield G : [Lb/e/b/k/d;
    //   1622: iload_3
    //   1623: aaload
    //   1624: astore #18
    //   1626: aload #18
    //   1628: getfield g : Lb/e/b/i;
    //   1631: astore #21
    //   1633: aload_0
    //   1634: getfield G : [Lb/e/b/k/d;
    //   1637: iload #14
    //   1639: aaload
    //   1640: getfield g : Lb/e/b/i;
    //   1643: astore #22
    //   1645: goto -> 1699
    //   1648: aload #23
    //   1650: getfield G : [Lb/e/b/k/d;
    //   1653: iload #14
    //   1655: aaload
    //   1656: getfield d : Lb/e/b/k/d;
    //   1659: astore #26
    //   1661: aload #26
    //   1663: ifnull -> 1676
    //   1666: aload #26
    //   1668: getfield g : Lb/e/b/i;
    //   1671: astore #18
    //   1673: goto -> 1679
    //   1676: aconst_null
    //   1677: astore #18
    //   1679: aload_0
    //   1680: getfield G : [Lb/e/b/k/d;
    //   1683: iload #14
    //   1685: aaload
    //   1686: getfield g : Lb/e/b/i;
    //   1689: astore #22
    //   1691: aload #18
    //   1693: astore #21
    //   1695: aload #26
    //   1697: astore #18
    //   1699: iload #9
    //   1701: istore #8
    //   1703: aload #18
    //   1705: ifnull -> 1718
    //   1708: iload #9
    //   1710: aload #18
    //   1712: invokevirtual a : ()I
    //   1715: iadd
    //   1716: istore #8
    //   1718: iload #13
    //   1720: istore #9
    //   1722: aload #19
    //   1724: ifnull -> 1743
    //   1727: iload #13
    //   1729: aload #19
    //   1731: getfield G : [Lb/e/b/k/d;
    //   1734: iload #14
    //   1736: aaload
    //   1737: invokevirtual a : ()I
    //   1740: iadd
    //   1741: istore #9
    //   1743: aload #27
    //   1745: ifnull -> 1462
    //   1748: aload #17
    //   1750: ifnull -> 1462
    //   1753: aload #21
    //   1755: ifnull -> 1462
    //   1758: aload #22
    //   1760: ifnull -> 1462
    //   1763: aload_0
    //   1764: aload #20
    //   1766: if_acmpne -> 1781
    //   1769: aload #20
    //   1771: getfield G : [Lb/e/b/k/d;
    //   1774: iload_3
    //   1775: aaload
    //   1776: invokevirtual a : ()I
    //   1779: istore #9
    //   1781: aload_0
    //   1782: aload #24
    //   1784: if_acmpne -> 1803
    //   1787: aload #24
    //   1789: getfield G : [Lb/e/b/k/d;
    //   1792: iload #14
    //   1794: aaload
    //   1795: invokevirtual a : ()I
    //   1798: istore #8
    //   1800: goto -> 1803
    //   1803: iload #12
    //   1805: ifeq -> 1815
    //   1808: bipush #8
    //   1810: istore #13
    //   1812: goto -> 1818
    //   1815: iconst_5
    //   1816: istore #13
    //   1818: aload_1
    //   1819: aload #27
    //   1821: aload #17
    //   1823: iload #9
    //   1825: ldc 0.5
    //   1827: aload #21
    //   1829: aload #22
    //   1831: iload #8
    //   1833: iload #13
    //   1835: invokevirtual a : (Lb/e/b/i;Lb/e/b/i;IFLb/e/b/i;Lb/e/b/i;II)V
    //   1838: aload_0
    //   1839: invokevirtual y : ()I
    //   1842: bipush #8
    //   1844: if_icmpeq -> 1850
    //   1847: aload_0
    //   1848: astore #19
    //   1850: aload #4
    //   1852: astore_0
    //   1853: goto -> 1409
    //   1856: iload #11
    //   1858: ifeq -> 2423
    //   1861: aload #20
    //   1863: ifnull -> 2423
    //   1866: aload #4
    //   1868: getfield j : I
    //   1871: istore #8
    //   1873: iload #8
    //   1875: ifle -> 1894
    //   1878: aload #4
    //   1880: getfield i : I
    //   1883: iload #8
    //   1885: if_icmpne -> 1894
    //   1888: iconst_1
    //   1889: istore #8
    //   1891: goto -> 1897
    //   1894: iconst_0
    //   1895: istore #8
    //   1897: aload #20
    //   1899: astore #4
    //   1901: aload #4
    //   1903: astore #17
    //   1905: aload #4
    //   1907: ifnull -> 2263
    //   1910: aload #4
    //   1912: getfield e0 : [Lb/e/b/k/e;
    //   1915: iload_2
    //   1916: aaload
    //   1917: astore_0
    //   1918: aload_0
    //   1919: ifnull -> 1941
    //   1922: aload_0
    //   1923: invokevirtual y : ()I
    //   1926: bipush #8
    //   1928: if_icmpne -> 1941
    //   1931: aload_0
    //   1932: getfield e0 : [Lb/e/b/k/e;
    //   1935: iload_2
    //   1936: aaload
    //   1937: astore_0
    //   1938: goto -> 1918
    //   1941: aload #4
    //   1943: aload #20
    //   1945: if_acmpeq -> 2236
    //   1948: aload #4
    //   1950: aload #24
    //   1952: if_acmpeq -> 2236
    //   1955: aload_0
    //   1956: ifnull -> 2236
    //   1959: aload_0
    //   1960: aload #24
    //   1962: if_acmpne -> 1970
    //   1965: aconst_null
    //   1966: astore_0
    //   1967: goto -> 1970
    //   1970: aload #4
    //   1972: getfield G : [Lb/e/b/k/d;
    //   1975: iload_3
    //   1976: aaload
    //   1977: astore #18
    //   1979: aload #18
    //   1981: getfield g : Lb/e/b/i;
    //   1984: astore #22
    //   1986: aload #18
    //   1988: getfield d : Lb/e/b/k/d;
    //   1991: astore #19
    //   1993: aload #19
    //   1995: ifnull -> 2005
    //   1998: aload #19
    //   2000: getfield g : Lb/e/b/i;
    //   2003: astore #19
    //   2005: aload #17
    //   2007: getfield G : [Lb/e/b/k/d;
    //   2010: astore #19
    //   2012: iload_3
    //   2013: iconst_1
    //   2014: iadd
    //   2015: istore #14
    //   2017: aload #19
    //   2019: iload #14
    //   2021: aaload
    //   2022: getfield g : Lb/e/b/i;
    //   2025: astore #26
    //   2027: aload #18
    //   2029: invokevirtual a : ()I
    //   2032: istore #13
    //   2034: aload #4
    //   2036: getfield G : [Lb/e/b/k/d;
    //   2039: iload #14
    //   2041: aaload
    //   2042: invokevirtual a : ()I
    //   2045: istore #12
    //   2047: aload_0
    //   2048: ifnull -> 2087
    //   2051: aload_0
    //   2052: getfield G : [Lb/e/b/k/d;
    //   2055: iload_3
    //   2056: aaload
    //   2057: astore #18
    //   2059: aload #18
    //   2061: getfield g : Lb/e/b/i;
    //   2064: astore #19
    //   2066: aload #18
    //   2068: getfield d : Lb/e/b/k/d;
    //   2071: astore #21
    //   2073: aload #21
    //   2075: ifnull -> 2081
    //   2078: goto -> 2124
    //   2081: aconst_null
    //   2082: astore #21
    //   2084: goto -> 2131
    //   2087: aload #24
    //   2089: getfield G : [Lb/e/b/k/d;
    //   2092: iload_3
    //   2093: aaload
    //   2094: astore #18
    //   2096: aload #18
    //   2098: ifnull -> 2111
    //   2101: aload #18
    //   2103: getfield g : Lb/e/b/i;
    //   2106: astore #19
    //   2108: goto -> 2114
    //   2111: aconst_null
    //   2112: astore #19
    //   2114: aload #4
    //   2116: getfield G : [Lb/e/b/k/d;
    //   2119: iload #14
    //   2121: aaload
    //   2122: astore #21
    //   2124: aload #21
    //   2126: getfield g : Lb/e/b/i;
    //   2129: astore #21
    //   2131: iload #12
    //   2133: istore #9
    //   2135: aload #18
    //   2137: ifnull -> 2150
    //   2140: iload #12
    //   2142: aload #18
    //   2144: invokevirtual a : ()I
    //   2147: iadd
    //   2148: istore #9
    //   2150: iload #13
    //   2152: istore #12
    //   2154: aload #17
    //   2156: ifnull -> 2175
    //   2159: iload #13
    //   2161: aload #17
    //   2163: getfield G : [Lb/e/b/k/d;
    //   2166: iload #14
    //   2168: aaload
    //   2169: invokevirtual a : ()I
    //   2172: iadd
    //   2173: istore #12
    //   2175: iload #8
    //   2177: ifeq -> 2187
    //   2180: bipush #8
    //   2182: istore #13
    //   2184: goto -> 2190
    //   2187: iconst_4
    //   2188: istore #13
    //   2190: aload #22
    //   2192: ifnull -> 2233
    //   2195: aload #26
    //   2197: ifnull -> 2233
    //   2200: aload #19
    //   2202: ifnull -> 2233
    //   2205: aload #21
    //   2207: ifnull -> 2233
    //   2210: aload_1
    //   2211: aload #22
    //   2213: aload #26
    //   2215: iload #12
    //   2217: ldc 0.5
    //   2219: aload #19
    //   2221: aload #21
    //   2223: iload #9
    //   2225: iload #13
    //   2227: invokevirtual a : (Lb/e/b/i;Lb/e/b/i;IFLb/e/b/i;Lb/e/b/i;II)V
    //   2230: goto -> 2233
    //   2233: goto -> 2236
    //   2236: aload #4
    //   2238: invokevirtual y : ()I
    //   2241: bipush #8
    //   2243: if_icmpeq -> 2249
    //   2246: goto -> 2253
    //   2249: aload #17
    //   2251: astore #4
    //   2253: aload #4
    //   2255: astore #17
    //   2257: aload_0
    //   2258: astore #4
    //   2260: goto -> 1905
    //   2263: aload #20
    //   2265: getfield G : [Lb/e/b/k/d;
    //   2268: iload_3
    //   2269: aaload
    //   2270: astore_0
    //   2271: aload #25
    //   2273: getfield G : [Lb/e/b/k/d;
    //   2276: iload_3
    //   2277: aaload
    //   2278: getfield d : Lb/e/b/k/d;
    //   2281: astore #4
    //   2283: aload #24
    //   2285: getfield G : [Lb/e/b/k/d;
    //   2288: astore #17
    //   2290: iload_3
    //   2291: iconst_1
    //   2292: iadd
    //   2293: istore_2
    //   2294: aload #17
    //   2296: iload_2
    //   2297: aaload
    //   2298: astore #17
    //   2300: aload #23
    //   2302: getfield G : [Lb/e/b/k/d;
    //   2305: iload_2
    //   2306: aaload
    //   2307: getfield d : Lb/e/b/k/d;
    //   2310: astore #18
    //   2312: aload #4
    //   2314: ifnull -> 2389
    //   2317: aload #20
    //   2319: aload #24
    //   2321: if_acmpeq -> 2346
    //   2324: aload_1
    //   2325: aload_0
    //   2326: getfield g : Lb/e/b/i;
    //   2329: aload #4
    //   2331: getfield g : Lb/e/b/i;
    //   2334: aload_0
    //   2335: invokevirtual a : ()I
    //   2338: iconst_5
    //   2339: invokevirtual a : (Lb/e/b/i;Lb/e/b/i;II)Lb/e/b/b;
    //   2342: pop
    //   2343: goto -> 2389
    //   2346: aload #18
    //   2348: ifnull -> 2389
    //   2351: aload_1
    //   2352: aload_0
    //   2353: getfield g : Lb/e/b/i;
    //   2356: aload #4
    //   2358: getfield g : Lb/e/b/i;
    //   2361: aload_0
    //   2362: invokevirtual a : ()I
    //   2365: ldc 0.5
    //   2367: aload #17
    //   2369: getfield g : Lb/e/b/i;
    //   2372: aload #18
    //   2374: getfield g : Lb/e/b/i;
    //   2377: aload #17
    //   2379: invokevirtual a : ()I
    //   2382: iconst_5
    //   2383: invokevirtual a : (Lb/e/b/i;Lb/e/b/i;IFLb/e/b/i;Lb/e/b/i;II)V
    //   2386: goto -> 2389
    //   2389: aload #18
    //   2391: ifnull -> 2423
    //   2394: aload #20
    //   2396: aload #24
    //   2398: if_acmpeq -> 2423
    //   2401: aload_1
    //   2402: aload #17
    //   2404: getfield g : Lb/e/b/i;
    //   2407: aload #18
    //   2409: getfield g : Lb/e/b/i;
    //   2412: aload #17
    //   2414: invokevirtual a : ()I
    //   2417: ineg
    //   2418: iconst_5
    //   2419: invokevirtual a : (Lb/e/b/i;Lb/e/b/i;II)Lb/e/b/b;
    //   2422: pop
    //   2423: iload #10
    //   2425: ifne -> 2433
    //   2428: iload #11
    //   2430: ifeq -> 2633
    //   2433: aload #20
    //   2435: ifnull -> 2633
    //   2438: aload #20
    //   2440: aload #24
    //   2442: if_acmpeq -> 2633
    //   2445: aload #20
    //   2447: getfield G : [Lb/e/b/k/d;
    //   2450: iload_3
    //   2451: aaload
    //   2452: astore #17
    //   2454: aload #24
    //   2456: getfield G : [Lb/e/b/k/d;
    //   2459: astore_0
    //   2460: iload_3
    //   2461: iconst_1
    //   2462: iadd
    //   2463: istore_2
    //   2464: aload_0
    //   2465: iload_2
    //   2466: aaload
    //   2467: astore #18
    //   2469: aload #17
    //   2471: getfield d : Lb/e/b/k/d;
    //   2474: astore_0
    //   2475: aload_0
    //   2476: ifnull -> 2488
    //   2479: aload_0
    //   2480: getfield g : Lb/e/b/i;
    //   2483: astore #4
    //   2485: goto -> 2491
    //   2488: aconst_null
    //   2489: astore #4
    //   2491: aload #18
    //   2493: getfield d : Lb/e/b/k/d;
    //   2496: astore_0
    //   2497: aload_0
    //   2498: ifnull -> 2509
    //   2501: aload_0
    //   2502: getfield g : Lb/e/b/i;
    //   2505: astore_0
    //   2506: goto -> 2511
    //   2509: aconst_null
    //   2510: astore_0
    //   2511: aload #23
    //   2513: aload #24
    //   2515: if_acmpeq -> 2543
    //   2518: aload #23
    //   2520: getfield G : [Lb/e/b/k/d;
    //   2523: iload_2
    //   2524: aaload
    //   2525: getfield d : Lb/e/b/k/d;
    //   2528: astore_0
    //   2529: aload_0
    //   2530: ifnull -> 2541
    //   2533: aload_0
    //   2534: getfield g : Lb/e/b/i;
    //   2537: astore_0
    //   2538: goto -> 2543
    //   2541: aconst_null
    //   2542: astore_0
    //   2543: aload #20
    //   2545: aload #24
    //   2547: if_acmpne -> 2569
    //   2550: aload #20
    //   2552: getfield G : [Lb/e/b/k/d;
    //   2555: astore #18
    //   2557: aload #18
    //   2559: iload_3
    //   2560: aaload
    //   2561: astore #17
    //   2563: aload #18
    //   2565: iload_2
    //   2566: aaload
    //   2567: astore #18
    //   2569: aload #4
    //   2571: ifnull -> 2633
    //   2574: aload_0
    //   2575: ifnull -> 2633
    //   2578: aload #17
    //   2580: invokevirtual a : ()I
    //   2583: istore_3
    //   2584: aload #24
    //   2586: ifnonnull -> 2596
    //   2589: aload #23
    //   2591: astore #19
    //   2593: goto -> 2600
    //   2596: aload #24
    //   2598: astore #19
    //   2600: aload #19
    //   2602: getfield G : [Lb/e/b/k/d;
    //   2605: iload_2
    //   2606: aaload
    //   2607: invokevirtual a : ()I
    //   2610: istore_2
    //   2611: aload_1
    //   2612: aload #17
    //   2614: getfield g : Lb/e/b/i;
    //   2617: aload #4
    //   2619: iload_3
    //   2620: ldc 0.5
    //   2622: aload_0
    //   2623: aload #18
    //   2625: getfield g : Lb/e/b/i;
    //   2628: iload_2
    //   2629: iconst_5
    //   2630: invokevirtual a : (Lb/e/b/i;Lb/e/b/i;IFLb/e/b/i;Lb/e/b/i;II)V
    //   2633: return
  }
}


/* Location:              /home/yc/Downloads/LeaveHomeSafe.jar!/b/e/b/k/b.class
 * Java compiler version: 6 (50.0)
 * JD-Core Version:       1.1.3
 */